Workbook

Sheet ResocontoWS
C1: ALEXANDRA | E1: ESTEFANY | G1: GIUDITTA | I1: NURA | K1: JOEL | M1: aa | O1: SANTO | P1: SARA | Q1: MASSI | R1: STAFF | S1: STAFF2 | T1: aa | U1: ANAHITA | V1: ANDREA | W1: CINZIA | X1: FERGIE | Y1: CARLOS | Z1: aa | AA1: aa | AB1: aa | AC1: aa
A2: DATA EVENTO | B2: DESCRIZIONE | C2: Sede | D2: Codice | E2: Sede | F2: Codice | G2: Sede | H2: Codice | I2: Sede | J2: Codice | K2: Sede | L2: Codice | M2: Sede | N2: Codice | O2: Codice | P2: Codice | Q2: Codice | R2: Codice | S2: Codice | T2: Codice | U2: Codice | V2: Codice | W2: Codice | X2: Codice | Y2: Codice | Z2: Codice | AA2: Codice | AB2: Codice | AC2: Codice | AD2: TOTALE Sede e Codice | AE2: Bonus Team Vendita
A3: 45949 | B3: WS_BANANA | C3: =COUNTIF(INDIRECT("'"&$B3&"'!$B:$B"),"*"&C$1&"*")- COUNTIFS(INDIRECT("'"&$B3&"'!$B:$B"),"*"&C$1&"*",INDIRECT("'"&$B3&"'!$L:$L"),"*") -> 1 | D3: =COUNTIF(INDIRECT("'"&$B3&"'!$L:$L"),"*"&C$1&"*") -> 4 | E3: =COUNTIF(INDIRECT("'"&$B3&"'!$B:$B"),"*"&E$1&"*")- COUNTIFS(INDIRECT("'"&$B3&"'!$B:$B"),"*"&E$1&"*",INDIRECT("'"&$B3&"'!$L:$L"),"*") -> 0 | F3: =COUNTIF(INDIRECT("'"&$B3&"'!$L:$L"),"*"&E$1&"*") -> 4 | G3: =COUNTIF(INDIRECT("'"&$B3&"'!$B:$B"),"*"&G$1&"*")- COUNTIFS(INDIRECT("'"&$B3&"'!$B:$B"),"*"&G$1&"*",INDIRECT("'"&$B3&"'!$L:$L"),"*") -> 0 | H3: =COUNTIF(INDIRECT("'"&$B3&"'!$L:$L"),"*"&G$1&"*") -> 0 | I3: =COUNTIF(INDIRECT("'"&$B3&"'!$B:$B"),"*"&I$1&"*")- COUNTIFS(INDIRECT("'"&$B3&"'!$B:$B"),"*"&I$1&"*",INDIRECT("'"&$B3&"'!$L:$L"),"*") -> 1 | J3: =COUNTIF(INDIRECT("'"&$B3&"'!$L:$L"),"*"&I$1&"*") -> 8 | K3: =COUNTIF(INDIRECT("'"&$B3&"'!$B:$B"),"*"&K$1&"*")- COUNTIFS(INDIRECT("'"&$B3&"'!$B:$B"),"*"&K$1&"*",INDIRECT("'"&$B3&"'!$L:$L"),"*") -> 0 | L3: =COUNTIF(INDIRECT("'"&$B3&"'!$L:$L"),"*"&K$1&"*") -> 0 | M3: =COUNTIF(INDIRECT("'"&$B3&"'!$B:$B"),"*"&M$1&"*")- COUNTIFS(INDIRECT("'"&$B3&"'!$B:$B"),"*"&M$1&"*",INDIRECT("'"&$B3&"'!$L:$L"),"*") -> 0 | N3: =COUNTIF(INDIRECT("'"&$B3&"'!$L:$L"),"*"&M$1&"*") -> 0 | O3: =COUNTIF(INDIRECT("'"&$B3&"'!$L:$L"),"*"&O$1&"*") -> 0 | P3: =COUNTIF(INDIRECT("'"&$B3&"'!$L:$L"),"*"&P$1&"*") -> 1 | Q3: =COUNTIF(INDIRECT("'"&$B3&"'!$L:$L"),"*"&Q$1&"*") -> 0 | R3: =COUNTIF(INDIRECT("'"&$B3&"'!$L:$L"),"*"&R$1&"*") -> 0 | S3: =COUNTIF(INDIRECT("'"&$B3&"'!$L:$L"),"*"&S$1&"*") -> 0 | T3: =COUNTIF(INDIRECT("'"&$B3&"'!$L:$L"),"*"&T$1&"*") -> 0 | U3: =COUNTIF(INDIRECT("'"&$B3&"'!$L:$L"),"*"&U$1&"*") -> 0 | V3: =COUNTIF(INDIRECT("'"&$B3&"'!$L:$L"),"*"&V$1&"*") -> 0 | ... AC3: =COUNTIF(INDIRECT("'"&$B3&"'!$L:$L"),"*"&AC$1&"*") -> 0 | AD3: =SUM(C3:AC3) -> 19 | AE3: =AD3*1 -> 19
A4: 45956 | B4: WS_TIMOR | C4: =COUNTIF(INDIRECT("'"&$B4&"'!$B:$B"),"*"&C$1&"*")- COUNTIFS(INDIRECT("'"&$B4&"'!$B:$B"),"*"&C$1&"*",INDIRECT("'"&$B4&"'!$L:$L"),"*") -> 3 | D4: =COUNTIF(INDIRECT("'"&$B4&"'!$L:$L"),"*"&C$1&"*") -> 2 | E4: =COUNTIF(INDIRECT("'"&$B4&"'!$B:$B"),"*"&E$1&"*")- COUNTIFS(INDIRECT("'"&$B4&"'!$B:$B"),"*"&E$1&"*",INDIRECT("'"&$B4&"'!$L:$L"),"*") -> 0 | F4: =COUNTIF(INDIRECT("'"&$B4&"'!$L:$L"),"*"&E$1&"*") -> 5 | G4: =COUNTIF(INDIRECT("'"&$B4&"'!$B:$B"),"*"&G$1&"*")- COUNTIFS(INDIRECT("'"&$B4&"'!$B:$B"),"*"&G$1&"*",INDIRECT("'"&$B4&"'!$L:$L"),"*") -> 0 | H4: =COUNTIF(INDIRECT("'"&$B4&"'!$L:$L"),"*"&G$1&"*") -> 2 | I4: =COUNTIF(INDIRECT("'"&$B4&"'!$B:$B"),"*"&I$1&"*")- COUNTIFS(INDIRECT("'"&$B4&"'!$B:$B"),"*"&I$1&"*",INDIRECT("'"&$B4&"'!$L:$L"),"*") -> 0 | J4: =COUNTIF(INDIRECT("'"&$B4&"'!$L:$L"),"*"&I$1&"*") -> 4 | K4: =COUNTIF(INDIRECT("'"&$B4&"'!$B:$B"),"*"&K$1&"*")- COUNTIFS(INDIRECT("'"&$B4&"'!$B:$B"),"*"&K$1&"*",INDIRECT("'"&$B4&"'!$L:$L"),"*") -> 0 | L4: =COUNTIF(INDIRECT("'"&$B4&"'!$L:$L"),"*"&K$1&"*") -> 0 | M4: =COUNTIF(INDIRECT("'"&$B4&"'!$B:$B"),"*"&M$1&"*")- COUNTIFS(INDIRECT("'"&$B4&"'!$B:$B"),"*"&M$1&"*",INDIRECT("'"&$B4&"'!$L:$L"),"*") -> 0 | N4: =COUNTIF(INDIRECT("'"&$B4&"'!$L:$L"),"*"&M$1&"*") -> 0 | O4: =COUNTIF(INDIRECT("'"&$B4&"'!$L:$L"),"*"&O$1&"*") -> 0 | P4: =COUNTIF(INDIRECT("'"&$B4&"'!$L:$L"),"*"&P$1&"*") -> 2 | Q4: =COUNTIF(INDIRECT("'"&$B4&"'!$L:$L"),"*"&Q$1&"*") -> 0 | R4: =COUNTIF(INDIRECT("'"&$B4&"'!$L:$L"),"*"&R$1&"*") -> 0 | S4: =COUNTIF(INDIRECT("'"&$B4&"'!$L:$L"),"*"&S$1&"*") -> 0 | T4: =COUNTIF(INDIRECT("'"&$B4&"'!$L:$L"),"*"&T$1&"*") -> 0 | U4: =COUNTIF(INDIRECT("'"&$B4&"'!$L:$L"),"*"&U$1&"*") -> 0 | V4: =COUNTIF(INDIRECT("'"&$B4&"'!$L:$L"),"*"&V$1&"*") -> 0 | ... AC4: =COUNTIF(INDIRECT("'"&$B4&"'!$L:$L"),"*"&AC$1&"*") -> 0 | AD4: =SUM(C4:AC4) -> 18 | AE4: =AD4*1 -> 18
A5: 45956 | B5: WS_LULU | C5: =COUNTIF(INDIRECT("'"&$B5&"'!$B:$B"),"*"&C$1&"*")- COUNTIFS(INDIRECT("'"&$B5&"'!$B:$B"),"*"&C$1&"*",INDIRECT("'"&$B5&"'!$L:$L"),"*") -> 0 | D5: =COUNTIF(INDIRECT("'"&$B5&"'!$L:$L"),"*"&C$1&"*") -> 1 | E5: =COUNTIF(INDIRECT("'"&$B5&"'!$B:$B"),"*"&E$1&"*")- COUNTIFS(INDIRECT("'"&$B5&"'!$B:$B"),"*"&E$1&"*",INDIRECT("'"&$B5&"'!$L:$L"),"*") -> 0 | F5: =COUNTIF(INDIRECT("'"&$B5&"'!$L:$L"),"*"&E$1&"*") -> 4 | G5: =COUNTIF(INDIRECT("'"&$B5&"'!$B:$B"),"*"&G$1&"*")- COUNTIFS(INDIRECT("'"&$B5&"'!$B:$B"),"*"&G$1&"*",INDIRECT("'"&$B5&"'!$L:$L"),"*") -> 0 | H5: =COUNTIF(INDIRECT("'"&$B5&"'!$L:$L"),"*"&G$1&"*") -> 0 | I5: =COUNTIF(INDIRECT("'"&$B5&"'!$B:$B"),"*"&I$1&"*")- COUNTIFS(INDIRECT("'"&$B5&"'!$B:$B"),"*"&I$1&"*",INDIRECT("'"&$B5&"'!$L:$L"),"*") -> 0 | J5: =COUNTIF(INDIRECT("'"&$B5&"'!$L:$L"),"*"&I$1&"*") -> 3 | K5: =COUNTIF(INDIRECT("'"&$B5&"'!$B:$B"),"*"&K$1&"*")- COUNTIFS(INDIRECT("'"&$B5&"'!$B:$B"),"*"&K$1&"*",INDIRECT("'"&$B5&"'!$L:$L"),"*") -> 0 | L5: =COUNTIF(INDIRECT("'"&$B5&"'!$L:$L"),"*"&K$1&"*") -> 4 | M5: =COUNTIF(INDIRECT("'"&$B5&"'!$B:$B"),"*"&M$1&"*")- COUNTIFS(INDIRECT("'"&$B5&"'!$B:$B"),"*"&M$1&"*",INDIRECT("'"&$B5&"'!$L:$L"),"*") -> 0 | N5: =COUNTIF(INDIRECT("'"&$B5&"'!$L:$L"),"*"&M$1&"*") -> 0 | O5: =COUNTIF(INDIRECT("'"&$B5&"'!$L:$L"),"*"&O$1&"*") -> 0 | P5: =COUNTIF(INDIRECT("'"&$B5&"'!$L:$L"),"*"&P$1&"*") -> 0 | Q5: =COUNTIF(INDIRECT("'"&$B5&"'!$L:$L"),"*"&Q$1&"*") -> 0 | R5: =COUNTIF(INDIRECT("'"&$B5&"'!$L:$L"),"*"&R$1&"*") -> 0 | S5: =COUNTIF(INDIRECT("'"&$B5&"'!$L:$L"),"*"&S$1&"*") -> 0 | T5: =COUNTIF(INDIRECT("'"&$B5&"'!$L:$L"),"*"&T$1&"*") -> 0 | U5: =COUNTIF(INDIRECT("'"&$B5&"'!$L:$L"),"*"&U$1&"*") -> 0 | V5: =COUNTIF(INDIRECT("'"&$B5&"'!$L:$L"),"*"&V$1&"*") -> 0 | ... AC5: =COUNTIF(INDIRECT("'"&$B5&"'!$L:$L"),"*"&AC$1&"*") -> 0 | AD5: =SUM(C5:AC5) -> 12 | AE5: =AD5*1 -> 12
A6: 45970 | B6: WS_KUMO | C6: =COUNTIF(INDIRECT("'"&$B6&"'!$B:$B"),"*"&C$1&"*")- COUNTIFS(INDIRECT("'"&$B6&"'!$B:$B"),"*"&C$1&"*",INDIRECT("'"&$B6&"'!$L:$L"),"*") -> 0 | D6: =COUNTIF(INDIRECT("'"&$B6&"'!$L:$L"),"*"&C$1&"*") -> 1 | E6: =COUNTIF(INDIRECT("'"&$B6&"'!$B:$B"),"*"&E$1&"*")- COUNTIFS(INDIRECT("'"&$B6&"'!$B:$B"),"*"&E$1&"*",INDIRECT("'"&$B6&"'!$L:$L"),"*") -> 0 | F6: =COUNTIF(INDIRECT("'"&$B6&"'!$L:$L"),"*"&E$1&"*") -> 2 | G6: =COUNTIF(INDIRECT("'"&$B6&"'!$B:$B"),"*"&G$1&"*")- COUNTIFS(INDIRECT("'"&$B6&"'!$B:$B"),"*"&G$1&"*",INDIRECT("'"&$B6&"'!$L:$L"),"*") -> 0 | H6: =COUNTIF(INDIRECT("'"&$B6&"'!$L:$L"),"*"&G$1&"*") -> 0 | I6: =COUNTIF(INDIRECT("'"&$B6&"'!$B:$B"),"*"&I$1&"*")- COUNTIFS(INDIRECT("'"&$B6&"'!$B:$B"),"*"&I$1&"*",INDIRECT("'"&$B6&"'!$L:$L"),"*") -> 2 | J6: =COUNTIF(INDIRECT("'"&$B6&"'!$L:$L"),"*"&I$1&"*") -> 4 | K6: =COUNTIF(INDIRECT("'"&$B6&"'!$B:$B"),"*"&K$1&"*")- COUNTIFS(INDIRECT("'"&$B6&"'!$B:$B"),"*"&K$1&"*",INDIRECT("'"&$B6&"'!$L:$L"),"*") -> 0 | L6: =COUNTIF(INDIRECT("'"&$B6&"'!$L:$L"),"*"&K$1&"*") -> 1 | M6: =COUNTIF(INDIRECT("'"&$B6&"'!$B:$B"),"*"&M$1&"*")- COUNTIFS(INDIRECT("'"&$B6&"'!$B:$B"),"*"&M$1&"*",INDIRECT("'"&$B6&"'!$L:$L"),"*") -> 0 | N6: =COUNTIF(INDIRECT("'"&$B6&"'!$L:$L"),"*"&M$1&"*") -> 0 | O6: =COUNTIF(INDIRECT("'"&$B6&"'!$L:$L"),"*"&O$1&"*") -> 0 | P6: =COUNTIF(INDIRECT("'"&$B6&"'!$L:$L"),"*"&P$1&"*") -> 1 | Q6: =COUNTIF(INDIRECT("'"&$B6&"'!$L:$L"),"*"&Q$1&"*") -> 0 | R6: =COUNTIF(INDIRECT("'"&$B6&"'!$L:$L"),"*"&R$1&"*") -> 0 | S6: =COUNTIF(INDIRECT("'"&$B6&"'!$L:$L"),"*"&S$1&"*") -> 0 | T6: =COUNTIF(INDIRECT("'"&$B6&"'!$L:$L"),"*"&T$1&"*") -> 0 | U6: =COUNTIF(INDIRECT("'"&$B6&"'!$L:$L"),"*"&U$1&"*") -> 0 | V6: =COUNTIF(INDIRECT("'"&$B6&"'!$L:$L"),"*"&V$1&"*") -> 0 | ... AC6: =COUNTIF(INDIRECT("'"&$B6&"'!$L:$L"),"*"&AC$1&"*") -> 0 | AD6: =SUM(C6:AC6) -> 11 | AE6: =AD6*1 -> 11
A7: 45970 | B7: WS_LELI | C7: =COUNTIF(INDIRECT("'"&$B7&"'!$B:$B"),"*"&C$1&"*")- COUNTIFS(INDIRECT("'"&$B7&"'!$B:$B"),"*"&C$1&"*",INDIRECT("'"&$B7&"'!$L:$L"),"*") -> 0 | D7: =COUNTIF(INDIRECT("'"&$B7&"'!$L:$L"),"*"&C$1&"*") -> 2 | E7: =COUNTIF(INDIRECT("'"&$B7&"'!$B:$B"),"*"&E$1&"*")- COUNTIFS(INDIRECT("'"&$B7&"'!$B:$B"),"*"&E$1&"*",INDIRECT("'"&$B7&"'!$L:$L"),"*") -> 0 | F7: =COUNTIF(INDIRECT("'"&$B7&"'!$L:$L"),"*"&E$1&"*") -> 1 | G7: =COUNTIF(INDIRECT("'"&$B7&"'!$B:$B"),"*"&G$1&"*")- COUNTIFS(INDIRECT("'"&$B7&"'!$B:$B"),"*"&G$1&"*",INDIRECT("'"&$B7&"'!$L:$L"),"*") -> 0 | H7: =COUNTIF(INDIRECT("'"&$B7&"'!$L:$L"),"*"&G$1&"*") -> 0 | I7: =COUNTIF(INDIRECT("'"&$B7&"'!$B:$B"),"*"&I$1&"*")- COUNTIFS(INDIRECT("'"&$B7&"'!$B:$B"),"*"&I$1&"*",INDIRECT("'"&$B7&"'!$L:$L"),"*") -> 1 | J7: =COUNTIF(INDIRECT("'"&$B7&"'!$L:$L"),"*"&I$1&"*") -> 0 | K7: =COUNTIF(INDIRECT("'"&$B7&"'!$B:$B"),"*"&K$1&"*")- COUNTIFS(INDIRECT("'"&$B7&"'!$B:$B"),"*"&K$1&"*",INDIRECT("'"&$B7&"'!$L:$L"),"*") -> 0 | L7: =COUNTIF(INDIRECT("'"&$B7&"'!$L:$L"),"*"&K$1&"*") -> 1 | M7: =COUNTIF(INDIRECT("'"&$B7&"'!$B:$B"),"*"&M$1&"*")- COUNTIFS(INDIRECT("'"&$B7&"'!$B:$B"),"*"&M$1&"*",INDIRECT("'"&$B7&"'!$L:$L"),"*") -> 0 | N7: =COUNTIF(INDIRECT("'"&$B7&"'!$L:$L"),"*"&M$1&"*") -> 0 | O7: =COUNTIF(INDIRECT("'"&$B7&"'!$L:$L"),"*"&O$1&"*") -> 0 | P7: =COUNTIF(INDIRECT("'"&$B7&"'!$L:$L"),"*"&P$1&"*") -> 0 | Q7: =COUNTIF(INDIRECT("'"&$B7&"'!$L:$L"),"*"&Q$1&"*") -> 0 | R7: =COUNTIF(INDIRECT("'"&$B7&"'!$L:$L"),"*"&R$1&"*") -> 0 | S7: =COUNTIF(INDIRECT("'"&$B7&"'!$L:$L"),"*"&S$1&"*") -> 0 | T7: =COUNTIF(INDIRECT("'"&$B7&"'!$L:$L"),"*"&T$1&"*") -> 0 | U7: =COUNTIF(INDIRECT("'"&$B7&"'!$L:$L"),"*"&U$1&"*") -> 0 | V7: =COUNTIF(INDIRECT("'"&$B7&"'!$L:$L"),"*"&V$1&"*") -> 0 | ... AC7: =COUNTIF(INDIRECT("'"&$B7&"'!$L:$L"),"*"&AC$1&"*") -> 0 | AD7: =SUM(C7:AC7) -> 5 | AE7: =AD7*1 -> 5
A8: 45977 | B8: WS_DEBORAHESPOSITO | C8: =COUNTIF(INDIRECT("'"&$B8&"'!$B:$B"),"*"&C$1&"*")- COUNTIFS(INDIRECT("'"&$B8&"'!$B:$B"),"*"&C$1&"*",INDIRECT("'"&$B8&"'!$L:$L"),"*") -> 0 | D8: =COUNTIF(INDIRECT("'"&$B8&"'!$L:$L"),"*"&C$1&"*") -> 6 | E8: =COUNTIF(INDIRECT("'"&$B8&"'!$B:$B"),"*"&E$1&"*")- COUNTIFS(INDIRECT("'"&$B8&"'!$B:$B"),"*"&E$1&"*",INDIRECT("'"&$B8&"'!$L:$L"),"*") -> 0 | F8: =COUNTIF(INDIRECT("'"&$B8&"'!$L:$L"),"*"&E$1&"*") -> 4 | G8: =COUNTIF(INDIRECT("'"&$B8&"'!$B:$B"),"*"&G$1&"*")- COUNTIFS(INDIRECT("'"&$B8&"'!$B:$B"),"*"&G$1&"*",INDIRECT("'"&$B8&"'!$L:$L"),"*") -> 0 | H8: =COUNTIF(INDIRECT("'"&$B8&"'!$L:$L"),"*"&G$1&"*") -> 0 | I8: =COUNTIF(INDIRECT("'"&$B8&"'!$B:$B"),"*"&I$1&"*")- COUNTIFS(INDIRECT("'"&$B8&"'!$B:$B"),"*"&I$1&"*",INDIRECT("'"&$B8&"'!$L:$L"),"*") -> 4 | J8: =COUNTIF(INDIRECT("'"&$B8&"'!$L:$L"),"*"&I$1&"*") -> 5 | K8: =COUNTIF(INDIRECT("'"&$B8&"'!$B:$B"),"*"&K$1&"*")- COUNTIFS(INDIRECT("'"&$B8&"'!$B:$B"),"*"&K$1&"*",INDIRECT("'"&$B8&"'!$L:$L"),"*") -> 0 | L8: =COUNTIF(INDIRECT("'"&$B8&"'!$L:$L"),"*"&K$1&"*") -> 1 | M8: =COUNTIF(INDIRECT("'"&$B8&"'!$B:$B"),"*"&M$1&"*")- COUNTIFS(INDIRECT("'"&$B8&"'!$B:$B"),"*"&M$1&"*",INDIRECT("'"&$B8&"'!$L:$L"),"*") -> 0 | N8: =COUNTIF(INDIRECT("'"&$B8&"'!$L:$L"),"*"&M$1&"*") -> 0 | O8: =COUNTIF(INDIRECT("'"&$B8&"'!$L:$L"),"*"&O$1&"*") -> 0 | P8: =COUNTIF(INDIRECT("'"&$B8&"'!$L:$L"),"*"&P$1&"*") -> 1 | Q8: =COUNTIF(INDIRECT("'"&$B8&"'!$L:$L"),"*"&Q$1&"*") -> 0 | R8: =COUNTIF(INDIRECT("'"&$B8&"'!$L:$L"),"*"&R$1&"*") -> 0 | S8: =COUNTIF(INDIRECT("'"&$B8&"'!$L:$L"),"*"&S$1&"*") -> 0 | T8: =COUNTIF(INDIRECT("'"&$B8&"'!$L:$L"),"*"&T$1&"*") -> 0 | U8: =COUNTIF(INDIRECT("'"&$B8&"'!$L:$L"),"*"&U$1&"*") -> 0 | V8: =COUNTIF(INDIRECT("'"&$B8&"'!$L:$L"),"*"&V$1&"*") -> 0 | ... AC8: =COUNTIF(INDIRECT("'"&$B8&"'!$L:$L"),"*"&AC$1&"*") -> 0 | AD8: =SUM(C8:AC8) -> 21 | AE8: =AD8*1 -> 21
A9: 45977 | B9: WS_DEANGELIS | C9: =COUNTIF(INDIRECT("'"&$B9&"'!$B:$B"),"*"&C$1&"*")- COUNTIFS(INDIRECT("'"&$B9&"'!$B:$B"),"*"&C$1&"*",INDIRECT("'"&$B9&"'!$L:$L"),"*") -> 0 | D9: =COUNTIF(INDIRECT("'"&$B9&"'!$L:$L"),"*"&C$1&"*") -> 0 | E9: =COUNTIF(INDIRECT("'"&$B9&"'!$B:$B"),"*"&E$1&"*")- COUNTIFS(INDIRECT("'"&$B9&"'!$B:$B"),"*"&E$1&"*",INDIRECT("'"&$B9&"'!$L:$L"),"*") -> 0 | F9: =COUNTIF(INDIRECT("'"&$B9&"'!$L:$L"),"*"&E$1&"*") -> 1 | G9: =COUNTIF(INDIRECT("'"&$B9&"'!$B:$B"),"*"&G$1&"*")- COUNTIFS(INDIRECT("'"&$B9&"'!$B:$B"),"*"&G$1&"*",INDIRECT("'"&$B9&"'!$L:$L"),"*") -> 0 | H9: =COUNTIF(INDIRECT("'"&$B9&"'!$L:$L"),"*"&G$1&"*") -> 1 | I9: =COUNTIF(INDIRECT("'"&$B9&"'!$B:$B"),"*"&I$1&"*")- COUNTIFS(INDIRECT("'"&$B9&"'!$B:$B"),"*"&I$1&"*",INDIRECT("'"&$B9&"'!$L:$L"),"*") -> 4 | J9: =COUNTIF(INDIRECT("'"&$B9&"'!$L:$L"),"*"&I$1&"*") -> 2 | K9: =COUNTIF(INDIRECT("'"&$B9&"'!$B:$B"),"*"&K$1&"*")- COUNTIFS(INDIRECT("'"&$B9&"'!$B:$B"),"*"&K$1&"*",INDIRECT("'"&$B9&"'!$L:$L"),"*") -> 0 | L9: =COUNTIF(INDIRECT("'"&$B9&"'!$L:$L"),"*"&K$1&"*") -> 1 | M9: =COUNTIF(INDIRECT("'"&$B9&"'!$B:$B"),"*"&M$1&"*")- COUNTIFS(INDIRECT("'"&$B9&"'!$B:$B"),"*"&M$1&"*",INDIRECT("'"&$B9&"'!$L:$L"),"*") -> 0 | N9: =COUNTIF(INDIRECT("'"&$B9&"'!$L:$L"),"*"&M$1&"*") -> 0 | O9: =COUNTIF(INDIRECT("'"&$B9&"'!$L:$L"),"*"&O$1&"*") -> 0 | P9: =COUNTIF(INDIRECT("'"&$B9&"'!$L:$L"),"*"&P$1&"*") -> 0 | Q9: =COUNTIF(INDIRECT("'"&$B9&"'!$L:$L"),"*"&Q$1&"*") -> 1 | R9: =COUNTIF(INDIRECT("'"&$B9&"'!$L:$L"),"*"&R$1&"*") -> 0 | S9: =COUNTIF(INDIRECT("'"&$B9&"'!$L:$L"),"*"&S$1&"*") -> 0 | T9: =COUNTIF(INDIRECT("'"&$B9&"'!$L:$L"),"*"&T$1&"*") -> 0 | U9: =COUNTIF(INDIRECT("'"&$B9&"'!$L:$L"),"*"&U$1&"*") -> 0 | V9: =COUNTIF(INDIRECT("'"&$B9&"'!$L:$L"),"*"&V$1&"*") -> 0 | ... AC9: =COUNTIF(INDIRECT("'"&$B9&"'!$L:$L"),"*"&AC$1&"*") -> 0 | AD9: =SUM(C9:AC9) -> 10 | AE9: =AD9*1 -> 10
A10: 46005 | B10: WS_NEREA | C10: =COUNTIF(INDIRECT("'"&$B10&"'!$B:$B"),"*"&C$1&"*")- COUNTIFS(INDIRECT("'"&$B10&"'!$B:$B"),"*"&C$1&"*",INDIRECT("'"&$B10&"'!$L:$L"),"*") -> 0 | D10: =COUNTIF(INDIRECT("'"&$B10&"'!$L:$L"),"*"&C$1&"*") -> 1 | E10: =COUNTIF(INDIRECT("'"&$B10&"'!$B:$B"),"*"&E$1&"*")- COUNTIFS(INDIRECT("'"&$B10&"'!$B:$B"),"*"&E$1&"*",INDIRECT("'"&$B10&"'!$L:$L"),"*") -> 0 | F10: =COUNTIF(INDIRECT("'"&$B10&"'!$L:$L"),"*"&E$1&"*") -> 1 | G10: =COUNTIF(INDIRECT("'"&$B10&"'!$B:$B"),"*"&G$1&"*")- COUNTIFS(INDIRECT("'"&$B10&"'!$B:$B"),"*"&G$1&"*",INDIRECT("'"&$B10&"'!$L:$L"),"*") -> 0 | H10: =COUNTIF(INDIRECT("'"&$B10&"'!$L:$L"),"*"&G$1&"*") -> 1 | I10: =COUNTIF(INDIRECT("'"&$B10&"'!$B:$B"),"*"&I$1&"*")- COUNTIFS(INDIRECT("'"&$B10&"'!$B:$B"),"*"&I$1&"*",INDIRECT("'"&$B10&"'!$L:$L"),"*") -> 0 | J10: =COUNTIF(INDIRECT("'"&$B10&"'!$L:$L"),"*"&I$1&"*") -> 4 | K10: =COUNTIF(INDIRECT("'"&$B10&"'!$B:$B"),"*"&K$1&"*")- COUNTIFS(INDIRECT("'"&$B10&"'!$B:$B"),"*"&K$1&"*",INDIRECT("'"&$B10&"'!$L:$L"),"*") -> 0 | L10: =COUNTIF(INDIRECT("'"&$B10&"'!$L:$L"),"*"&K$1&"*") -> 0 | M10: =COUNTIF(INDIRECT("'"&$B10&"'!$B:$B"),"*"&M$1&"*")- COUNTIFS(INDIRECT("'"&$B10&"'!$B:$B"),"*"&M$1&"*",INDIRECT("'"&$B10&"'!$L:$L"),"*") -> 0 | N10: =COUNTIF(INDIRECT("'"&$B10&"'!$L:$L"),"*"&M$1&"*") -> 0 | O10: =COUNTIF(INDIRECT("'"&$B10&"'!$L:$L"),"*"&O$1&"*") -> 0 | P10: =COUNTIF(INDIRECT("'"&$B10&"'!$L:$L"),"*"&P$1&"*") -> 0 | Q10: =COUNTIF(INDIRECT("'"&$B10&"'!$L:$L"),"*"&Q$1&"*") -> 1 | R10: =COUNTIF(INDIRECT("'"&$B10&"'!$L:$L"),"*"&R$1&"*") -> 0 | S10: =COUNTIF(INDIRECT("'"&$B10&"'!$L:$L"),"*"&S$1&"*") -> 0 | T10: =COUNTIF(INDIRECT("'"&$B10&"'!$L:$L"),"*"&T$1&"*") -> 0 | U10: =COUNTIF(INDIRECT("'"&$B10&"'!$L:$L"),"*"&U$1&"*") -> 0 | V10: =COUNTIF(INDIRECT("'"&$B10&"'!$L:$L"),"*"&V$1&"*") -> 0 | ... AC10: =COUNTIF(INDIRECT("'"&$B10&"'!$L:$L"),"*"&AC$1&"*") -> 0 | AD10: =SUM(C10:AC10) -> 8 | AE10: =AD10*1 -> 8
A11: 46005 | B11: WS_FESTA NATALE | C11: =COUNTIF(INDIRECT("'"&$B11&"'!$B:$B"),"*"&C$1&"*")- COUNTIFS(INDIRECT("'"&$B11&"'!$B:$B"),"*"&C$1&"*",INDIRECT("'"&$B11&"'!$L:$L"),"*") -> 0 | D11: =COUNTIF(INDIRECT("'"&$B11&"'!$L:$L"),"*"&C$1&"*") -> 10 | E11: =COUNTIF(INDIRECT("'"&$B11&"'!$B:$B"),"*"&E$1&"*")- COUNTIFS(INDIRECT("'"&$B11&"'!$B:$B"),"*"&E$1&"*",INDIRECT("'"&$B11&"'!$L:$L"),"*") -> 2 | F11: =COUNTIF(INDIRECT("'"&$B11&"'!$L:$L"),"*"&E$1&"*") -> 6 | G11: =COUNTIF(INDIRECT("'"&$B11&"'!$B:$B"),"*"&G$1&"*")- COUNTIFS(INDIRECT("'"&$B11&"'!$B:$B"),"*"&G$1&"*",INDIRECT("'"&$B11&"'!$L:$L"),"*") -> 0 | H11: =COUNTIF(INDIRECT("'"&$B11&"'!$L:$L"),"*"&G$1&"*") -> 8 | I11: =COUNTIF(INDIRECT("'"&$B11&"'!$B:$B"),"*"&I$1&"*")- COUNTIFS(INDIRECT("'"&$B11&"'!$B:$B"),"*"&I$1&"*",INDIRECT("'"&$B11&"'!$L:$L"),"*") -> 0 | J11: =COUNTIF(INDIRECT("'"&$B11&"'!$L:$L"),"*"&I$1&"*") -> 23 | K11: =COUNTIF(INDIRECT("'"&$B11&"'!$B:$B"),"*"&K$1&"*")- COUNTIFS(INDIRECT("'"&$B11&"'!$B:$B"),"*"&K$1&"*",INDIRECT("'"&$B11&"'!$L:$L"),"*") -> 0 | L11: =COUNTIF(INDIRECT("'"&$B11&"'!$L:$L"),"*"&K$1&"*") -> 7 | M11: =COUNTIF(INDIRECT("'"&$B11&"'!$B:$B"),"*"&M$1&"*")- COUNTIFS(INDIRECT("'"&$B11&"'!$B:$B"),"*"&M$1&"*",INDIRECT("'"&$B11&"'!$L:$L"),"*") -> 0 | N11: =COUNTIF(INDIRECT("'"&$B11&"'!$L:$L"),"*"&M$1&"*") -> 0 | O11: =COUNTIF(INDIRECT("'"&$B11&"'!$L:$L"),"*"&O$1&"*") -> 49 | P11: =COUNTIF(INDIRECT("'"&$B11&"'!$L:$L"),"*"&P$1&"*") -> 0 | Q11: =COUNTIF(INDIRECT("'"&$B11&"'!$L:$L"),"*"&Q$1&"*") -> 0 | R11: =COUNTIF(INDIRECT("'"&$B11&"'!$L:$L"),"*"&R$1&"*") -> 0 | S11: =COUNTIF(INDIRECT("'"&$B11&"'!$L:$L"),"*"&S$1&"*") -> 0 | T11: =COUNTIF(INDIRECT("'"&$B11&"'!$L:$L"),"*"&T$1&"*") -> 0 | U11: =COUNTIF(INDIRECT("'"&$B11&"'!$L:$L"),"*"&U$1&"*") -> 0 | V11: =COUNTIF(INDIRECT("'"&$B11&"'!$L:$L"),"*"&V$1&"*") -> 0 | ... AC11: =COUNTIF(INDIRECT("'"&$B11&"'!$L:$L"),"*"&AC$1&"*") -> 0 | AD11: =SUM(C11:AC11) -> 105 | AE11: =AD11*1 -> 105
A12: 46005 | B12: SOLO SERATA_FESTA NATALE | C12: =COUNTIF(INDIRECT("'"&$B12&"'!$B:$B"),"*"&C$1&"*")- COUNTIFS(INDIRECT("'"&$B12&"'!$B:$B"),"*"&C$1&"*",INDIRECT("'"&$B12&"'!$L:$L"),"*") -> 1 | D12: =COUNTIF(INDIRECT("'"&$B12&"'!$L:$L"),"*"&C$1&"*") -> 31 | E12: =COUNTIF(INDIRECT("'"&$B12&"'!$B:$B"),"*"&E$1&"*")- COUNTIFS(INDIRECT("'"&$B12&"'!$B:$B"),"*"&E$1&"*",INDIRECT("'"&$B12&"'!$L:$L"),"*") -> 3 | F12: =COUNTIF(INDIRECT("'"&$B12&"'!$L:$L"),"*"&E$1&"*") -> 14 | G12: =COUNTIF(INDIRECT("'"&$B12&"'!$B:$B"),"*"&G$1&"*")- COUNTIFS(INDIRECT("'"&$B12&"'!$B:$B"),"*"&G$1&"*",INDIRECT("'"&$B12&"'!$L:$L"),"*") -> 0 | H12: =COUNTIF(INDIRECT("'"&$B12&"'!$L:$L"),"*"&G$1&"*") -> 18 | I12: =COUNTIF(INDIRECT("'"&$B12&"'!$B:$B"),"*"&I$1&"*")- COUNTIFS(INDIRECT("'"&$B12&"'!$B:$B"),"*"&I$1&"*",INDIRECT("'"&$B12&"'!$L:$L"),"*") -> 0 | J12: =COUNTIF(INDIRECT("'"&$B12&"'!$L:$L"),"*"&I$1&"*") -> 22 | K12: =COUNTIF(INDIRECT("'"&$B12&"'!$B:$B"),"*"&K$1&"*")- COUNTIFS(INDIRECT("'"&$B12&"'!$B:$B"),"*"&K$1&"*",INDIRECT("'"&$B12&"'!$L:$L"),"*") -> 1 | L12: =COUNTIF(INDIRECT("'"&$B12&"'!$L:$L"),"*"&K$1&"*") -> 11 | M12: =COUNTIF(INDIRECT("'"&$B12&"'!$B:$B"),"*"&M$1&"*")- COUNTIFS(INDIRECT("'"&$B12&"'!$B:$B"),"*"&M$1&"*",INDIRECT("'"&$B12&"'!$L:$L"),"*") -> 0 | N12: =COUNTIF(INDIRECT("'"&$B12&"'!$L:$L"),"*"&M$1&"*") -> 0 | O12: =COUNTIF(INDIRECT("'"&$B12&"'!$L:$L"),"*"&O$1&"*") -> 51 | P12: =COUNTIF(INDIRECT("'"&$B12&"'!$L:$L"),"*"&P$1&"*") -> 0 | Q12: =COUNTIF(INDIRECT("'"&$B12&"'!$L:$L"),"*"&Q$1&"*") -> 2 | R12: =COUNTIF(INDIRECT("'"&$B12&"'!$L:$L"),"*"&R$1&"*") -> 0 | S12: =COUNTIF(INDIRECT("'"&$B12&"'!$L:$L"),"*"&S$1&"*") -> 0 | T12: =COUNTIF(INDIRECT("'"&$B12&"'!$L:$L"),"*"&T$1&"*") -> 0 | U12: =COUNTIF(INDIRECT("'"&$B12&"'!$L:$L"),"*"&U$1&"*") -> 0 | V12: =COUNTIF(INDIRECT("'"&$B12&"'!$L:$L"),"*"&V$1&"*") -> 0 | ... AC12: =COUNTIF(INDIRECT("'"&$B12&"'!$L:$L"),"*"&AC$1&"*") -> 0 | AD12: =SUM(C12:AC12) -> 154 | AE12: =AD12*1 -> 154
A13: 46054 | B13: WS_ALESSIOCAVALIERE | C13: =COUNTIF(INDIRECT("'"&$B13&"'!$B:$B"),"*"&C$1&"*")- COUNTIFS(INDIRECT("'"&$B13&"'!$B:$B"),"*"&C$1&"*",INDIRECT("'"&$B13&"'!$L:$L"),"*") -> 0 | D13: =COUNTIF(INDIRECT("'"&$B13&"'!$L:$L"),"*"&C$1&"*") -> 2 | E13: =COUNTIF(INDIRECT("'"&$B13&"'!$B:$B"),"*"&E$1&"*")- COUNTIFS(INDIRECT("'"&$B13&"'!$B:$B"),"*"&E$1&"*",INDIRECT("'"&$B13&"'!$L:$L"),"*") -> 0 | F13: =COUNTIF(INDIRECT("'"&$B13&"'!$L:$L"),"*"&E$1&"*") -> 1 | G13: =COUNTIF(INDIRECT("'"&$B13&"'!$B:$B"),"*"&G$1&"*")- COUNTIFS(INDIRECT("'"&$B13&"'!$B:$B"),"*"&G$1&"*",INDIRECT("'"&$B13&"'!$L:$L"),"*") -> 0 | H13: =COUNTIF(INDIRECT("'"&$B13&"'!$L:$L"),"*"&G$1&"*") -> 0 | I13: =COUNTIF(INDIRECT("'"&$B13&"'!$B:$B"),"*"&I$1&"*")- COUNTIFS(INDIRECT("'"&$B13&"'!$B:$B"),"*"&I$1&"*",INDIRECT("'"&$B13&"'!$L:$L"),"*") -> 0 | J13: =COUNTIF(INDIRECT("'"&$B13&"'!$L:$L"),"*"&I$1&"*") -> 2 | K13: =COUNTIF(INDIRECT("'"&$B13&"'!$B:$B"),"*"&K$1&"*")- COUNTIFS(INDIRECT("'"&$B13&"'!$B:$B"),"*"&K$1&"*",INDIRECT("'"&$B13&"'!$L:$L"),"*") -> 0 | L13: =COUNTIF(INDIRECT("'"&$B13&"'!$L:$L"),"*"&K$1&"*") -> 0 | M13: =COUNTIF(INDIRECT("'"&$B13&"'!$B:$B"),"*"&M$1&"*")- COUNTIFS(INDIRECT("'"&$B13&"'!$B:$B"),"*"&M$1&"*",INDIRECT("'"&$B13&"'!$L:$L"),"*") -> 0 | N13: =COUNTIF(INDIRECT("'"&$B13&"'!$L:$L"),"*"&M$1&"*") -> 0 | O13: =COUNTIF(INDIRECT("'"&$B13&"'!$L:$L"),"*"&O$1&"*") -> 0 | P13: =COUNTIF(INDIRECT("'"&$B13&"'!$L:$L"),"*"&P$1&"*") -> 1 | Q13: =COUNTIF(INDIRECT("'"&$B13&"'!$L:$L"),"*"&Q$1&"*") -> 0 | R13: =COUNTIF(INDIRECT("'"&$B13&"'!$L:$L"),"*"&R$1&"*") -> 0 | S13: =COUNTIF(INDIRECT("'"&$B13&"'!$L:$L"),"*"&S$1&"*") -> 0 | T13: =COUNTIF(INDIRECT("'"&$B13&"'!$L:$L"),"*"&T$1&"*") -> 0 | U13: =COUNTIF(INDIRECT("'"&$B13&"'!$L:$L"),"*"&U$1&"*") -> 0 | V13: =COUNTIF(INDIRECT("'"&$B13&"'!$L:$L"),"*"&V$1&"*") -> 0 | ... AC13: =COUNTIF(INDIRECT("'"&$B13&"'!$L:$L"),"*"&AC$1&"*") -> 0 | AD13: =SUM(C13:AC13) -> 6 | AE13: =AD13*1 -> 6
A14: 46075 | B14: WS_EMANUELLO | C14: =COUNTIF(INDIRECT("'"&$B14&"'!$B:$B"),"*"&C$1&"*")- COUNTIFS(INDIRECT("'"&$B14&"'!$B:$B"),"*"&C$1&"*",INDIRECT("'"&$B14&"'!$L:$L"),"*") -> 0 | D14: =COUNTIF(INDIRECT("'"&$B14&"'!$L:$L"),"*"&C$1&"*") -> 10 | E14: =COUNTIF(INDIRECT("'"&$B14&"'!$B:$B"),"*"&E$1&"*")- COUNTIFS(INDIRECT("'"&$B14&"'!$B:$B"),"*"&E$1&"*",INDIRECT("'"&$B14&"'!$L:$L"),"*") -> 0 | F14: =COUNTIF(INDIRECT("'"&$B14&"'!$L:$L"),"*"&E$1&"*") -> 3 | G14: =COUNTIF(INDIRECT("'"&$B14&"'!$B:$B"),"*"&G$1&"*")- COUNTIFS(INDIRECT("'"&$B14&"'!$B:$B"),"*"&G$1&"*",INDIRECT("'"&$B14&"'!$L:$L"),"*") -> 0 | H14: =COUNTIF(INDIRECT("'"&$B14&"'!$L:$L"),"*"&G$1&"*") -> 1 | I14: =COUNTIF(INDIRECT("'"&$B14&"'!$B:$B"),"*"&I$1&"*")- COUNTIFS(INDIRECT("'"&$B14&"'!$B:$B"),"*"&I$1&"*",INDIRECT("'"&$B14&"'!$L:$L"),"*") -> 0 | J14: =COUNTIF(INDIRECT("'"&$B14&"'!$L:$L"),"*"&I$1&"*") -> 24 | K14: =COUNTIF(INDIRECT("'"&$B14&"'!$B:$B"),"*"&K$1&"*")- COUNTIFS(INDIRECT("'"&$B14&"'!$B:$B"),"*"&K$1&"*",INDIRECT("'"&$B14&"'!$L:$L"),"*") -> 0 | L14: =COUNTIF(INDIRECT("'"&$B14&"'!$L:$L"),"*"&K$1&"*") -> 4 | M14: =COUNTIF(INDIRECT("'"&$B14&"'!$B:$B"),"*"&M$1&"*")- COUNTIFS(INDIRECT("'"&$B14&"'!$B:$B"),"*"&M$1&"*",INDIRECT("'"&$B14&"'!$L:$L"),"*") -> 0 | N14: =COUNTIF(INDIRECT("'"&$B14&"'!$L:$L"),"*"&M$1&"*") -> 0 | O14: =COUNTIF(INDIRECT("'"&$B14&"'!$L:$L"),"*"&O$1&"*") -> 0 | P14: =COUNTIF(INDIRECT("'"&$B14&"'!$L:$L"),"*"&P$1&"*") -> 1 | Q14: =COUNTIF(INDIRECT("'"&$B14&"'!$L:$L"),"*"&Q$1&"*") -> 0 | R14: =COUNTIF(INDIRECT("'"&$B14&"'!$L:$L"),"*"&R$1&"*") -> 0 | S14: =COUNTIF(INDIRECT("'"&$B14&"'!$L:$L"),"*"&S$1&"*") -> 0 | T14: =COUNTIF(INDIRECT("'"&$B14&"'!$L:$L"),"*"&T$1&"*") -> 0 | U14: =COUNTIF(INDIRECT("'"&$B14&"'!$L:$L"),"*"&U$1&"*") -> 0 | V14: =COUNTIF(INDIRECT("'"&$B14&"'!$L:$L"),"*"&V$1&"*") -> 0 | ... AC14: =COUNTIF(INDIRECT("'"&$B14&"'!$L:$L"),"*"&AC$1&"*") -> 0 | AD14: =SUM(C14:AC14) -> 43 | AE14: =AD14*1 -> 43
... A18: 46131 | B18: WS_JASMINE_ANDRIANO | C18: =COUNTIF(INDIRECT("'"&$B18&"'!$B:$B"),"*"&C$1&"*")- COUNTIFS(INDIRECT("'"&$B18&"'!$B:$B"),"*"&C$1&"*",INDIRECT("'"&$B18&"'!$L:$L"),"*") -> 0 | D18: =COUNTIF(INDIRECT("'"&$B18&"'!$L:$L"),"*"&C$1&"*") -> 1 | E18: =COUNTIF(INDIRECT("'"&$B18&"'!$B:$B"),"*"&E$1&"*")- COUNTIFS(INDIRECT("'"&$B18&"'!$B:$B"),"*"&E$1&"*",INDIRECT("'"&$B18&"'!$L:$L"),"*") -> 0 | F18: =COUNTIF(INDIRECT("'"&$B18&"'!$L:$L"),"*"&E$1&"*") -> 1 | G18: =COUNTIF(INDIRECT("'"&$B18&"'!$B:$B"),"*"&G$1&"*")- COUNTIFS(INDIRECT("'"&$B18&"'!$B:$B"),"*"&G$1&"*",INDIRECT("'"&$B18&"'!$L:$L"),"*") -> 0 | H18: =COUNTIF(INDIRECT("'"&$B18&"'!$L:$L"),"*"&G$1&"*") -> 0 | I18: =COUNTIF(INDIRECT("'"&$B18&"'!$B:$B"),"*"&I$1&"*")- COUNTIFS(INDIRECT("'"&$B18&"'!$B:$B"),"*"&I$1&"*",INDIRECT("'"&$B18&"'!$L:$L"),"*") -> 0 | J18: =COUNTIF(INDIRECT("'"&$B18&"'!$L:$L"),"*"&I$1&"*") -> 1 | K18: =COUNTIF(INDIRECT("'"&$B18&"'!$B:$B"),"*"&K$1&"*")- COUNTIFS(INDIRECT("'"&$B18&"'!$B:$B"),"*"&K$1&"*",INDIRECT("'"&$B18&"'!$L:$L"),"*") -> 0 | L18: =COUNTIF(INDIRECT("'"&$B18&"'!$L:$L"),"*"&K$1&"*") -> 0 | M18: =COUNTIF(INDIRECT("'"&$B18&"'!$B:$B"),"*"&M$1&"*")- COUNTIFS(INDIRECT("'"&$B18&"'!$B:$B"),"*"&M$1&"*",INDIRECT("'"&$B18&"'!$L:$L"),"*") -> 0 | N18: =COUNTIF(INDIRECT("'"&$B18&"'!$L:$L"),"*"&M$1&"*") -> 0 | O18: =COUNTIF(INDIRECT("'"&$B18&"'!$L:$L"),"*"&O$1&"*") -> 0 | P18: =COUNTIF(INDIRECT("'"&$B18&"'!$L:$L"),"*"&P$1&"*") -> 0 | Q18: =COUNTIF(INDIRECT("'"&$B18&"'!$L:$L"),"*"&Q$1&"*") -> 0 | R18: =COUNTIF(INDIRECT("'"&$B18&"'!$L:$L"),"*"&R$1&"*") -> 0 | S18: =COUNTIF(INDIRECT("'"&$B18&"'!$L:$L"),"*"&S$1&"*") -> 0 | T18: =COUNTIF(INDIRECT("'"&$B18&"'!$L:$L"),"*"&T$1&"*") -> 0 | U18: =COUNTIF(INDIRECT("'"&$B18&"'!$L:$L"),"*"&U$1&"*") -> 0 | V18: =COUNTIF(INDIRECT("'"&$B18&"'!$L:$L"),"*"&V$1&"*") -> 0 | ... AC18: =COUNTIF(INDIRECT("'"&$B18&"'!$L:$L"),"*"&AC$1&"*") -> 0 | AD18: =SUM(C18:AC18) -> 3 | AE18: =AD18*1 -> 3
C19: =COUNTIF(INDIRECT("'"&$B19&"'!$B:$B"),"*"&C$1&"*")- COUNTIFS(INDIRECT("'"&$B19&"'!$B:$B"),"*"&C$1&"*",INDIRECT("'"&$B19&"'!$L:$L"),"*") -> 0 | D19: =COUNTIF(INDIRECT("'"&$B19&"'!$L:$L"),"*"&C$1&"*") -> 0 | E19: =COUNTIF(INDIRECT("'"&$B19&"'!$B:$B"),"*"&E$1&"*")- COUNTIFS(INDIRECT("'"&$B19&"'!$B:$B"),"*"&E$1&"*",INDIRECT("'"&$B19&"'!$L:$L"),"*") -> 0 | F19: =COUNTIF(INDIRECT("'"&$B19&"'!$L:$L"),"*"&E$1&"*") -> 0 | G19: =COUNTIF(INDIRECT("'"&$B19&"'!$B:$B"),"*"&G$1&"*")- COUNTIFS(INDIRECT("'"&$B19&"'!$B:$B"),"*"&G$1&"*",INDIRECT("'"&$B19&"'!$L:$L"),"*") -> 0 | H19: =COUNTIF(INDIRECT("'"&$B19&"'!$L:$L"),"*"&G$1&"*") -> 0 | I19: =COUNTIF(INDIRECT("'"&$B19&"'!$B:$B"),"*"&I$1&"*")- COUNTIFS(INDIRECT("'"&$B19&"'!$B:$B"),"*"&I$1&"*",INDIRECT("'"&$B19&"'!$L:$L"),"*") -> 0 | J19: =COUNTIF(INDIRECT("'"&$B19&"'!$L:$L"),"*"&I$1&"*") -> 0 | K19: =COUNTIF(INDIRECT("'"&$B19&"'!$B:$B"),"*"&K$1&"*")- COUNTIFS(INDIRECT("'"&$B19&"'!$B:$B"),"*"&K$1&"*",INDIRECT("'"&$B19&"'!$L:$L"),"*") -> 0 | L19: =COUNTIF(INDIRECT("'"&$B19&"'!$L:$L"),"*"&K$1&"*") -> 0 | M19: =COUNTIF(INDIRECT("'"&$B19&"'!$B:$B"),"*"&M$1&"*")- COUNTIFS(INDIRECT("'"&$B19&"'!$B:$B"),"*"&M$1&"*",INDIRECT("'"&$B19&"'!$L:$L"),"*") -> 0 | N19: =COUNTIF(INDIRECT("'"&$B19&"'!$L:$L"),"*"&M$1&"*") -> 0 | O19: =COUNTIF(INDIRECT("'"&$B19&"'!$L:$L"),"*"&O$1&"*") -> 0 | P19: =COUNTIF(INDIRECT("'"&$B19&"'!$L:$L"),"*"&P$1&"*") -> 0 | Q19: =COUNTIF(INDIRECT("'"&$B19&"'!$L:$L"),"*"&Q$1&"*") -> 0 | R19: =COUNTIF(INDIRECT("'"&$B19&"'!$L:$L"),"*"&R$1&"*") -> 0 | S19: =COUNTIF(INDIRECT("'"&$B19&"'!$L:$L"),"*"&S$1&"*") -> 0 | T19: =COUNTIF(INDIRECT("'"&$B19&"'!$L:$L"),"*"&T$1&"*") -> 0 | U19: =COUNTIF(INDIRECT("'"&$B19&"'!$L:$L"),"*"&U$1&"*") -> 0 | V19: =COUNTIF(INDIRECT("'"&$B19&"'!$L:$L"),"*"&V$1&"*") -> 0 | ... AC19: =COUNTIF(INDIRECT("'"&$B19&"'!$L:$L"),"*"&AC$1&"*") -> 0 | AD19: =SUM(C19:AC19) -> 0 | AE19: =AD19*1 -> 0
C20: =COUNTIF(INDIRECT("'"&$B20&"'!$B:$B"),"*"&C$1&"*")- COUNTIFS(INDIRECT("'"&$B20&"'!$B:$B"),"*"&C$1&"*",INDIRECT("'"&$B20&"'!$L:$L"),"*") -> 0 | D20: =COUNTIF(INDIRECT("'"&$B20&"'!$L:$L"),"*"&C$1&"*") -> 0 | E20: =COUNTIF(INDIRECT("'"&$B20&"'!$B:$B"),"*"&E$1&"*")- COUNTIFS(INDIRECT("'"&$B20&"'!$B:$B"),"*"&E$1&"*",INDIRECT("'"&$B20&"'!$L:$L"),"*") -> 0 | F20: =COUNTIF(INDIRECT("'"&$B20&"'!$L:$L"),"*"&E$1&"*") -> 0 | G20: =COUNTIF(INDIRECT("'"&$B20&"'!$B:$B"),"*"&G$1&"*")- COUNTIFS(INDIRECT("'"&$B20&"'!$B:$B"),"*"&G$1&"*",INDIRECT("'"&$B20&"'!$L:$L"),"*") -> 0 | H20: =COUNTIF(INDIRECT("'"&$B20&"'!$L:$L"),"*"&G$1&"*") -> 0 | I20: =COUNTIF(INDIRECT("'"&$B20&"'!$B:$B"),"*"&I$1&"*")- COUNTIFS(INDIRECT("'"&$B20&"'!$B:$B"),"*"&I$1&"*",INDIRECT("'"&$B20&"'!$L:$L"),"*") -> 0 | J20: =COUNTIF(INDIRECT("'"&$B20&"'!$L:$L"),"*"&I$1&"*") -> 0 | K20: =COUNTIF(INDIRECT("'"&$B20&"'!$B:$B"),"*"&K$1&"*")- COUNTIFS(INDIRECT("'"&$B20&"'!$B:$B"),"*"&K$1&"*",INDIRECT("'"&$B20&"'!$L:$L"),"*") -> 0 | L20: =COUNTIF(INDIRECT("'"&$B20&"'!$L:$L"),"*"&K$1&"*") -> 0 | M20: =COUNTIF(INDIRECT("'"&$B20&"'!$B:$B"),"*"&M$1&"*")- COUNTIFS(INDIRECT("'"&$B20&"'!$B:$B"),"*"&M$1&"*",INDIRECT("'"&$B20&"'!$L:$L"),"*") -> 0 | N20: =COUNTIF(INDIRECT("'"&$B20&"'!$L:$L"),"*"&M$1&"*") -> 0 | O20: =COUNTIF(INDIRECT("'"&$B20&"'!$L:$L"),"*"&O$1&"*") -> 0 | P20: =COUNTIF(INDIRECT("'"&$B20&"'!$L:$L"),"*"&P$1&"*") -> 0 | Q20: =COUNTIF(INDIRECT("'"&$B20&"'!$L:$L"),"*"&Q$1&"*") -> 0 | R20: =COUNTIF(INDIRECT("'"&$B20&"'!$L:$L"),"*"&R$1&"*") -> 0 | S20: =COUNTIF(INDIRECT("'"&$B20&"'!$L:$L"),"*"&S$1&"*") -> 0 | T20: =COUNTIF(INDIRECT("'"&$B20&"'!$L:$L"),"*"&T$1&"*") -> 0 | U20: =COUNTIF(INDIRECT("'"&$B20&"'!$L:$L"),"*"&U$1&"*") -> 0 | V20: =COUNTIF(INDIRECT("'"&$B20&"'!$L:$L"),"*"&V$1&"*") -> 0 | ... AC20: =COUNTIF(INDIRECT("'"&$B20&"'!$L:$L"),"*"&AC$1&"*") -> 0 | AD20: =SUM(C20:AC20) -> 0 | AE20: =AD20*1 -> 0
C21: =COUNTIF(INDIRECT("'"&$B21&"'!$B:$B"),"*"&C$1&"*")- COUNTIFS(INDIRECT("'"&$B21&"'!$B:$B"),"*"&C$1&"*",INDIRECT("'"&$B21&"'!$L:$L"),"*") -> 0 | D21: =COUNTIF(INDIRECT("'"&$B21&"'!$L:$L"),"*"&C$1&"*") -> 0 | E21: =COUNTIF(INDIRECT("'"&$B21&"'!$B:$B"),"*"&E$1&"*")- COUNTIFS(INDIRECT("'"&$B21&"'!$B:$B"),"*"&E$1&"*",INDIRECT("'"&$B21&"'!$L:$L"),"*") -> 0 | F21: =COUNTIF(INDIRECT("'"&$B21&"'!$L:$L"),"*"&E$1&"*") -> 0 | G21: =COUNTIF(INDIRECT("'"&$B21&"'!$B:$B"),"*"&G$1&"*")- COUNTIFS(INDIRECT("'"&$B21&"'!$B:$B"),"*"&G$1&"*",INDIRECT("'"&$B21&"'!$L:$L"),"*") -> 0 | H21: =COUNTIF(INDIRECT("'"&$B21&"'!$L:$L"),"*"&G$1&"*") -> 0 | I21: =COUNTIF(INDIRECT("'"&$B21&"'!$B:$B"),"*"&I$1&"*")- COUNTIFS(INDIRECT("'"&$B21&"'!$B:$B"),"*"&I$1&"*",INDIRECT("'"&$B21&"'!$L:$L"),"*") -> 0 | J21: =COUNTIF(INDIRECT("'"&$B21&"'!$L:$L"),"*"&I$1&"*") -> 0 | K21: =COUNTIF(INDIRECT("'"&$B21&"'!$B:$B"),"*"&K$1&"*")- COUNTIFS(INDIRECT("'"&$B21&"'!$B:$B"),"*"&K$1&"*",INDIRECT("'"&$B21&"'!$L:$L"),"*") -> 0 | L21: =COUNTIF(INDIRECT("'"&$B21&"'!$L:$L"),"*"&K$1&"*") -> 0 | M21: =COUNTIF(INDIRECT("'"&$B21&"'!$B:$B"),"*"&M$1&"*")- COUNTIFS(INDIRECT("'"&$B21&"'!$B:$B"),"*"&M$1&"*",INDIRECT("'"&$B21&"'!$L:$L"),"*") -> 0 | N21: =COUNTIF(INDIRECT("'"&$B21&"'!$L:$L"),"*"&M$1&"*") -> 0 | O21: =COUNTIF(INDIRECT("'"&$B21&"'!$L:$L"),"*"&O$1&"*") -> 0 | P21: =COUNTIF(INDIRECT("'"&$B21&"'!$L:$L"),"*"&P$1&"*") -> 0 | Q21: =COUNTIF(INDIRECT("'"&$B21&"'!$L:$L"),"*"&Q$1&"*") -> 0 | R21: =COUNTIF(INDIRECT("'"&$B21&"'!$L:$L"),"*"&R$1&"*") -> 0 | S21: =COUNTIF(INDIRECT("'"&$B21&"'!$L:$L"),"*"&S$1&"*") -> 0 | T21: =COUNTIF(INDIRECT("'"&$B21&"'!$L:$L"),"*"&T$1&"*") -> 0 | U21: =COUNTIF(INDIRECT("'"&$B21&"'!$L:$L"),"*"&U$1&"*") -> 0 | V21: =COUNTIF(INDIRECT("'"&$B21&"'!$L:$L"),"*"&V$1&"*") -> 0 | ... AC21: =COUNTIF(INDIRECT("'"&$B21&"'!$L:$L"),"*"&AC$1&"*") -> 0 | AD21: =SUM(C21:AC21) -> 0 | AE21: =AD21*1 -> 0
C22: =COUNTIF(INDIRECT("'"&$B22&"'!$B:$B"),"*"&C$1&"*")- COUNTIFS(INDIRECT("'"&$B22&"'!$B:$B"),"*"&C$1&"*",INDIRECT("'"&$B22&"'!$L:$L"),"*") -> 0 | D22: =COUNTIF(INDIRECT("'"&$B22&"'!$L:$L"),"*"&C$1&"*") -> 0 | E22: =COUNTIF(INDIRECT("'"&$B22&"'!$B:$B"),"*"&E$1&"*")- COUNTIFS(INDIRECT("'"&$B22&"'!$B:$B"),"*"&E$1&"*",INDIRECT("'"&$B22&"'!$L:$L"),"*") -> 0 | F22: =COUNTIF(INDIRECT("'"&$B22&"'!$L:$L"),"*"&E$1&"*") -> 0 | G22: =COUNTIF(INDIRECT("'"&$B22&"'!$B:$B"),"*"&G$1&"*")- COUNTIFS(INDIRECT("'"&$B22&"'!$B:$B"),"*"&G$1&"*",INDIRECT("'"&$B22&"'!$L:$L"),"*") -> 0 | H22: =COUNTIF(INDIRECT("'"&$B22&"'!$L:$L"),"*"&G$1&"*") -> 0 | I22: =COUNTIF(INDIRECT("'"&$B22&"'!$B:$B"),"*"&I$1&"*")- COUNTIFS(INDIRECT("'"&$B22&"'!$B:$B"),"*"&I$1&"*",INDIRECT("'"&$B22&"'!$L:$L"),"*") -> 0 | J22: =COUNTIF(INDIRECT("'"&$B22&"'!$L:$L"),"*"&I$1&"*") -> 0 | K22: =COUNTIF(INDIRECT("'"&$B22&"'!$B:$B"),"*"&K$1&"*")- COUNTIFS(INDIRECT("'"&$B22&"'!$B:$B"),"*"&K$1&"*",INDIRECT("'"&$B22&"'!$L:$L"),"*") -> 0 | L22: =COUNTIF(INDIRECT("'"&$B22&"'!$L:$L"),"*"&K$1&"*") -> 0 | M22: =COUNTIF(INDIRECT("'"&$B22&"'!$B:$B"),"*"&M$1&"*")- COUNTIFS(INDIRECT("'"&$B22&"'!$B:$B"),"*"&M$1&"*",INDIRECT("'"&$B22&"'!$L:$L"),"*") -> 0 | N22: =COUNTIF(INDIRECT("'"&$B22&"'!$L:$L"),"*"&M$1&"*") -> 0 | O22: =COUNTIF(INDIRECT("'"&$B22&"'!$L:$L"),"*"&O$1&"*") -> 0 | P22: =COUNTIF(INDIRECT("'"&$B22&"'!$L:$L"),"*"&P$1&"*") -> 0 | Q22: =COUNTIF(INDIRECT("'"&$B22&"'!$L:$L"),"*"&Q$1&"*") -> 0 | R22: =COUNTIF(INDIRECT("'"&$B22&"'!$L:$L"),"*"&R$1&"*") -> 0 | S22: =COUNTIF(INDIRECT("'"&$B22&"'!$L:$L"),"*"&S$1&"*") -> 0 | T22: =COUNTIF(INDIRECT("'"&$B22&"'!$L:$L"),"*"&T$1&"*") -> 0 | U22: =COUNTIF(INDIRECT("'"&$B22&"'!$L:$L"),"*"&U$1&"*") -> 0 | V22: =COUNTIF(INDIRECT("'"&$B22&"'!$L:$L"),"*"&V$1&"*") -> 0 | ... AC22: =COUNTIF(INDIRECT("'"&$B22&"'!$L:$L"),"*"&AC$1&"*") -> 0 | AD22: =SUM(C22:AC22) -> 0 | AE22: =AD22*1 -> 0
C23: =COUNTIF(INDIRECT("'"&$B23&"'!$B:$B"),"*"&C$1&"*")- COUNTIFS(INDIRECT("'"&$B23&"'!$B:$B"),"*"&C$1&"*",INDIRECT("'"&$B23&"'!$L:$L"),"*") -> 0 | D23: =COUNTIF(INDIRECT("'"&$B23&"'!$L:$L"),"*"&C$1&"*") -> 0 | E23: =COUNTIF(INDIRECT("'"&$B23&"'!$B:$B"),"*"&E$1&"*")- COUNTIFS(INDIRECT("'"&$B23&"'!$B:$B"),"*"&E$1&"*",INDIRECT("'"&$B23&"'!$L:$L"),"*") -> 0 | F23: =COUNTIF(INDIRECT("'"&$B23&"'!$L:$L"),"*"&E$1&"*") -> 0 | G23: =COUNTIF(INDIRECT("'"&$B23&"'!$B:$B"),"*"&G$1&"*")- COUNTIFS(INDIRECT("'"&$B23&"'!$B:$B"),"*"&G$1&"*",INDIRECT("'"&$B23&"'!$L:$L"),"*") -> 0 | H23: =COUNTIF(INDIRECT("'"&$B23&"'!$L:$L"),"*"&G$1&"*") -> 0 | I23: =COUNTIF(INDIRECT("'"&$B23&"'!$B:$B"),"*"&I$1&"*")- COUNTIFS(INDIRECT("'"&$B23&"'!$B:$B"),"*"&I$1&"*",INDIRECT("'"&$B23&"'!$L:$L"),"*") -> 0 | J23: =COUNTIF(INDIRECT("'"&$B23&"'!$L:$L"),"*"&I$1&"*") -> 0 | K23: =COUNTIF(INDIRECT("'"&$B23&"'!$B:$B"),"*"&K$1&"*")- COUNTIFS(INDIRECT("'"&$B23&"'!$B:$B"),"*"&K$1&"*",INDIRECT("'"&$B23&"'!$L:$L"),"*") -> 0 | L23: =COUNTIF(INDIRECT("'"&$B23&"'!$L:$L"),"*"&K$1&"*") -> 0 | M23: =COUNTIF(INDIRECT("'"&$B23&"'!$B:$B"),"*"&M$1&"*")- COUNTIFS(INDIRECT("'"&$B23&"'!$B:$B"),"*"&M$1&"*",INDIRECT("'"&$B23&"'!$L:$L"),"*") -> 0 | N23: =COUNTIF(INDIRECT("'"&$B23&"'!$L:$L"),"*"&M$1&"*") -> 0 | O23: =COUNTIF(INDIRECT("'"&$B23&"'!$L:$L"),"*"&O$1&"*") -> 0 | P23: =COUNTIF(INDIRECT("'"&$B23&"'!$L:$L"),"*"&P$1&"*") -> 0 | Q23: =COUNTIF(INDIRECT("'"&$B23&"'!$L:$L"),"*"&Q$1&"*") -> 0 | R23: =COUNTIF(INDIRECT("'"&$B23&"'!$L:$L"),"*"&R$1&"*") -> 0 | S23: =COUNTIF(INDIRECT("'"&$B23&"'!$L:$L"),"*"&S$1&"*") -> 0 | T23: =COUNTIF(INDIRECT("'"&$B23&"'!$L:$L"),"*"&T$1&"*") -> 0 | U23: =COUNTIF(INDIRECT("'"&$B23&"'!$L:$L"),"*"&U$1&"*") -> 0 | V23: =COUNTIF(INDIRECT("'"&$B23&"'!$L:$L"),"*"&V$1&"*") -> 0 | ... AC23: =COUNTIF(INDIRECT("'"&$B23&"'!$L:$L"),"*"&AC$1&"*") -> 0 | AD23: =SUM(C23:AC23) -> 0 | AE23: =AD23*1 -> 0
C24: =COUNTIF(INDIRECT("'"&$B24&"'!$B:$B"),"*"&C$1&"*")- COUNTIFS(INDIRECT("'"&$B24&"'!$B:$B"),"*"&C$1&"*",INDIRECT("'"&$B24&"'!$L:$L"),"*") -> 0 | D24: =COUNTIF(INDIRECT("'"&$B24&"'!$L:$L"),"*"&C$1&"*") -> 0 | E24: =COUNTIF(INDIRECT("'"&$B24&"'!$B:$B"),"*"&E$1&"*")- COUNTIFS(INDIRECT("'"&$B24&"'!$B:$B"),"*"&E$1&"*",INDIRECT("'"&$B24&"'!$L:$L"),"*") -> 0 | F24: =COUNTIF(INDIRECT("'"&$B24&"'!$L:$L"),"*"&E$1&"*") -> 0 | G24: =COUNTIF(INDIRECT("'"&$B24&"'!$B:$B"),"*"&G$1&"*")- COUNTIFS(INDIRECT("'"&$B24&"'!$B:$B"),"*"&G$1&"*",INDIRECT("'"&$B24&"'!$L:$L"),"*") -> 0 | H24: =COUNTIF(INDIRECT("'"&$B24&"'!$L:$L"),"*"&G$1&"*") -> 0 | I24: =COUNTIF(INDIRECT("'"&$B24&"'!$B:$B"),"*"&I$1&"*")- COUNTIFS(INDIRECT("'"&$B24&"'!$B:$B"),"*"&I$1&"*",INDIRECT("'"&$B24&"'!$L:$L"),"*") -> 0 | J24: =COUNTIF(INDIRECT("'"&$B24&"'!$L:$L"),"*"&I$1&"*") -> 0 | K24: =COUNTIF(INDIRECT("'"&$B24&"'!$B:$B"),"*"&K$1&"*")- COUNTIFS(INDIRECT("'"&$B24&"'!$B:$B"),"*"&K$1&"*",INDIRECT("'"&$B24&"'!$L:$L"),"*") -> 0 | L24: =COUNTIF(INDIRECT("'"&$B24&"'!$L:$L"),"*"&K$1&"*") -> 0 | M24: =COUNTIF(INDIRECT("'"&$B24&"'!$B:$B"),"*"&M$1&"*")- COUNTIFS(INDIRECT("'"&$B24&"'!$B:$B"),"*"&M$1&"*",INDIRECT("'"&$B24&"'!$L:$L"),"*") -> 0 | N24: =COUNTIF(INDIRECT("'"&$B24&"'!$L:$L"),"*"&M$1&"*") -> 0 | O24: =COUNTIF(INDIRECT("'"&$B24&"'!$L:$L"),"*"&O$1&"*") -> 0 | P24: =COUNTIF(INDIRECT("'"&$B24&"'!$L:$L"),"*"&P$1&"*") -> 0 | Q24: =COUNTIF(INDIRECT("'"&$B24&"'!$L:$L"),"*"&Q$1&"*") -> 0 | R24: =COUNTIF(INDIRECT("'"&$B24&"'!$L:$L"),"*"&R$1&"*") -> 0 | S24: =COUNTIF(INDIRECT("'"&$B24&"'!$L:$L"),"*"&S$1&"*") -> 0 | T24: =COUNTIF(INDIRECT("'"&$B24&"'!$L:$L"),"*"&T$1&"*") -> 0 | U24: =COUNTIF(INDIRECT("'"&$B24&"'!$L:$L"),"*"&U$1&"*") -> 0 | V24: =COUNTIF(INDIRECT("'"&$B24&"'!$L:$L"),"*"&V$1&"*") -> 0 | ... AC24: =COUNTIF(INDIRECT("'"&$B24&"'!$L:$L"),"*"&AC$1&"*") -> 0 | AD24: =SUM(C24:AC24) -> 0 | AE24: =AD24*1 -> 0
C25: =COUNTIF(INDIRECT("'"&$B25&"'!$B:$B"),"*"&C$1&"*")- COUNTIFS(INDIRECT("'"&$B25&"'!$B:$B"),"*"&C$1&"*",INDIRECT("'"&$B25&"'!$L:$L"),"*") -> 0 | D25: =COUNTIF(INDIRECT("'"&$B25&"'!$L:$L"),"*"&C$1&"*") -> 0 | E25: =COUNTIF(INDIRECT("'"&$B25&"'!$B:$B"),"*"&E$1&"*")- COUNTIFS(INDIRECT("'"&$B25&"'!$B:$B"),"*"&E$1&"*",INDIRECT("'"&$B25&"'!$L:$L"),"*") -> 0 | F25: =COUNTIF(INDIRECT("'"&$B25&"'!$L:$L"),"*"&E$1&"*") -> 0 | G25: =COUNTIF(INDIRECT("'"&$B25&"'!$B:$B"),"*"&G$1&"*")- COUNTIFS(INDIRECT("'"&$B25&"'!$B:$B"),"*"&G$1&"*",INDIRECT("'"&$B25&"'!$L:$L"),"*") -> 0 | H25: =COUNTIF(INDIRECT("'"&$B25&"'!$L:$L"),"*"&G$1&"*") -> 0 | I25: =COUNTIF(INDIRECT("'"&$B25&"'!$B:$B"),"*"&I$1&"*")- COUNTIFS(INDIRECT("'"&$B25&"'!$B:$B"),"*"&I$1&"*",INDIRECT("'"&$B25&"'!$L:$L"),"*") -> 0 | J25: =COUNTIF(INDIRECT("'"&$B25&"'!$L:$L"),"*"&I$1&"*") -> 0 | K25: =COUNTIF(INDIRECT("'"&$B25&"'!$B:$B"),"*"&K$1&"*")- COUNTIFS(INDIRECT("'"&$B25&"'!$B:$B"),"*"&K$1&"*",INDIRECT("'"&$B25&"'!$L:$L"),"*") -> 0 | L25: =COUNTIF(INDIRECT("'"&$B25&"'!$L:$L"),"*"&K$1&"*") -> 0 | M25: =COUNTIF(INDIRECT("'"&$B25&"'!$B:$B"),"*"&M$1&"*")- COUNTIFS(INDIRECT("'"&$B25&"'!$B:$B"),"*"&M$1&"*",INDIRECT("'"&$B25&"'!$L:$L"),"*") -> 0 | N25: =COUNTIF(INDIRECT("'"&$B25&"'!$L:$L"),"*"&M$1&"*") -> 0 | O25: =COUNTIF(INDIRECT("'"&$B25&"'!$L:$L"),"*"&O$1&"*") -> 0 | P25: =COUNTIF(INDIRECT("'"&$B25&"'!$L:$L"),"*"&P$1&"*") -> 0 | Q25: =COUNTIF(INDIRECT("'"&$B25&"'!$L:$L"),"*"&Q$1&"*") -> 0 | R25: =COUNTIF(INDIRECT("'"&$B25&"'!$L:$L"),"*"&R$1&"*") -> 0 | S25: =COUNTIF(INDIRECT("'"&$B25&"'!$L:$L"),"*"&S$1&"*") -> 0 | T25: =COUNTIF(INDIRECT("'"&$B25&"'!$L:$L"),"*"&T$1&"*") -> 0 | U25: =COUNTIF(INDIRECT("'"&$B25&"'!$L:$L"),"*"&U$1&"*") -> 0 | V25: =COUNTIF(INDIRECT("'"&$B25&"'!$L:$L"),"*"&V$1&"*") -> 0 | ... AC25: =COUNTIF(INDIRECT("'"&$B25&"'!$L:$L"),"*"&AC$1&"*") -> 0 | AD25: =SUM(C25:AC25) -> 0 | AE25: =AD25*1 -> 0
B32: punti TOTALE | C32: =SUM(C3:C31) -> 6 | D32: =SUM(D3:D31) -> 82 | E32: =SUM(E3:E31) -> 5 | F32: =SUM(F3:F31) -> 63 | G32: =SUM(G3:G31) -> 0 | H32: =SUM(H3:H31) -> 36 | I32: =SUM(I3:I31) -> 14 | J32: =SUM(J3:J31) -> 124 | ... AE32: =SUM(AE3:AE31) -> 475
B33: subTOTALE | C33: =C32*1.5 -> 9 | D33: =D32*1 -> 82 | E33: =E32*1.5 -> 7.5 | F33: =F32*1 -> 63 | G33: =G32*1.5 -> 0 | H33: =H32*1 -> 36 | I33: =I32*1.5 -> 21 | J33: =J32*1 -> 124 | K33: =K32*1.5 -> 3 | L33: =L32*1 -> 32 | M33: =M32*1.5 -> 0 | N33: =N32*1 -> 0 | O33: =O32*1 -> 100 | P33: =P32*1 -> 7 | Q33: =Q32*1 -> 4 | R33: =R32*1 -> 0 | S33: =S32*1 -> 0 | T33: =T32*3 -> 0 | U33: =U32*3 -> 0 | V33: =V32*3 -> 0 | W33: =W32*3 -> 0 | X33: =X32*3 -> 0 | Y33: =Y32*3 -> 0
B34: TOTALE | C34: =C33+D33 -> 91 | E34: =E33+F33 -> 70.5 | G34: =G33+H33 -> 36 | I34: =I33+J33 -> 145 | K34: =K33+L33 -> 35 | M34: =M33+N33 -> 0 | O34: =O33 -> 100 | P34: =P33 -> 7 | Q34: =Q33 -> 4 | R34: =R33 -> 0 | S34: =S33 -> 0 | T34: =T33 -> 0 | U34: =U33 -> 0 | V34: =V33 -> 0 | ... Y34: =Y33 -> 0 | AE34: =SUM(C34:AC34) -> 488.5
A35: Legenda: | B35: 1 sede = € 1,50 | C35: 1 codice = € 1,00 | E35: 1 bonus Team = €1,00 | G35: 1 bonus Staff (nome) = €3,00 | I35: Il saldo verrà liquidato a metà luglio 2025 in contanti
B36: SEDE: | C36: la colonna SEDE conta solo se un nome si trova nella colonna che si chiama VENDITA e PAGAMENTO di qualsiasi file collegato a questo Resoconto
B37: CODICE: | C37: la colonna CODICE conta solo se un nome si trova nella colonna che si chiama CODICE SCONTO di qualsiasi file collegato a questo Resoconto

Sheet WS_JASMINE_ANDRIANO
C1: WS_JASMINE ANDRIANO_19APR2026
A2: CHI SCRIVE | B2: VENDITA | C2: DATA INSERIMENTO /RICHIESTA | D2: ID ANAGRAFICA | E2: COGNOME | F2: NOME | G2: TELEFONO | H2: CODICE FISCALE | I2: EMAIL | J2: DATA PAGAMENTO /RICEVUTA | K2: QUOTA | L2: CODICE SCONTO | M2: IMPORTO FINALE | N2: DIGIT/CASH - TESS/NON TESS | O2: PRESENZA | P2: NOTE | Q2: INSERITO SU ATHENA | R2: RICEVUTA FATTA | S2: FATTURA FATTA | T2: VERIFICA PAGAMENTO
C3: 14:30-16:00_COMMERCIAL (€32 entro il 18 Marzo compreso → €37 dal 19 Marzo al 18 Aprile compreso → €42 il giorno stesso)
A4: Estefany | B4: ONLINE | C4: 46065 | E4: CARRIERA | F4: MARTA | G4: 3770848139 | H4: CRRMRT00P67G388G | I4: mcarriera27@gmail.com | J4: 46065 | K4: 32 | L4: ALEXANDRA02WS | M4: =IFERROR(__xludf.DUMMYFUNCTION("IF( K4="""", """", ROUND( IF( L4="""", K4, IF( ISERROR(FIND(""-"",L4)), K4 - VALUE(REGEXEXTRACT(L4,""(\d+)"")), K4 * (1 - VALUE(REGEXEXTRACT(L4,""(\d+)""))/100) ) ), 2 ) ) "),30.0) -> 30 | N4: DIGIT - NON TESSERATO | O4: FALSE | Q4: INSERITO | R4: FALSE | S4: TRUE | T4: TRUE
A5: Estefany | B5: ONLINE | C5: 46094 | E5: KOSTANECKA | F5: ALEKSANDRA | G5: 3478569980 | H5: KSTLSN05A68Z127Q | I5: ola.kostanecka2005@gmail.com | J5: 46094 | K5: 32 | M5: =IFERROR(__xludf.DUMMYFUNCTION("IF( K5="""", """", ROUND( IF( L5="""", K5, IF( ISERROR(FIND(""-"",L5)), K5 - VALUE(REGEXEXTRACT(L5,""(\d+)"")), K5 * (1 - VALUE(REGEXEXTRACT(L5,""(\d+)""))/100) ) ), 2 ) ) "),32.0) -> 32 | N5: DIGIT - NON TESSERATO | O5: FALSE | Q5: INSERITO | R5: FALSE | S5: TRUE | T5: TRUE
A6: Estefany | B6: ONLINE | C6: 46078 | E6: LUNGHI | F6: REBECCA | G6: 3463062200 | H6: LNGRCC05R48B300Y | I6: rebeccalunghi@gmail.com | J6: 46078 | K6: 37 | M6: =IFERROR(__xludf.DUMMYFUNCTION("IF( K6="""", """", ROUND( IF( L6="""", K6, IF( ISERROR(FIND(""-"",L6)), K6 - VALUE(REGEXEXTRACT(L6,""(\d+)"")), K6 * (1 - VALUE(REGEXEXTRACT(L6,""(\d+)""))/100) ) ), 2 ) ) "),37.0) -> 37 | N6: DIGIT - NON TESSERATO | O6: FALSE | Q6: INSERITO | R6: FALSE | S6: TRUE | T6: TRUE
A7: Estefany | B7: ONLINE | C7: 46078 | E7: ESPINOZA | F7: CAMILLA | G7: 3711436102 | H7: SPNSLY03B44Z605H | I7: ce200304@gmail.com | J7: 46078 | K7: 37 | M7: =IFERROR(__xludf.DUMMYFUNCTION("IF( K7="""", """", ROUND( IF( L7="""", K7, IF( ISERROR(FIND(""-"",L7)), K7 - VALUE(REGEXEXTRACT(L7,""(\d+)"")), K7 * (1 - VALUE(REGEXEXTRACT(L7,""(\d+)""))/100) ) ), 2 ) ) "),37.0) -> 37 | N7: DIGIT - NON TESSERATO | O7: FALSE | Q7: INSERITO | R7: FALSE | S7: TRUE | T7: TRUE
A8: Estefany | B8: SEDE Estefany | C8: 46097 | E8: CAMPAGNA | F8: ALESSIO | G8: 3517240804 | H8: CMPLSS98A21H501J | I8: alessiotcgtrade@gmail.com | J8: 46097 | K8: 32 | L8: ESTEFANY02WS | M8: =IFERROR(__xludf.DUMMYFUNCTION("IF( K8="""", """", ROUND( IF( L8="""", K8, IF( ISERROR(FIND(""-"",L8)), K8 - VALUE(REGEXEXTRACT(L8,""(\d+)"")), K8 * (1 - VALUE(REGEXEXTRACT(L8,""(\d+)""))/100) ) ), 2 ) ) "),30.0) -> 30 | N8: DIGIT - TESSERATO | O8: FALSE | Q8: INSERITO | R8: TRUE | S8: TRUE | T8: TRUE
A9: Nura | B9: SEDE Nura | C9: 46098 | E9: MAMMANO | F9: SARA | G9: 3497813495 | H9: MMMSRA06R61F205O | I9: carlotta.contina01@gmail.com | J9: 46098 | K9: 32 | L9: NURA02WS | M9: =IFERROR(__xludf.DUMMYFUNCTION("IF( K9="""", """", ROUND( IF( L9="""", K9, IF( ISERROR(FIND(""-"",L9)), K9 - VALUE(REGEXEXTRACT(L9,""(\d+)"")), K9 * (1 - VALUE(REGEXEXTRACT(L9,""(\d+)""))/100) ) ), 2 ) ) "),30.0) -> 30 | N9: DIGIT - TESSERATO | O9: FALSE | Q9: INSERITO | R9: FALSE | S9: TRUE | T9: TRUE
A10: Estefany | B10: ONLINE | C10: 46099 | E10: SITNIKOVA | F10: SOFIIA | G10: 3511913556 | H10: STNSFO06R59Z138C | I10: sitnikovasofiia42@gmail.com | J10: 46099 | K10: 32 | M10: =IFERROR(__xludf.DUMMYFUNCTION("IF( K10="""", """", ROUND( IF( L10="""", K10, IF( ISERROR(FIND(""-"",L10)), K10 - VALUE(REGEXEXTRACT(L10,""(\d+)"")), K10 * (1 - VALUE(REGEXEXTRACT(L10,""(\d+)""))/100) ) ), 2 ) ) "),32.0) -> 32 | N10: DIGIT - NON TESSERATO | O10: FALSE | Q10: INSERITO | R10: FALSE | S10: TRUE | T10: TRUE
A11: Estefany | B11: ONLINE | C11: 46102 | E11: ALVARADO | F11: ANTONELL | G11: 3444243088 | H11: LVRNNL03D61Z511D | I11: antonella.alvarado13@gmail.com | J11: 46102 | K11: 37 | M11: =IFERROR(__xludf.DUMMYFUNCTION("IF( K11="""", """", ROUND( IF( L11="""", K11, IF( ISERROR(FIND(""-"",L11)), K11 - VALUE(REGEXEXTRACT(L11,""(\d+)"")), K11 * (1 - VALUE(REGEXEXTRACT(L11,""(\d+)""))/100) ) ), 2 ) ) "),37.0) -> 37 | N11: DIGIT - TESSERATO | O11: FALSE | Q11: INSERITO | R11: TRUE | S11: FALSE | T11: TRUE
M12: =IFERROR(__xludf.DUMMYFUNCTION("IF( K12="""", """", ROUND( IF( L12="""", K12, IF( ISERROR(FIND(""-"",L12)), K12 - VALUE(REGEXEXTRACT(L12,""(\d+)"")), K12 * (1 - VALUE(REGEXEXTRACT(L12,""(\d+)""))/100) ) ), 2 ) ) ")," ") | O12: FALSE | R12: FALSE | S12: FALSE | T12: FALSE
M13: =IFERROR(__xludf.DUMMYFUNCTION("IF( K13="""", """", ROUND( IF( L13="""", K13, IF( ISERROR(FIND(""-"",L13)), K13 - VALUE(REGEXEXTRACT(L13,""(\d+)"")), K13 * (1 - VALUE(REGEXEXTRACT(L13,""(\d+)""))/100) ) ), 2 ) ) ")," ") | O13: FALSE | R13: FALSE | S13: FALSE | T13: FALSE
M14: =IFERROR(__xludf.DUMMYFUNCTION("IF( K14="""", """", ROUND( IF( L14="""", K14, IF( ISERROR(FIND(""-"",L14)), K14 - VALUE(REGEXEXTRACT(L14,""(\d+)"")), K14 * (1 - VALUE(REGEXEXTRACT(L14,""(\d+)""))/100) ) ), 2 ) ) ")," ") | O14: FALSE | R14: FALSE | S14: FALSE | T14: FALSE
M15: =IFERROR(__xludf.DUMMYFUNCTION("IF( K15="""", """", ROUND( IF( L15="""", K15, IF( ISERROR(FIND(""-"",L15)), K15 - VALUE(REGEXEXTRACT(L15,""(\d+)"")), K15 * (1 - VALUE(REGEXEXTRACT(L15,""(\d+)""))/100) ) ), 2 ) ) ")," ") | O15: FALSE | R15: FALSE | S15: FALSE | T15: FALSE
G16: SMS E MAIL INVIATE | M16: =IFERROR(__xludf.DUMMYFUNCTION("IF( K16="""", """", ROUND( IF( L16="""", K16, IF( ISERROR(FIND(""-"",L16)), K16 - VALUE(REGEXEXTRACT(L16,""(\d+)"")), K16 * (1 - VALUE(REGEXEXTRACT(L16,""(\d+)""))/100) ) ), 2 ) ) ")," ") | O16: FALSE | R16: FALSE | S16: FALSE | T16: FALSE
M17: =IFERROR(__xludf.DUMMYFUNCTION("IF( K17="""", """", ROUND( IF( L17="""", K17, IF( ISERROR(FIND(""-"",L17)), K17 - VALUE(REGEXEXTRACT(L17,""(\d+)"")), K17 * (1 - VALUE(REGEXEXTRACT(L17,""(\d+)""))/100) ) ), 2 ) ) ")," ") | O17: FALSE | R17: FALSE | S17: FALSE | T17: FALSE
M18: =IFERROR(__xludf.DUMMYFUNCTION("IF( K18="""", """", ROUND( IF( L18="""", K18, IF( ISERROR(FIND(""-"",L18)), K18 - VALUE(REGEXEXTRACT(L18,""(\d+)"")), K18 * (1 - VALUE(REGEXEXTRACT(L18,""(\d+)""))/100) ) ), 2 ) ) ")," ") | O18: FALSE | R18: FALSE | S18: FALSE | T18: FALSE
M19: =IFERROR(__xludf.DUMMYFUNCTION("IF( K19="""", """", ROUND( IF( L19="""", K19, IF( ISERROR(FIND(""-"",L19)), K19 - VALUE(REGEXEXTRACT(L19,""(\d+)"")), K19 * (1 - VALUE(REGEXEXTRACT(L19,""(\d+)""))/100) ) ), 2 ) ) ")," ") | O19: FALSE | R19: FALSE | S19: FALSE | T19: FALSE
M20: =IFERROR(__xludf.DUMMYFUNCTION("IF( K20="""", """", ROUND( IF( L20="""", K20, IF( ISERROR(FIND(""-"",L20)), K20 - VALUE(REGEXEXTRACT(L20,""(\d+)"")), K20 * (1 - VALUE(REGEXEXTRACT(L20,""(\d+)""))/100) ) ), 2 ) ) ")," ") | O20: FALSE | R20: FALSE | S20: FALSE | T20: FALSE
M21: =IFERROR(__xludf.DUMMYFUNCTION("IF( K21="""", """", ROUND( IF( L21="""", K21, IF( ISERROR(FIND(""-"",L21)), K21 - VALUE(REGEXEXTRACT(L21,""(\d+)"")), K21 * (1 - VALUE(REGEXEXTRACT(L21,""(\d+)""))/100) ) ), 2 ) ) ")," ") | O21: FALSE | R21: FALSE | S21: FALSE | T21: FALSE
M22: =IFERROR(__xludf.DUMMYFUNCTION("IF( K22="""", """", ROUND( IF( L22="""", K22, IF( ISERROR(FIND(""-"",L22)), K22 - VALUE(REGEXEXTRACT(L22,""(\d+)"")), K22 * (1 - VALUE(REGEXEXTRACT(L22,""(\d+)""))/100) ) ), 2 ) ) ")," ") | O22: FALSE | R22: FALSE | S22: FALSE | T22: FALSE
M23: =IFERROR(__xludf.DUMMYFUNCTION("IF( K23="""", """", ROUND( IF( L23="""", K23, IF( ISERROR(FIND(""-"",L23)), K23 - VALUE(REGEXEXTRACT(L23,""(\d+)"")), K23 * (1 - VALUE(REGEXEXTRACT(L23,""(\d+)""))/100) ) ), 2 ) ) ")," ") | O23: FALSE | R23: FALSE | S23: FALSE | T23: FALSE
M24: =IFERROR(__xludf.DUMMYFUNCTION("IF( K24="""", """", ROUND( IF( L24="""", K24, IF( ISERROR(FIND(""-"",L24)), K24 - VALUE(REGEXEXTRACT(L24,""(\d+)"")), K24 * (1 - VALUE(REGEXEXTRACT(L24,""(\d+)""))/100) ) ), 2 ) ) ")," ") | O24: FALSE | R24: FALSE | S24: FALSE | T24: FALSE
M25: =IFERROR(__xludf.DUMMYFUNCTION("IF( K25="""", """", ROUND( IF( L25="""", K25, IF( ISERROR(FIND(""-"",L25)), K25 - VALUE(REGEXEXTRACT(L25,""(\d+)"")), K25 * (1 - VALUE(REGEXEXTRACT(L25,""(\d+)""))/100) ) ), 2 ) ) ")," ") | O25: FALSE | R25: FALSE | S25: FALSE | T25: FALSE
M26: =IFERROR(__xludf.DUMMYFUNCTION("IF( K26="""", """", ROUND( IF( L26="""", K26, IF( ISERROR(FIND(""-"",L26)), K26 - VALUE(REGEXEXTRACT(L26,""(\d+)"")), K26 * (1 - VALUE(REGEXEXTRACT(L26,""(\d+)""))/100) ) ), 2 ) ) ")," ") | O26: FALSE | R26: FALSE | S26: FALSE | T26: FALSE
M27: =IFERROR(__xludf.DUMMYFUNCTION("IF( K27="""", """", ROUND( IF( L27="""", K27, IF( ISERROR(FIND(""-"",L27)), K27 - VALUE(REGEXEXTRACT(L27,""(\d+)"")), K27 * (1 - VALUE(REGEXEXTRACT(L27,""(\d+)""))/100) ) ), 2 ) ) ")," ") | O27: FALSE | R27: FALSE | S27: FALSE | T27: FALSE
M28: =IFERROR(__xludf.DUMMYFUNCTION("IF( K28="""", """", ROUND( IF( L28="""", K28, IF( ISERROR(FIND(""-"",L28)), K28 - VALUE(REGEXEXTRACT(L28,""(\d+)"")), K28 * (1 - VALUE(REGEXEXTRACT(L28,""(\d+)""))/100) ) ), 2 ) ) ")," ") | O28: FALSE | R28: FALSE | S28: FALSE | T28: FALSE
M29: =IFERROR(__xludf.DUMMYFUNCTION("IF( K29="""", """", ROUND( IF( L29="""", K29, IF( ISERROR(FIND(""-"",L29)), K29 - VALUE(REGEXEXTRACT(L29,""(\d+)"")), K29 * (1 - VALUE(REGEXEXTRACT(L29,""(\d+)""))/100) ) ), 2 ) ) ")," ") | O29: FALSE | R29: FALSE | S29: FALSE | T29: FALSE
M30: =IFERROR(__xludf.DUMMYFUNCTION("IF( K30="""", """", ROUND( IF( L30="""", K30, IF( ISERROR(FIND(""-"",L30)), K30 - VALUE(REGEXEXTRACT(L30,""(\d+)"")), K30 * (1 - VALUE(REGEXEXTRACT(L30,""(\d+)""))/100) ) ), 2 ) ) ")," ") | O30: FALSE | R30: FALSE | S30: FALSE | T30: FALSE
M31: =IFERROR(__xludf.DUMMYFUNCTION("IF( K31="""", """", ROUND( IF( L31="""", K31, IF( ISERROR(FIND(""-"",L31)), K31 - VALUE(REGEXEXTRACT(L31,""(\d+)"")), K31 * (1 - VALUE(REGEXEXTRACT(L31,""(\d+)""))/100) ) ), 2 ) ) ")," ") | O31: FALSE | R31: FALSE | S31: FALSE | T31: FALSE
M32: =IFERROR(__xludf.DUMMYFUNCTION("IF( K32="""", """", ROUND( IF( L32="""", K32, IF( ISERROR(FIND(""-"",L32)), K32 - VALUE(REGEXEXTRACT(L32,""(\d+)"")), K32 * (1 - VALUE(REGEXEXTRACT(L32,""(\d+)""))/100) ) ), 2 ) ) ")," ") | O32: FALSE | R32: FALSE | S32: FALSE | T32: FALSE
M33: =IFERROR(__xludf.DUMMYFUNCTION("IF( K33="""", """", ROUND( IF( L33="""", K33, IF( ISERROR(FIND(""-"",L33)), K33 - VALUE(REGEXEXTRACT(L33,""(\d+)"")), K33 * (1 - VALUE(REGEXEXTRACT(L33,""(\d+)""))/100) ) ), 2 ) ) ")," ") | O33: FALSE | R33: FALSE | S33: FALSE | T33: FALSE
M34: =IFERROR(__xludf.DUMMYFUNCTION("IF( K34="""", """", ROUND( IF( L34="""", K34, IF( ISERROR(FIND(""-"",L34)), K34 - VALUE(REGEXEXTRACT(L34,""(\d+)"")), K34 * (1 - VALUE(REGEXEXTRACT(L34,""(\d+)""))/100) ) ), 2 ) ) ")," ") | O34: FALSE | R34: FALSE | S34: FALSE | T34: FALSE
M35: =IFERROR(__xludf.DUMMYFUNCTION("IF( K35="""", """", ROUND( IF( L35="""", K35, IF( ISERROR(FIND(""-"",L35)), K35 - VALUE(REGEXEXTRACT(L35,""(\d+)"")), K35 * (1 - VALUE(REGEXEXTRACT(L35,""(\d+)""))/100) ) ), 2 ) ) ")," ") | O35: FALSE | R35: FALSE | S35: FALSE | T35: FALSE
M36: =IFERROR(__xludf.DUMMYFUNCTION("IF( K36="""", """", ROUND( IF( L36="""", K36, IF( ISERROR(FIND(""-"",L36)), K36 - VALUE(REGEXEXTRACT(L36,""(\d+)"")), K36 * (1 - VALUE(REGEXEXTRACT(L36,""(\d+)""))/100) ) ), 2 ) ) ")," ") | O36: FALSE | R36: FALSE | S36: FALSE | T36: FALSE
M37: =IFERROR(__xludf.DUMMYFUNCTION("IF( K37="""", """", ROUND( IF( L37="""", K37, IF( ISERROR(FIND(""-"",L37)), K37 - VALUE(REGEXEXTRACT(L37,""(\d+)"")), K37 * (1 - VALUE(REGEXEXTRACT(L37,""(\d+)""))/100) ) ), 2 ) ) ")," ") | O37: FALSE | R37: FALSE | S37: FALSE | T37: FALSE
M38: =IFERROR(__xludf.DUMMYFUNCTION("IF( K38="""", """", ROUND( IF( L38="""", K38, IF( ISERROR(FIND(""-"",L38)), K38 - VALUE(REGEXEXTRACT(L38,""(\d+)"")), K38 * (1 - VALUE(REGEXEXTRACT(L38,""(\d+)""))/100) ) ), 2 ) ) ")," ") | O38: FALSE | R38: FALSE | S38: FALSE | T38: FALSE
M39: =IFERROR(__xludf.DUMMYFUNCTION("IF( K39="""", """", ROUND( IF( L39="""", K39, IF( ISERROR(FIND(""-"",L39)), K39 - VALUE(REGEXEXTRACT(L39,""(\d+)"")), K39 * (1 - VALUE(REGEXEXTRACT(L39,""(\d+)""))/100) ) ), 2 ) ) ")," ") | O39: FALSE | R39: FALSE | S39: FALSE | T39: FALSE
M40: =IFERROR(__xludf.DUMMYFUNCTION("IF( K40="""", """", ROUND( IF( L40="""", K40, IF( ISERROR(FIND(""-"",L40)), K40 - VALUE(REGEXEXTRACT(L40,""(\d+)"")), K40 * (1 - VALUE(REGEXEXTRACT(L40,""(\d+)""))/100) ) ), 2 ) ) ")," ") | O40: FALSE | R40: FALSE | S40: FALSE | T40: FALSE
M41: =IFERROR(__xludf.DUMMYFUNCTION("IF( K41="""", """", ROUND( IF( L41="""", K41, IF( ISERROR(FIND(""-"",L41)), K41 - VALUE(REGEXEXTRACT(L41,""(\d+)"")), K41 * (1 - VALUE(REGEXEXTRACT(L41,""(\d+)""))/100) ) ), 2 ) ) ")," ") | O41: FALSE | R41: FALSE | S41: FALSE | T41: FALSE
M42: =IFERROR(__xludf.DUMMYFUNCTION("IF( K42="""", """", ROUND( IF( L42="""", K42, IF( ISERROR(FIND(""-"",L42)), K42 - VALUE(REGEXEXTRACT(L42,""(\d+)"")), K42 * (1 - VALUE(REGEXEXTRACT(L42,""(\d+)""))/100) ) ), 2 ) ) ")," ") | O42: FALSE | R42: FALSE | S42: FALSE | T42: FALSE
M43: =IFERROR(__xludf.DUMMYFUNCTION("IF( K43="""", """", ROUND( IF( L43="""", K43, IF( ISERROR(FIND(""-"",L43)), K43 - VALUE(REGEXEXTRACT(L43,""(\d+)"")), K43 * (1 - VALUE(REGEXEXTRACT(L43,""(\d+)""))/100) ) ), 2 ) ) ")," ") | O43: FALSE | R43: FALSE | S43: FALSE | T43: FALSE
M44: =IFERROR(__xludf.DUMMYFUNCTION("IF( K44="""", """", ROUND( IF( L44="""", K44, IF( ISERROR(FIND(""-"",L44)), K44 - VALUE(REGEXEXTRACT(L44,""(\d+)"")), K44 * (1 - VALUE(REGEXEXTRACT(L44,""(\d+)""))/100) ) ), 2 ) ) ")," ") | O44: FALSE | R44: FALSE | S44: FALSE | T44: FALSE
M45: =IFERROR(__xludf.DUMMYFUNCTION("IF( K45="""", """", ROUND( IF( L45="""", K45, IF( ISERROR(FIND(""-"",L45)), K45 - VALUE(REGEXEXTRACT(L45,""(\d+)"")), K45 * (1 - VALUE(REGEXEXTRACT(L45,""(\d+)""))/100) ) ), 2 ) ) ")," ") | O45: FALSE | R45: FALSE | S45: FALSE | T45: FALSE
M46: =IFERROR(__xludf.DUMMYFUNCTION("IF( K46="""", """", ROUND( IF( L46="""", K46, IF( ISERROR(FIND(""-"",L46)), K46 - VALUE(REGEXEXTRACT(L46,""(\d+)"")), K46 * (1 - VALUE(REGEXEXTRACT(L46,""(\d+)""))/100) ) ), 2 ) ) ")," ") | O46: FALSE | R46: FALSE | S46: FALSE | T46: FALSE
M47: =IFERROR(__xludf.DUMMYFUNCTION("IF( K47="""", """", ROUND( IF( L47="""", K47, IF( ISERROR(FIND(""-"",L47)), K47 - VALUE(REGEXEXTRACT(L47,""(\d+)"")), K47 * (1 - VALUE(REGEXEXTRACT(L47,""(\d+)""))/100) ) ), 2 ) ) ")," ") | O47: FALSE | R47: FALSE | S47: FALSE | T47: FALSE
M48: =IFERROR(__xludf.DUMMYFUNCTION("IF( K48="""", """", ROUND( IF( L48="""", K48, IF( ISERROR(FIND(""-"",L48)), K48 - VALUE(REGEXEXTRACT(L48,""(\d+)"")), K48 * (1 - VALUE(REGEXEXTRACT(L48,""(\d+)""))/100) ) ), 2 ) ) ")," ") | O48: FALSE | R48: FALSE | S48: FALSE | T48: FALSE
M49: =IFERROR(__xludf.DUMMYFUNCTION("IF( K49="""", """", ROUND( IF( L49="""", K49, IF( ISERROR(FIND(""-"",L49)), K49 - VALUE(REGEXEXTRACT(L49,""(\d+)"")), K49 * (1 - VALUE(REGEXEXTRACT(L49,""(\d+)""))/100) ) ), 2 ) ) ")," ") | O49: FALSE | R49: FALSE | S49: FALSE | T49: FALSE
M50: =IFERROR(__xludf.DUMMYFUNCTION("IF( K50="""", """", ROUND( IF( L50="""", K50, IF( ISERROR(FIND(""-"",L50)), K50 - VALUE(REGEXEXTRACT(L50,""(\d+)"")), K50 * (1 - VALUE(REGEXEXTRACT(L50,""(\d+)""))/100) ) ), 2 ) ) ")," ") | O50: FALSE | R50: FALSE | S50: FALSE | T50: FALSE
M51: =IFERROR(__xludf.DUMMYFUNCTION("IF( K51="""", """", ROUND( IF( L51="""", K51, IF( ISERROR(FIND(""-"",L51)), K51 - VALUE(REGEXEXTRACT(L51,""(\d+)"")), K51 * (1 - VALUE(REGEXEXTRACT(L51,""(\d+)""))/100) ) ), 2 ) ) ")," ") | O51: FALSE | R51: FALSE | S51: FALSE | T51: FALSE
M52: =IFERROR(__xludf.DUMMYFUNCTION("IF( K52="""", """", ROUND( IF( L52="""", K52, IF( ISERROR(FIND(""-"",L52)), K52 - VALUE(REGEXEXTRACT(L52,""(\d+)"")), K52 * (1 - VALUE(REGEXEXTRACT(L52,""(\d+)""))/100) ) ), 2 ) ) ")," ") | O52: FALSE | R52: FALSE | S52: FALSE | T52: FALSE
M53: =IFERROR(__xludf.DUMMYFUNCTION("IF( K53="""", """", ROUND( IF( L53="""", K53, IF( ISERROR(FIND(""-"",L53)), K53 - VALUE(REGEXEXTRACT(L53,""(\d+)"")), K53 * (1 - VALUE(REGEXEXTRACT(L53,""(\d+)""))/100) ) ), 2 ) ) ")," ") | O53: FALSE | R53: FALSE | S53: FALSE | T53: FALSE
M54: =IFERROR(__xludf.DUMMYFUNCTION("IF( K54="""", """", ROUND( IF( L54="""", K54, IF( ISERROR(FIND(""-"",L54)), K54 - VALUE(REGEXEXTRACT(L54,""(\d+)"")), K54 * (1 - VALUE(REGEXEXTRACT(L54,""(\d+)""))/100) ) ), 2 ) ) ")," ") | O54: FALSE | R54: FALSE | S54: FALSE | T54: FALSE
M55: =IFERROR(__xludf.DUMMYFUNCTION("IF( K55="""", """", ROUND( IF( L55="""", K55, IF( ISERROR(FIND(""-"",L55)), K55 - VALUE(REGEXEXTRACT(L55,""(\d+)"")), K55 * (1 - VALUE(REGEXEXTRACT(L55,""(\d+)""))/100) ) ), 2 ) ) ")," ") | O55: FALSE | R55: FALSE | S55: FALSE | T55: FALSE
M56: =IFERROR(__xludf.DUMMYFUNCTION("IF( K56="""", """", ROUND( IF( L56="""", K56, IF( ISERROR(FIND(""-"",L56)), K56 - VALUE(REGEXEXTRACT(L56,""(\d+)"")), K56 * (1 - VALUE(REGEXEXTRACT(L56,""(\d+)""))/100) ) ), 2 ) ) ")," ") | O56: FALSE | R56: FALSE | S56: FALSE | T56: FALSE
M57: =IFERROR(__xludf.DUMMYFUNCTION("IF( K57="""", """", ROUND( IF( L57="""", K57, IF( ISERROR(FIND(""-"",L57)), K57 - VALUE(REGEXEXTRACT(L57,""(\d+)"")), K57 * (1 - VALUE(REGEXEXTRACT(L57,""(\d+)""))/100) ) ), 2 ) ) ")," ") | O57: FALSE | R57: FALSE | S57: FALSE | T57: FALSE
M58: =IFERROR(__xludf.DUMMYFUNCTION("IF( K58="""", """", ROUND( IF( L58="""", K58, IF( ISERROR(FIND(""-"",L58)), K58 - VALUE(REGEXEXTRACT(L58,""(\d+)"")), K58 * (1 - VALUE(REGEXEXTRACT(L58,""(\d+)""))/100) ) ), 2 ) ) ")," ") | O58: FALSE | R58: FALSE | S58: FALSE | T58: FALSE
M59: =IFERROR(__xludf.DUMMYFUNCTION("IF( K59="""", """", ROUND( IF( L59="""", K59, IF( ISERROR(FIND(""-"",L59)), K59 - VALUE(REGEXEXTRACT(L59,""(\d+)"")), K59 * (1 - VALUE(REGEXEXTRACT(L59,""(\d+)""))/100) ) ), 2 ) ) ")," ") | O59: FALSE | R59: FALSE | S59: FALSE | T59: FALSE
M60: =IFERROR(__xludf.DUMMYFUNCTION("IF( K60="""", """", ROUND( IF( L60="""", K60, IF( ISERROR(FIND(""-"",L60)), K60 - VALUE(REGEXEXTRACT(L60,""(\d+)"")), K60 * (1 - VALUE(REGEXEXTRACT(L60,""(\d+)""))/100) ) ), 2 ) ) ")," ") | O60: FALSE | R60: FALSE | S60: FALSE | T60: FALSE
M61: =IFERROR(__xludf.DUMMYFUNCTION("IF( K61="""", """", ROUND( IF( L61="""", K61, IF( ISERROR(FIND(""-"",L61)), K61 - VALUE(REGEXEXTRACT(L61,""(\d+)"")), K61 * (1 - VALUE(REGEXEXTRACT(L61,""(\d+)""))/100) ) ), 2 ) ) ")," ") | O61: FALSE | R61: FALSE | S61: FALSE | T61: FALSE
M62: =IFERROR(__xludf.DUMMYFUNCTION("IF( K62="""", """", ROUND( IF( L62="""", K62, IF( ISERROR(FIND(""-"",L62)), K62 - VALUE(REGEXEXTRACT(L62,""(\d+)"")), K62 * (1 - VALUE(REGEXEXTRACT(L62,""(\d+)""))/100) ) ), 2 ) ) ")," ") | O62: FALSE | R62: FALSE | S62: FALSE | T62: FALSE
M63: =IFERROR(__xludf.DUMMYFUNCTION("IF( K63="""", """", ROUND( IF( L63="""", K63, IF( ISERROR(FIND(""-"",L63)), K63 - VALUE(REGEXEXTRACT(L63,""(\d+)"")), K63 * (1 - VALUE(REGEXEXTRACT(L63,""(\d+)""))/100) ) ), 2 ) ) ")," ") | O63: FALSE | R63: FALSE | S63: FALSE | T63: FALSE
M64: =IFERROR(__xludf.DUMMYFUNCTION("IF( K64="""", """", ROUND( IF( L64="""", K64, IF( ISERROR(FIND(""-"",L64)), K64 - VALUE(REGEXEXTRACT(L64,""(\d+)"")), K64 * (1 - VALUE(REGEXEXTRACT(L64,""(\d+)""))/100) ) ), 2 ) ) ")," ") | O64: FALSE | R64: FALSE | S64: FALSE | T64: FALSE
M65: =IFERROR(__xludf.DUMMYFUNCTION("IF( K65="""", """", ROUND( IF( L65="""", K65, IF( ISERROR(FIND(""-"",L65)), K65 - VALUE(REGEXEXTRACT(L65,""(\d+)"")), K65 * (1 - VALUE(REGEXEXTRACT(L65,""(\d+)""))/100) ) ), 2 ) ) ")," ") | O65: FALSE | R65: FALSE | S65: FALSE | T65: FALSE
M66: =IFERROR(__xludf.DUMMYFUNCTION("IF( K66="""", """", ROUND( IF( L66="""", K66, IF( ISERROR(FIND(""-"",L66)), K66 - VALUE(REGEXEXTRACT(L66,""(\d+)"")), K66 * (1 - VALUE(REGEXEXTRACT(L66,""(\d+)""))/100) ) ), 2 ) ) ")," ") | O66: FALSE | R66: FALSE | S66: FALSE | T66: FALSE
M67: =IFERROR(__xludf.DUMMYFUNCTION("IF( K67="""", """", ROUND( IF( L67="""", K67, IF( ISERROR(FIND(""-"",L67)), K67 - VALUE(REGEXEXTRACT(L67,""(\d+)"")), K67 * (1 - VALUE(REGEXEXTRACT(L67,""(\d+)""))/100) ) ), 2 ) ) ")," ") | O67: FALSE | R67: FALSE | S67: FALSE | T67: FALSE
M68: =IFERROR(__xludf.DUMMYFUNCTION("IF( K68="""", """", ROUND( IF( L68="""", K68, IF( ISERROR(FIND(""-"",L68)), K68 - VALUE(REGEXEXTRACT(L68,""(\d+)"")), K68 * (1 - VALUE(REGEXEXTRACT(L68,""(\d+)""))/100) ) ), 2 ) ) ")," ") | O68: FALSE | R68: FALSE | S68: FALSE | T68: FALSE
M69: =IFERROR(__xludf.DUMMYFUNCTION("IF( K69="""", """", ROUND( IF( L69="""", K69, IF( ISERROR(FIND(""-"",L69)), K69 - VALUE(REGEXEXTRACT(L69,""(\d+)"")), K69 * (1 - VALUE(REGEXEXTRACT(L69,""(\d+)""))/100) ) ), 2 ) ) ")," ") | O69: FALSE | R69: FALSE | S69: FALSE | T69: FALSE
M70: =IFERROR(__xludf.DUMMYFUNCTION("IF( K70="""", """", ROUND( IF( L70="""", K70, IF( ISERROR(FIND(""-"",L70)), K70 - VALUE(REGEXEXTRACT(L70,""(\d+)"")), K70 * (1 - VALUE(REGEXEXTRACT(L70,""(\d+)""))/100) ) ), 2 ) ) ")," ") | O70: FALSE | R70: FALSE | S70: FALSE | T70: FALSE
M71: =IFERROR(__xludf.DUMMYFUNCTION("IF( K71="""", """", ROUND( IF( L71="""", K71, IF( ISERROR(FIND(""-"",L71)), K71 - VALUE(REGEXEXTRACT(L71,""(\d+)"")), K71 * (1 - VALUE(REGEXEXTRACT(L71,""(\d+)""))/100) ) ), 2 ) ) ")," ") | O71: FALSE | R71: FALSE | S71: FALSE | T71: FALSE
M72: =IFERROR(__xludf.DUMMYFUNCTION("IF( K72="""", """", ROUND( IF( L72="""", K72, IF( ISERROR(FIND(""-"",L72)), K72 - VALUE(REGEXEXTRACT(L72,""(\d+)"")), K72 * (1 - VALUE(REGEXEXTRACT(L72,""(\d+)""))/100) ) ), 2 ) ) ")," ") | O72: FALSE | R72: FALSE | S72: FALSE | T72: FALSE
M73: =IFERROR(__xludf.DUMMYFUNCTION("IF( K73="""", """", ROUND( IF( L73="""", K73, IF( ISERROR(FIND(""-"",L73)), K73 - VALUE(REGEXEXTRACT(L73,""(\d+)"")), K73 * (1 - VALUE(REGEXEXTRACT(L73,""(\d+)""))/100) ) ), 2 ) ) ")," ") | O73: FALSE | R73: FALSE | S73: FALSE | T73: FALSE
M74: =IFERROR(__xludf.DUMMYFUNCTION("IF( K74="""", """", ROUND( IF( L74="""", K74, IF( ISERROR(FIND(""-"",L74)), K74 - VALUE(REGEXEXTRACT(L74,""(\d+)"")), K74 * (1 - VALUE(REGEXEXTRACT(L74,""(\d+)""))/100) ) ), 2 ) ) ")," ") | O74: FALSE | R74: FALSE | S74: FALSE | T74: FALSE
M75: =IFERROR(__xludf.DUMMYFUNCTION("IF( K75="""", """", ROUND( IF( L75="""", K75, IF( ISERROR(FIND(""-"",L75)), K75 - VALUE(REGEXEXTRACT(L75,""(\d+)"")), K75 * (1 - VALUE(REGEXEXTRACT(L75,""(\d+)""))/100) ) ), 2 ) ) ")," ") | O75: FALSE | R75: FALSE | S75: FALSE | T75: FALSE
M76: =IFERROR(__xludf.DUMMYFUNCTION("IF( K76="""", """", ROUND( IF( L76="""", K76, IF( ISERROR(FIND(""-"",L76)), K76 - VALUE(REGEXEXTRACT(L76,""(\d+)"")), K76 * (1 - VALUE(REGEXEXTRACT(L76,""(\d+)""))/100) ) ), 2 ) ) ")," ") | O76: FALSE | R76: FALSE | S76: FALSE | T76: FALSE
M77: =IFERROR(__xludf.DUMMYFUNCTION("IF( K77="""", """", ROUND( IF( L77="""", K77, IF( ISERROR(FIND(""-"",L77)), K77 - VALUE(REGEXEXTRACT(L77,""(\d+)"")), K77 * (1 - VALUE(REGEXEXTRACT(L77,""(\d+)""))/100) ) ), 2 ) ) ")," ") | O77: FALSE | R77: FALSE | S77: FALSE | T77: FALSE
M78: =IFERROR(__xludf.DUMMYFUNCTION("IF( K78="""", """", ROUND( IF( L78="""", K78, IF( ISERROR(FIND(""-"",L78)), K78 - VALUE(REGEXEXTRACT(L78,""(\d+)"")), K78 * (1 - VALUE(REGEXEXTRACT(L78,""(\d+)""))/100) ) ), 2 ) ) ")," ") | O78: FALSE | R78: FALSE | S78: FALSE | T78: FALSE
M79: =IFERROR(__xludf.DUMMYFUNCTION("IF( K79="""", """", ROUND( IF( L79="""", K79, IF( ISERROR(FIND(""-"",L79)), K79 - VALUE(REGEXEXTRACT(L79,""(\d+)"")), K79 * (1 - VALUE(REGEXEXTRACT(L79,""(\d+)""))/100) ) ), 2 ) ) ")," ") | O79: FALSE | R79: FALSE | S79: FALSE | T79: FALSE
M80: =IFERROR(__xludf.DUMMYFUNCTION("IF( K80="""", """", ROUND( IF( L80="""", K80, IF( ISERROR(FIND(""-"",L80)), K80 - VALUE(REGEXEXTRACT(L80,""(\d+)"")), K80 * (1 - VALUE(REGEXEXTRACT(L80,""(\d+)""))/100) ) ), 2 ) ) ")," ") | O80: FALSE | R80: FALSE | S80: FALSE | T80: FALSE
M81: =IFERROR(__xludf.DUMMYFUNCTION("IF( K81="""", """", ROUND( IF( L81="""", K81, IF( ISERROR(FIND(""-"",L81)), K81 - VALUE(REGEXEXTRACT(L81,""(\d+)"")), K81 * (1 - VALUE(REGEXEXTRACT(L81,""(\d+)""))/100) ) ), 2 ) ) ")," ") | O81: FALSE | R81: FALSE | S81: FALSE | T81: FALSE
M82: =IFERROR(__xludf.DUMMYFUNCTION("IF( K82="""", """", ROUND( IF( L82="""", K82, IF( ISERROR(FIND(""-"",L82)), K82 - VALUE(REGEXEXTRACT(L82,""(\d+)"")), K82 * (1 - VALUE(REGEXEXTRACT(L82,""(\d+)""))/100) ) ), 2 ) ) ")," ") | O82: FALSE | R82: FALSE | S82: FALSE | T82: FALSE
M83: =IFERROR(__xludf.DUMMYFUNCTION("IF( K83="""", """", ROUND( IF( L83="""", K83, IF( ISERROR(FIND(""-"",L83)), K83 - VALUE(REGEXEXTRACT(L83,""(\d+)"")), K83 * (1 - VALUE(REGEXEXTRACT(L83,""(\d+)""))/100) ) ), 2 ) ) ")," ") | O83: FALSE | R83: FALSE | S83: FALSE | T83: FALSE
A84: TOTALE | B84: =COUNTIF(B4:B83,"ONLINE")+COUNTIF(B4:B83,"SEDE*") -> 8 | C84: TOTALE | D84: =COUNTIF(D4:D83, "*") -> 0 | E84: =COUNTIF(E4:E83, "*") -> 8 | F84: =COUNTIF(F4:F83, "*") -> 8 | G84: =COUNTA(G4:G83) -> 9 | H84: =COUNTIF(H4:H83, "*") -> 8 | I84: =COUNTIF(I4:I83, "*") -> 8 | J84: TOTALE | K84: =SUM(K4:K83) -> 271 | L84: =COUNTIF(L4:L83, "*") -> 3 | M84: =SUM(M4:M83) -> 265 | N84: =COUNTIF(N4:N83, "*") -> 8 | O84: =SUMPRODUCT(--O4:O83) -> 0 | P84: =COUNTIF(P4:P83, "*") -> 0 | Q84: =COUNTIF(Q4:Q83, "*") -> 8 | R84: =SUMPRODUCT(--R4:R83) -> 2 | S84: =SUMPRODUCT(--S4:S83) -> 7 | T84: =SUMPRODUCT(--T4:T83) -> 8
A85: SEDE | B85: =COUNTIF(B4:B83, "SEDE*") -> 2 | D85: TOTALI WS 1 | E85: LISTA PREZZI | F85: =IFERROR(__xludf.DUMMYFUNCTION("IFERROR(TRANSPOSE(SORT(UNIQUE(FILTER($M$4:$M$83,$M$4:$M$83<>"""")))),"""")"),30.0) -> 30 | G85: =IFERROR(__xludf.DUMMYFUNCTION("""COMPUTED_VALUE"""),32.0) -> 32 | H85: =IFERROR(__xludf.DUMMYFUNCTION("""COMPUTED_VALUE"""),37.0) -> 37 | P85: TOTALE | Q85: =IF(SUM(F87:O87)=0,"",SUM(F87:O87)) -> 60 | R85: Verifica | S85: =IF(SUM(M84) = SUM(Q85:Q89), "OK", "ERRORE") -> OK
A86: ONLINE | B86: =COUNTIF(B4:B83, "ONLINE") -> 6 | E86: PERSONE SEDE | F86: =IF( F$85="", "", COUNTIFS($B$4:$B$83,"*SEDE*",$M$4:$M$83,F$85) ) -> 2 | G86: =IF( G$85="", "", COUNTIFS($B$4:$B$83,"*SEDE*",$M$4:$M$83,G$85) ) -> 0 | H86: =IF( H$85="", "", COUNTIFS($B$4:$B$83,"*SEDE*",$M$4:$M$83,H$85) ) -> 0 | I86: =IF( I$85="", "", COUNTIFS($B$4:$B$83,"*SEDE*",$M$4:$M$83,I$85) ) | J86: =IF( J$85="", "", COUNTIFS($B$4:$B$83,"*SEDE*",$M$4:$M$83,J$85) ) | K86: =IF( K$85="", "", COUNTIFS($B$4:$B$83,"*SEDE*",$M$4:$M$83,K$85) ) | L86: =IF( L$85="", "", COUNTIFS($B$4:$B$83,"*SEDE*",$M$4:$M$83,L$85) ) | M86: =IF( M$85="", "", COUNTIFS($B$4:$B$83,"*SEDE*",$M$4:$M$83,M$85) ) | ... O86: =IF( O$85="", "", COUNTIFS($B$4:$B$83,"*SEDE*",$M$4:$M$83,O$85) )
E87: subTOTALE SEDE | F87: =IF( F$85="", "", SUMIFS($M$4:$M$83,$B$4:$B$83,"*SEDE*",$M$4:$M$83,F$85) ) -> 60 | G87: =IF( G$85="", "", SUMIFS($M$4:$M$83,$B$4:$B$83,"*SEDE*",$M$4:$M$83,G$85) ) -> 0 | H87: =IF( H$85="", "", SUMIFS($M$4:$M$83,$B$4:$B$83,"*SEDE*",$M$4:$M$83,H$85) ) -> 0 | I87: =IF( I$85="", "", SUMIFS($M$4:$M$83,$B$4:$B$83,"*SEDE*",$M$4:$M$83,I$85) ) | J87: =IF( J$85="", "", SUMIFS($M$4:$M$83,$B$4:$B$83,"*SEDE*",$M$4:$M$83,J$85) ) | K87: =IF( K$85="", "", SUMIFS($M$4:$M$83,$B$4:$B$83,"*SEDE*",$M$4:$M$83,K$85) ) | L87: =IF( L$85="", "", SUMIFS($M$4:$M$83,$B$4:$B$83,"*SEDE*",$M$4:$M$83,L$85) ) | M87: =IF( M$85="", "", SUMIFS($M$4:$M$83,$B$4:$B$83,"*SEDE*",$M$4:$M$83,M$85) ) | ... O87: =IF( O$85="", "", SUMIFS($M$4:$M$83,$B$4:$B$83,"*SEDE*",$M$4:$M$83,O$85) )
E88: PERSONE ONLINE | F88: =IF( F$85="", "", COUNTIFS($B$4:$B$83,"*ONLINE*",$M$4:$M$83,F$85) ) -> 1 | G88: =IF( G$85="", "", COUNTIFS($B$4:$B$83,"*ONLINE*",$M$4:$M$83,G$85) ) -> 2 | H88: =IF( H$85="", "", COUNTIFS($B$4:$B$83,"*ONLINE*",$M$4:$M$83,H$85) ) -> 3 | I88: =IF( I$85="", "", COUNTIFS($B$4:$B$83,"*ONLINE*",$M$4:$M$83,I$85) ) | J88: =IF( J$85="", "", COUNTIFS($B$4:$B$83,"*ONLINE*",$M$4:$M$83,J$85) ) | K88: =IF( K$85="", "", COUNTIFS($B$4:$B$83,"*ONLINE*",$M$4:$M$83,K$85) ) | L88: =IF( L$85="", "", COUNTIFS($B$4:$B$83,"*ONLINE*",$M$4:$M$83,L$85) ) | M88: =IF( M$85="", "", COUNTIFS($B$4:$B$83,"*ONLINE*",$M$4:$M$83,M$85) ) | ... O88: =IF( O$85="", "", COUNTIFS($B$4:$B$83,"*ONLINE*",$M$4:$M$83,O$85) ) | P88: TOTALE | Q88: =IF(SUM(F89:O89)=0,"",SUM(F89:O89)) -> 205
E89: subTOTALE ONLINE | F89: =IF( F$85="", "", SUMIFS($M$4:$M$83,$B$4:$B$83,"*ONLINE*",$M$4:$M$83,F$85) ) -> 30 | G89: =IF( G$85="", "", SUMIFS($M$4:$M$83,$B$4:$B$83,"*ONLINE*",$M$4:$M$83,G$85) ) -> 64 | H89: =IF( H$85="", "", SUMIFS($M$4:$M$83,$B$4:$B$83,"*ONLINE*",$M$4:$M$83,H$85) ) -> 111 | I89: =IF( I$85="", "", SUMIFS($M$4:$M$83,$B$4:$B$83,"*ONLINE*",$M$4:$M$83,I$85) ) | J89: =IF( J$85="", "", SUMIFS($M$4:$M$83,$B$4:$B$83,"*ONLINE*",$M$4:$M$83,J$85) ) | K89: =IF( K$85="", "", SUMIFS($M$4:$M$83,$B$4:$B$83,"*ONLINE*",$M$4:$M$83,K$85) ) | L89: =IF( L$85="", "", SUMIFS($M$4:$M$83,$B$4:$B$83,"*ONLINE*",$M$4:$M$83,L$85) ) | M89: =IF( M$85="", "", SUMIFS($M$4:$M$83,$B$4:$B$83,"*ONLINE*",$M$4:$M$83,M$85) ) | ... O89: =IF( O$85="", "", SUMIFS($M$4:$M$83,$B$4:$B$83,"*ONLINE*",$M$4:$M$83,O$85) )
C90: LISTA D'ATTESA oppure [ORARIO]_[GENERE] (€X entro il XX/XX compreso → €Y entro il YY/YY compreso → €Z il giorno stesso)
M91: =IFERROR(__xludf.DUMMYFUNCTION("IF( K91="""", """", ROUND( IF( L91="""", K91, IF( ISERROR(FIND(""-"",L91)), K91 - VALUE(REGEXEXTRACT(L91,""(\d+)"")), K91 * (1 - VALUE(REGEXEXTRACT(L91,""(\d+)""))/100) ) ), 2 ) ) ")," ") | O91: FALSE | R91: FALSE | S91: FALSE | T91: FALSE
M92: =IFERROR(__xludf.DUMMYFUNCTION("IF( K92="""", """", ROUND( IF( L92="""", K92, IF( ISERROR(FIND(""-"",L92)), K92 - VALUE(REGEXEXTRACT(L92,""(\d+)"")), K92 * (1 - VALUE(REGEXEXTRACT(L92,""(\d+)""))/100) ) ), 2 ) ) ")," ") | O92: FALSE | R92: FALSE | S92: FALSE | T92: FALSE
M93: =IFERROR(__xludf.DUMMYFUNCTION("IF( K93="""", """", ROUND( IF( L93="""", K93, IF( ISERROR(FIND(""-"",L93)), K93 - VALUE(REGEXEXTRACT(L93,""(\d+)"")), K93 * (1 - VALUE(REGEXEXTRACT(L93,""(\d+)""))/100) ) ), 2 ) ) ")," ") | O93: FALSE | R93: FALSE | S93: FALSE | T93: FALSE
M94: =IFERROR(__xludf.DUMMYFUNCTION("IF( K94="""", """", ROUND( IF( L94="""", K94, IF( ISERROR(FIND(""-"",L94)), K94 - VALUE(REGEXEXTRACT(L94,""(\d+)"")), K94 * (1 - VALUE(REGEXEXTRACT(L94,""(\d+)""))/100) ) ), 2 ) ) ")," ") | O94: FALSE | R94: FALSE | S94: FALSE | T94: FALSE
M95: =IFERROR(__xludf.DUMMYFUNCTION("IF( K95="""", """", ROUND( IF( L95="""", K95, IF( ISERROR(FIND(""-"",L95)), K95 - VALUE(REGEXEXTRACT(L95,""(\d+)"")), K95 * (1 - VALUE(REGEXEXTRACT(L95,""(\d+)""))/100) ) ), 2 ) ) ")," ") | O95: FALSE | R95: FALSE | S95: FALSE | T95: FALSE
M96: =IFERROR(__xludf.DUMMYFUNCTION("IF( K96="""", """", ROUND( IF( L96="""", K96, IF( ISERROR(FIND(""-"",L96)), K96 - VALUE(REGEXEXTRACT(L96,""(\d+)"")), K96 * (1 - VALUE(REGEXEXTRACT(L96,""(\d+)""))/100) ) ), 2 ) ) ")," ") | O96: FALSE | R96: FALSE | S96: FALSE | T96: FALSE
M97: =IFERROR(__xludf.DUMMYFUNCTION("IF( K97="""", """", ROUND( IF( L97="""", K97, IF( ISERROR(FIND(""-"",L97)), K97 - VALUE(REGEXEXTRACT(L97,""(\d+)"")), K97 * (1 - VALUE(REGEXEXTRACT(L97,""(\d+)""))/100) ) ), 2 ) ) ")," ") | O97: FALSE | R97: FALSE | S97: FALSE | T97: FALSE
M98: =IFERROR(__xludf.DUMMYFUNCTION("IF( K98="""", """", ROUND( IF( L98="""", K98, IF( ISERROR(FIND(""-"",L98)), K98 - VALUE(REGEXEXTRACT(L98,""(\d+)"")), K98 * (1 - VALUE(REGEXEXTRACT(L98,""(\d+)""))/100) ) ), 2 ) ) ")," ") | O98: FALSE | R98: FALSE | S98: FALSE | T98: FALSE
M99: =IFERROR(__xludf.DUMMYFUNCTION("IF( K99="""", """", ROUND( IF( L99="""", K99, IF( ISERROR(FIND(""-"",L99)), K99 - VALUE(REGEXEXTRACT(L99,""(\d+)"")), K99 * (1 - VALUE(REGEXEXTRACT(L99,""(\d+)""))/100) ) ), 2 ) ) ")," ") | O99: FALSE | R99: FALSE | S99: FALSE | T99: FALSE
M100: =IFERROR(__xludf.DUMMYFUNCTION("IF( K100="""", """", ROUND( IF( L100="""", K100, IF( ISERROR(FIND(""-"",L100)), K100 - VALUE(REGEXEXTRACT(L100,""(\d+)"")), K100 * (1 - VALUE(REGEXEXTRACT(L100,""(\d+)""))/100) ) ), 2 ) )"&" ")," ") | O100: FALSE | R100: FALSE | S100: FALSE | T100: FALSE
...

Sheet OC_AMBERALDRIN
C1: OC_AMBERALDRIN_15MAR2026
A2: CHI SCRIVE | B2: VENDITA | C2: DATA INSERIMENTO /RICHIESTA | D2: ID ANAGRAFICA | E2: COGNOME | F2: NOME | G2: TELEFONO | H2: CODICE FISCALE | I2: EMAIL | J2: DATA PAGAMENTO /RICEVUTA | K2: QUOTA | L2: CODICE SCONTO | M2: IMPORTO FINALE | N2: DIGIT/CASH - TESS/NON TESS | O2: PRESENZA | P2: NOTE | Q2: INSERITO SU ATHENA | R2: RICEVUTA FATTA | S2: FATTURA FATTA | T2: VERIFICA PAGAMENTO
C3: 14:30-16:30_URBAN COREOGRAFICO (€32 entro il 14/03 compreso → €37 il giorno stesso)
A4: Estefany | B4: ONLINE | C4: 46070 | D4: ID-000398 | E4: BRUZZESE | F4: ALISEA | G4: 3490659648 | H4: BRZLSA96L57F205J | I4: alisea.bruzzese@gmail.com | J4: 46070 | K4: 32 | L4: NURA02WS | M4: =IFERROR(__xludf.DUMMYFUNCTION("IF( K4="""", """", ROUND( IF( L4="""", K4, IF( ISERROR(FIND(""-"",L4)), K4 - VALUE(REGEXEXTRACT(L4,""(\d+)"")), K4 * (1 - VALUE(REGEXEXTRACT(L4,""(\d+)""))/100) ) ), 2 ) ) "),30.0) -> 30 | N4: DIGIT - TESSERATO | O4: TRUE | Q4: INSERITO | R4: TRUE | S4: FALSE | T4: TRUE
A5: Estefany | B5: ONLINE | C5: 46072 | D5: ID-000137 | E5: RAMBALDI | F5: ROBERTA | G5: 3313419879 | H5: RMBRRT96T64F205N | I5: rambaldi.roberta6@gmail.com | J5: 46072 | K5: 32 | L5: NURA02WS | M5: =IFERROR(__xludf.DUMMYFUNCTION("IF( K5="""", """", ROUND( IF( L5="""", K5, IF( ISERROR(FIND(""-"",L5)), K5 - VALUE(REGEXEXTRACT(L5,""(\d+)"")), K5 * (1 - VALUE(REGEXEXTRACT(L5,""(\d+)""))/100) ) ), 2 ) ) "),30.0) -> 30 | N5: DIGIT - TESSERATO | O5: TRUE | Q5: INSERITO | R5: TRUE | S5: FALSE | T5: TRUE
A6: Estefany | B6: ONLINE | C6: 46076 | D6: ID-000760 | E6: BINARELLI | F6: BEATRICE | G6: 3343934888 | H6: BNRBRC09B57H501G | I6: chiarabiselli@hotmail.com | J6: 46076 | K6: 32 | M6: =IFERROR(__xludf.DUMMYFUNCTION("IF( K6="""", """", ROUND( IF( L6="""", K6, IF( ISERROR(FIND(""-"",L6)), K6 - VALUE(REGEXEXTRACT(L6,""(\d+)"")), K6 * (1 - VALUE(REGEXEXTRACT(L6,""(\d+)""))/100) ) ), 2 ) ) "),32.0) -> 32 | N6: DIGIT - TESSERATO | O6: TRUE | Q6: INSERITO | R6: TRUE | S6: FALSE | T6: TRUE
A7: Estefany | B7: ONLINE | C7: 46077 | E7: REYES RODRIGUEZ | F7: CHRISTIAN MICHEL | G7: 3481955108 | H7: RYSCRS90C08Z514J | I7: Michel.9017@libero.it | J7: 46077 | K7: 32 | M7: =IFERROR(__xludf.DUMMYFUNCTION("IF( K7="""", """", ROUND( IF( L7="""", K7, IF( ISERROR(FIND(""-"",L7)), K7 - VALUE(REGEXEXTRACT(L7,""(\d+)"")), K7 * (1 - VALUE(REGEXEXTRACT(L7,""(\d+)""))/100) ) ), 2 ) ) "),32.0) -> 32 | N7: DIGIT - NON TESSERATO | O7: TRUE | Q7: INSERITO | R7: FALSE | S7: TRUE | T7: TRUE
A8: Estefany | B8: SEDE Estefany | C8: 46081 | D8: ID-000109 | E8: GALARDO | F8: CAMILLA | G8: 3389088473 | H8: GLRCLL09M57B354T | I8: perillimarta@gmail.com | J8: 46081 | K8: 32 | L8: ESTEFANY02WS | M8: =IFERROR(__xludf.DUMMYFUNCTION("IF( K8="""", """", ROUND( IF( L8="""", K8, IF( ISERROR(FIND(""-"",L8)), K8 - VALUE(REGEXEXTRACT(L8,""(\d+)"")), K8 * (1 - VALUE(REGEXEXTRACT(L8,""(\d+)""))/100) ) ), 2 ) ) "),30.0) -> 30 | N8: CASH - TESSERATO | O8: TRUE | Q8: INSERITO | R8: TRUE | S8: FALSE | T8: TRUE
A9: Estefany | B9: ONLINE | C9: 46082 | D9: ID-000440 | E9: CRIPPA | F9: GIULIA | G9: 3342145266 | H9: CRPGLI95E70A944Q | I9: giuliacrippa0@icloud.com | J9: 46082 | K9: 32 | M9: =IFERROR(__xludf.DUMMYFUNCTION("IF( K9="""", """", ROUND( IF( L9="""", K9, IF( ISERROR(FIND(""-"",L9)), K9 - VALUE(REGEXEXTRACT(L9,""(\d+)"")), K9 * (1 - VALUE(REGEXEXTRACT(L9,""(\d+)""))/100) ) ), 2 ) ) "),32.0) -> 32 | N9: DIGIT - TESSERATO | O9: TRUE | Q9: INSERITO | R9: TRUE | S9: FALSE | T9: TRUE
A10: Nura | B10: SEDE Nura | C10: 46087 | E10: TAGLIAVENTO | F10: GIULIA | G10: 3342627444 | H10: TGLGLI98L51H211P | I10: giuliatagliavento98@gmail.com | J10: 46087 | K10: 32 | M10: =IFERROR(__xludf.DUMMYFUNCTION("IF( K10="""", """", ROUND( IF( L10="""", K10, IF( ISERROR(FIND(""-"",L10)), K10 - VALUE(REGEXEXTRACT(L10,""(\d+)"")), K10 * (1 - VALUE(REGEXEXTRACT(L10,""(\d+)""))/100) ) ), 2 ) ) "),32.0) -> 32 | N10: DIGIT - TESSERATO | O10: TRUE | Q10: INSERITO | R10: TRUE | S10: FALSE | T10: TRUE
A11: Nura | B11: SEDE Nura | C11: 46087 | E11: PAOLO | F11: ROCCO | G11: 3487100315 | H11: RCCPLA70E23H264S | I11: castore@live.it | J11: 46087 | K11: 32 | L11: NURA02WS | M11: =IFERROR(__xludf.DUMMYFUNCTION("IF( K11="""", """", ROUND( IF( L11="""", K11, IF( ISERROR(FIND(""-"",L11)), K11 - VALUE(REGEXEXTRACT(L11,""(\d+)"")), K11 * (1 - VALUE(REGEXEXTRACT(L11,""(\d+)""))/100) ) ), 2 ) ) "),30.0) -> 30 | N11: DIGIT - TESSERATO | O11: TRUE | Q11: INSERITO | R11: TRUE | S11: FALSE | T11: TRUE
A12: Estefany | B12: ONLINE | C12: 46089 | E12: BRUZZESE | F12: ASIA | G12: 3337205209 | H12: BRZSAI03A41F205V | I12: asiabruzzese@gmail.com | J12: 46089 | K12: 32 | L12: NURA02WS | M12: =IFERROR(__xludf.DUMMYFUNCTION("IF( K12="""", """", ROUND( IF( L12="""", K12, IF( ISERROR(FIND(""-"",L12)), K12 - VALUE(REGEXEXTRACT(L12,""(\d+)"")), K12 * (1 - VALUE(REGEXEXTRACT(L12,""(\d+)""))/100) ) ), 2 ) ) "),30.0) -> 30 | N12: DIGIT - NON TESSERATO | O12: TRUE | Q12: INSERITO | R12: FALSE | S12: TRUE | T12: TRUE
A13: Estefany | B13: ONLINE | C13: 46090 | D13: ID-000803 | E13: PARATI | F13: SOFIA | G13: 3495601535 | H13: PRTSFO10L62I577J | I13: sara.garlati@gmail.com | J13: 46090 | K13: 32 | L13: ALEXANDRA02WS | M13: =IFERROR(__xludf.DUMMYFUNCTION("IF( K13="""", """", ROUND( IF( L13="""", K13, IF( ISERROR(FIND(""-"",L13)), K13 - VALUE(REGEXEXTRACT(L13,""(\d+)"")), K13 * (1 - VALUE(REGEXEXTRACT(L13,""(\d+)""))/100) ) ), 2 ) ) "),30.0) -> 30 | N13: DIGIT - TESSERATO | O13: TRUE | Q13: INSERITO | R13: TRUE | S13: FALSE | T13: TRUE
A14: Estefany | B14: ONLINE | C14: 46093 | D14: ID-000479 | E14: VENTURA | F14: GINEVRA | G14: 3400552152 | H14: VNTGVR10T50F205J | I14: chiaravenvi@gmail.com | J14: 46093 | K14: 32 | M14: =IFERROR(__xludf.DUMMYFUNCTION("IF( K14="""", """", ROUND( IF( L14="""", K14, IF( ISERROR(FIND(""-"",L14)), K14 - VALUE(REGEXEXTRACT(L14,""(\d+)"")), K14 * (1 - VALUE(REGEXEXTRACT(L14,""(\d+)""))/100) ) ), 2 ) ) "),32.0) -> 32 | N14: DIGIT - TESSERATO | O14: TRUE | Q14: INSERITO | R14: TRUE | S14: FALSE | T14: TRUE
A15: Estefany | B15: ONLINE | C15: 46092 | E15: CUELA | F15: ANTONIA | G15: 3513213519 | H15: CLUNNC02P55Z129J | I15: antoniaculea3@gmail.com | J15: 46092 | K15: 32 | M15: =IFERROR(__xludf.DUMMYFUNCTION("IF( K15="""", """", ROUND( IF( L15="""", K15, IF( ISERROR(FIND(""-"",L15)), K15 - VALUE(REGEXEXTRACT(L15,""(\d+)"")), K15 * (1 - VALUE(REGEXEXTRACT(L15,""(\d+)""))/100) ) ), 2 ) ) "),32.0) -> 32 | N15: DIGIT - NON TESSERATO | O15: TRUE | Q15: INSERITO | R15: FALSE | S15: TRUE | T15: TRUE
A16: Estefany | B16: ONLINE | C16: 46094 | D16: ID-002534 | E16: DE PANDIS | F16: BEATRICE | G16: 3382295075 | H16: DPNBRC06S46B157K | I16: beadepa@virgilio.it | J16: 46094 | K16: 32 | M16: =IFERROR(__xludf.DUMMYFUNCTION("IF( K16="""", """", ROUND( IF( L16="""", K16, IF( ISERROR(FIND(""-"",L16)), K16 - VALUE(REGEXEXTRACT(L16,""(\d+)"")), K16 * (1 - VALUE(REGEXEXTRACT(L16,""(\d+)""))/100) ) ), 2 ) ) "),32.0) -> 32 | N16: DIGIT - TESSERATO | O16: TRUE | Q16: INSERITO | R16: TRUE | S16: FALSE | T16: TRUE
A17: Nura | B17: SEDE Nura | C17: 46095 | E17: MENGYUN | F17: LARIA | G17: 3474965780 | H17: MNGLRA03A54Z210M | I17: 13642196573@163.com | J17: 46094 | K17: 32 | L17: NURA02WS | M17: =IFERROR(__xludf.DUMMYFUNCTION("IF( K17="""", """", ROUND( IF( L17="""", K17, IF( ISERROR(FIND(""-"",L17)), K17 - VALUE(REGEXEXTRACT(L17,""(\d+)"")), K17 * (1 - VALUE(REGEXEXTRACT(L17,""(\d+)""))/100) ) ), 2 ) ) "),30.0) -> 30 | N17: DIGIT - TESSERATO | O17: TRUE | Q17: INSERITO | R17: TRUE | S17: FALSE | T17: TRUE
A18: Nura | B18: SEDE Nura | C18: 46095 | E18: KANG | F18: YIAN | G18: 3283986848 | H18: KNGYNI96P44Z217R | I18: anki0904@gmail.com | J18: 46094 | K18: 32 | L18: NURA02WS | M18: =IFERROR(__xludf.DUMMYFUNCTION("IF( K18="""", """", ROUND( IF( L18="""", K18, IF( ISERROR(FIND(""-"",L18)), K18 - VALUE(REGEXEXTRACT(L18,""(\d+)"")), K18 * (1 - VALUE(REGEXEXTRACT(L18,""(\d+)""))/100) ) ), 2 ) ) "),30.0) -> 30 | N18: DIGIT - TESSERATO | O18: TRUE | Q18: INSERITO | R18: TRUE | S18: FALSE | T18: TRUE
A19: Nura | B19: SEDE Nura | C19: 46095 | E19: LIU | F19: YIRAN | G19: 3387062199 | H19: LIUYRN02D66Z210G | I19: lyiran077@gmail.com | J19: 46095 | K19: 32 | L19: NURA02WS | M19: =IFERROR(__xludf.DUMMYFUNCTION("IF( K19="""", """", ROUND( IF( L19="""", K19, IF( ISERROR(FIND(""-"",L19)), K19 - VALUE(REGEXEXTRACT(L19,""(\d+)"")), K19 * (1 - VALUE(REGEXEXTRACT(L19,""(\d+)""))/100) ) ), 2 ) ) "),30.0) -> 30 | N19: DIGIT - TESSERATO | O19: TRUE | Q19: INSERITO | R19: TRUE | S19: FALSE | T19: TRUE
A20: Estefany | B20: ONLINE | C20: 46073 | E20: TORRES GOMEZ | F20: JHISSEL | G20: 3801039339 | H20: TRRJSS03H68Z506V | I20: chaveznini26@gmail.com | J20: 46073 | K20: 32 | M20: =IFERROR(__xludf.DUMMYFUNCTION("IF( K20="""", """", ROUND( IF( L20="""", K20, IF( ISERROR(FIND(""-"",L20)), K20 - VALUE(REGEXEXTRACT(L20,""(\d+)"")), K20 * (1 - VALUE(REGEXEXTRACT(L20,""(\d+)""))/100) ) ), 2 ) ) "),32.0) -> 32 | N20: DIGIT - TESSERATO | O20: TRUE | Q20: INSERITO | R20: TRUE | S20: FALSE | T20: TRUE
M21: =IFERROR(__xludf.DUMMYFUNCTION("IF( K21="""", """", ROUND( IF( L21="""", K21, IF( ISERROR(FIND(""-"",L21)), K21 - VALUE(REGEXEXTRACT(L21,""(\d+)"")), K21 * (1 - VALUE(REGEXEXTRACT(L21,""(\d+)""))/100) ) ), 2 ) ) ")," ") | O21: FALSE | R21: FALSE | S21: FALSE | T21: FALSE
M22: =IFERROR(__xludf.DUMMYFUNCTION("IF( K22="""", """", ROUND( IF( L22="""", K22, IF( ISERROR(FIND(""-"",L22)), K22 - VALUE(REGEXEXTRACT(L22,""(\d+)"")), K22 * (1 - VALUE(REGEXEXTRACT(L22,""(\d+)""))/100) ) ), 2 ) ) ")," ") | O22: FALSE | R22: FALSE | S22: FALSE | T22: FALSE
M23: =IFERROR(__xludf.DUMMYFUNCTION("IF( K23="""", """", ROUND( IF( L23="""", K23, IF( ISERROR(FIND(""-"",L23)), K23 - VALUE(REGEXEXTRACT(L23,""(\d+)"")), K23 * (1 - VALUE(REGEXEXTRACT(L23,""(\d+)""))/100) ) ), 2 ) ) ")," ") | O23: FALSE | R23: FALSE | S23: FALSE | T23: FALSE
M24: =IFERROR(__xludf.DUMMYFUNCTION("IF( K24="""", """", ROUND( IF( L24="""", K24, IF( ISERROR(FIND(""-"",L24)), K24 - VALUE(REGEXEXTRACT(L24,""(\d+)"")), K24 * (1 - VALUE(REGEXEXTRACT(L24,""(\d+)""))/100) ) ), 2 ) ) ")," ") | O24: FALSE | R24: FALSE | S24: FALSE | T24: FALSE
M25: =IFERROR(__xludf.DUMMYFUNCTION("IF( K25="""", """", ROUND( IF( L25="""", K25, IF( ISERROR(FIND(""-"",L25)), K25 - VALUE(REGEXEXTRACT(L25,""(\d+)"")), K25 * (1 - VALUE(REGEXEXTRACT(L25,""(\d+)""))/100) ) ), 2 ) ) ")," ") | O25: FALSE | R25: FALSE | S25: FALSE | T25: FALSE
M26: =IFERROR(__xludf.DUMMYFUNCTION("IF( K26="""", """", ROUND( IF( L26="""", K26, IF( ISERROR(FIND(""-"",L26)), K26 - VALUE(REGEXEXTRACT(L26,""(\d+)"")), K26 * (1 - VALUE(REGEXEXTRACT(L26,""(\d+)""))/100) ) ), 2 ) ) ")," ") | O26: FALSE | R26: FALSE | S26: FALSE | T26: FALSE
M27: =IFERROR(__xludf.DUMMYFUNCTION("IF( K27="""", """", ROUND( IF( L27="""", K27, IF( ISERROR(FIND(""-"",L27)), K27 - VALUE(REGEXEXTRACT(L27,""(\d+)"")), K27 * (1 - VALUE(REGEXEXTRACT(L27,""(\d+)""))/100) ) ), 2 ) ) ")," ") | O27: FALSE | R27: FALSE | S27: FALSE | T27: FALSE
M28: =IFERROR(__xludf.DUMMYFUNCTION("IF( K28="""", """", ROUND( IF( L28="""", K28, IF( ISERROR(FIND(""-"",L28)), K28 - VALUE(REGEXEXTRACT(L28,""(\d+)"")), K28 * (1 - VALUE(REGEXEXTRACT(L28,""(\d+)""))/100) ) ), 2 ) ) ")," ") | O28: FALSE | R28: FALSE | S28: FALSE | T28: FALSE
M29: =IFERROR(__xludf.DUMMYFUNCTION("IF( K29="""", """", ROUND( IF( L29="""", K29, IF( ISERROR(FIND(""-"",L29)), K29 - VALUE(REGEXEXTRACT(L29,""(\d+)"")), K29 * (1 - VALUE(REGEXEXTRACT(L29,""(\d+)""))/100) ) ), 2 ) ) ")," ") | O29: FALSE | R29: FALSE | S29: FALSE | T29: FALSE
M30: =IFERROR(__xludf.DUMMYFUNCTION("IF( K30="""", """", ROUND( IF( L30="""", K30, IF( ISERROR(FIND(""-"",L30)), K30 - VALUE(REGEXEXTRACT(L30,""(\d+)"")), K30 * (1 - VALUE(REGEXEXTRACT(L30,""(\d+)""))/100) ) ), 2 ) ) ")," ") | O30: FALSE | R30: FALSE | S30: FALSE | T30: FALSE
M31: =IFERROR(__xludf.DUMMYFUNCTION("IF( K31="""", """", ROUND( IF( L31="""", K31, IF( ISERROR(FIND(""-"",L31)), K31 - VALUE(REGEXEXTRACT(L31,""(\d+)"")), K31 * (1 - VALUE(REGEXEXTRACT(L31,""(\d+)""))/100) ) ), 2 ) ) ")," ") | O31: FALSE | R31: FALSE | S31: FALSE | T31: FALSE
M32: =IFERROR(__xludf.DUMMYFUNCTION("IF( K32="""", """", ROUND( IF( L32="""", K32, IF( ISERROR(FIND(""-"",L32)), K32 - VALUE(REGEXEXTRACT(L32,""(\d+)"")), K32 * (1 - VALUE(REGEXEXTRACT(L32,""(\d+)""))/100) ) ), 2 ) ) ")," ") | O32: FALSE | R32: FALSE | S32: FALSE | T32: FALSE
M33: =IFERROR(__xludf.DUMMYFUNCTION("IF( K33="""", """", ROUND( IF( L33="""", K33, IF( ISERROR(FIND(""-"",L33)), K33 - VALUE(REGEXEXTRACT(L33,""(\d+)"")), K33 * (1 - VALUE(REGEXEXTRACT(L33,""(\d+)""))/100) ) ), 2 ) ) ")," ") | O33: FALSE | R33: FALSE | S33: FALSE | T33: FALSE
M34: =IFERROR(__xludf.DUMMYFUNCTION("IF( K34="""", """", ROUND( IF( L34="""", K34, IF( ISERROR(FIND(""-"",L34)), K34 - VALUE(REGEXEXTRACT(L34,""(\d+)"")), K34 * (1 - VALUE(REGEXEXTRACT(L34,""(\d+)""))/100) ) ), 2 ) ) ")," ") | O34: FALSE | R34: FALSE | S34: FALSE | T34: FALSE
M35: =IFERROR(__xludf.DUMMYFUNCTION("IF( K35="""", """", ROUND( IF( L35="""", K35, IF( ISERROR(FIND(""-"",L35)), K35 - VALUE(REGEXEXTRACT(L35,""(\d+)"")), K35 * (1 - VALUE(REGEXEXTRACT(L35,""(\d+)""))/100) ) ), 2 ) ) ")," ") | O35: FALSE | R35: FALSE | S35: FALSE | T35: FALSE
M36: =IFERROR(__xludf.DUMMYFUNCTION("IF( K36="""", """", ROUND( IF( L36="""", K36, IF( ISERROR(FIND(""-"",L36)), K36 - VALUE(REGEXEXTRACT(L36,""(\d+)"")), K36 * (1 - VALUE(REGEXEXTRACT(L36,""(\d+)""))/100) ) ), 2 ) ) ")," ") | O36: FALSE | R36: FALSE | S36: FALSE | T36: FALSE
M37: =IFERROR(__xludf.DUMMYFUNCTION("IF( K37="""", """", ROUND( IF( L37="""", K37, IF( ISERROR(FIND(""-"",L37)), K37 - VALUE(REGEXEXTRACT(L37,""(\d+)"")), K37 * (1 - VALUE(REGEXEXTRACT(L37,""(\d+)""))/100) ) ), 2 ) ) ")," ") | O37: FALSE | R37: FALSE | S37: FALSE | T37: FALSE
M38: =IFERROR(__xludf.DUMMYFUNCTION("IF( K38="""", """", ROUND( IF( L38="""", K38, IF( ISERROR(FIND(""-"",L38)), K38 - VALUE(REGEXEXTRACT(L38,""(\d+)"")), K38 * (1 - VALUE(REGEXEXTRACT(L38,""(\d+)""))/100) ) ), 2 ) ) ")," ") | O38: FALSE | R38: FALSE | S38: FALSE | T38: FALSE
M39: =IFERROR(__xludf.DUMMYFUNCTION("IF( K39="""", """", ROUND( IF( L39="""", K39, IF( ISERROR(FIND(""-"",L39)), K39 - VALUE(REGEXEXTRACT(L39,""(\d+)"")), K39 * (1 - VALUE(REGEXEXTRACT(L39,""(\d+)""))/100) ) ), 2 ) ) ")," ") | O39: FALSE | R39: FALSE | S39: FALSE | T39: FALSE
M40: =IFERROR(__xludf.DUMMYFUNCTION("IF( K40="""", """", ROUND( IF( L40="""", K40, IF( ISERROR(FIND(""-"",L40)), K40 - VALUE(REGEXEXTRACT(L40,""(\d+)"")), K40 * (1 - VALUE(REGEXEXTRACT(L40,""(\d+)""))/100) ) ), 2 ) ) ")," ") | O40: FALSE | R40: FALSE | S40: FALSE | T40: FALSE
M41: =IFERROR(__xludf.DUMMYFUNCTION("IF( K41="""", """", ROUND( IF( L41="""", K41, IF( ISERROR(FIND(""-"",L41)), K41 - VALUE(REGEXEXTRACT(L41,""(\d+)"")), K41 * (1 - VALUE(REGEXEXTRACT(L41,""(\d+)""))/100) ) ), 2 ) ) ")," ") | O41: FALSE | R41: FALSE | S41: FALSE | T41: FALSE
M42: =IFERROR(__xludf.DUMMYFUNCTION("IF( K42="""", """", ROUND( IF( L42="""", K42, IF( ISERROR(FIND(""-"",L42)), K42 - VALUE(REGEXEXTRACT(L42,""(\d+)"")), K42 * (1 - VALUE(REGEXEXTRACT(L42,""(\d+)""))/100) ) ), 2 ) ) ")," ") | O42: FALSE | R42: FALSE | S42: FALSE | T42: FALSE
M43: =IFERROR(__xludf.DUMMYFUNCTION("IF( K43="""", """", ROUND( IF( L43="""", K43, IF( ISERROR(FIND(""-"",L43)), K43 - VALUE(REGEXEXTRACT(L43,""(\d+)"")), K43 * (1 - VALUE(REGEXEXTRACT(L43,""(\d+)""))/100) ) ), 2 ) ) ")," ") | O43: FALSE | R43: FALSE | S43: FALSE | T43: FALSE
M44: =IFERROR(__xludf.DUMMYFUNCTION("IF( K44="""", """", ROUND( IF( L44="""", K44, IF( ISERROR(FIND(""-"",L44)), K44 - VALUE(REGEXEXTRACT(L44,""(\d+)"")), K44 * (1 - VALUE(REGEXEXTRACT(L44,""(\d+)""))/100) ) ), 2 ) ) ")," ") | O44: FALSE | R44: FALSE | S44: FALSE | T44: FALSE
M45: =IFERROR(__xludf.DUMMYFUNCTION("IF( K45="""", """", ROUND( IF( L45="""", K45, IF( ISERROR(FIND(""-"",L45)), K45 - VALUE(REGEXEXTRACT(L45,""(\d+)"")), K45 * (1 - VALUE(REGEXEXTRACT(L45,""(\d+)""))/100) ) ), 2 ) ) ")," ") | O45: FALSE | R45: FALSE | S45: FALSE | T45: FALSE
M46: =IFERROR(__xludf.DUMMYFUNCTION("IF( K46="""", """", ROUND( IF( L46="""", K46, IF( ISERROR(FIND(""-"",L46)), K46 - VALUE(REGEXEXTRACT(L46,""(\d+)"")), K46 * (1 - VALUE(REGEXEXTRACT(L46,""(\d+)""))/100) ) ), 2 ) ) ")," ") | O46: FALSE | R46: FALSE | S46: FALSE | T46: FALSE
M47: =IFERROR(__xludf.DUMMYFUNCTION("IF( K47="""", """", ROUND( IF( L47="""", K47, IF( ISERROR(FIND(""-"",L47)), K47 - VALUE(REGEXEXTRACT(L47,""(\d+)"")), K47 * (1 - VALUE(REGEXEXTRACT(L47,""(\d+)""))/100) ) ), 2 ) ) ")," ") | O47: FALSE | R47: FALSE | S47: FALSE | T47: FALSE
M48: =IFERROR(__xludf.DUMMYFUNCTION("IF( K48="""", """", ROUND( IF( L48="""", K48, IF( ISERROR(FIND(""-"",L48)), K48 - VALUE(REGEXEXTRACT(L48,""(\d+)"")), K48 * (1 - VALUE(REGEXEXTRACT(L48,""(\d+)""))/100) ) ), 2 ) ) ")," ") | O48: FALSE | R48: FALSE | S48: FALSE | T48: FALSE
M49: =IFERROR(__xludf.DUMMYFUNCTION("IF( K49="""", """", ROUND( IF( L49="""", K49, IF( ISERROR(FIND(""-"",L49)), K49 - VALUE(REGEXEXTRACT(L49,""(\d+)"")), K49 * (1 - VALUE(REGEXEXTRACT(L49,""(\d+)""))/100) ) ), 2 ) ) ")," ") | O49: FALSE | R49: FALSE | S49: FALSE | T49: FALSE
M50: =IFERROR(__xludf.DUMMYFUNCTION("IF( K50="""", """", ROUND( IF( L50="""", K50, IF( ISERROR(FIND(""-"",L50)), K50 - VALUE(REGEXEXTRACT(L50,""(\d+)"")), K50 * (1 - VALUE(REGEXEXTRACT(L50,""(\d+)""))/100) ) ), 2 ) ) ")," ") | O50: FALSE | R50: FALSE | S50: FALSE | T50: FALSE
M51: =IFERROR(__xludf.DUMMYFUNCTION("IF( K51="""", """", ROUND( IF( L51="""", K51, IF( ISERROR(FIND(""-"",L51)), K51 - VALUE(REGEXEXTRACT(L51,""(\d+)"")), K51 * (1 - VALUE(REGEXEXTRACT(L51,""(\d+)""))/100) ) ), 2 ) ) ")," ") | O51: FALSE | R51: FALSE | S51: FALSE | T51: FALSE
M52: =IFERROR(__xludf.DUMMYFUNCTION("IF( K52="""", """", ROUND( IF( L52="""", K52, IF( ISERROR(FIND(""-"",L52)), K52 - VALUE(REGEXEXTRACT(L52,""(\d+)"")), K52 * (1 - VALUE(REGEXEXTRACT(L52,""(\d+)""))/100) ) ), 2 ) ) ")," ") | O52: FALSE | R52: FALSE | S52: FALSE | T52: FALSE
M53: =IFERROR(__xludf.DUMMYFUNCTION("IF( K53="""", """", ROUND( IF( L53="""", K53, IF( ISERROR(FIND(""-"",L53)), K53 - VALUE(REGEXEXTRACT(L53,""(\d+)"")), K53 * (1 - VALUE(REGEXEXTRACT(L53,""(\d+)""))/100) ) ), 2 ) ) ")," ") | O53: FALSE | R53: FALSE | S53: FALSE | T53: FALSE
M54: =IFERROR(__xludf.DUMMYFUNCTION("IF( K54="""", """", ROUND( IF( L54="""", K54, IF( ISERROR(FIND(""-"",L54)), K54 - VALUE(REGEXEXTRACT(L54,""(\d+)"")), K54 * (1 - VALUE(REGEXEXTRACT(L54,""(\d+)""))/100) ) ), 2 ) ) ")," ") | O54: FALSE | R54: FALSE | S54: FALSE | T54: FALSE
M55: =IFERROR(__xludf.DUMMYFUNCTION("IF( K55="""", """", ROUND( IF( L55="""", K55, IF( ISERROR(FIND(""-"",L55)), K55 - VALUE(REGEXEXTRACT(L55,""(\d+)"")), K55 * (1 - VALUE(REGEXEXTRACT(L55,""(\d+)""))/100) ) ), 2 ) ) ")," ") | O55: FALSE | R55: FALSE | S55: FALSE | T55: FALSE
M56: =IFERROR(__xludf.DUMMYFUNCTION("IF( K56="""", """", ROUND( IF( L56="""", K56, IF( ISERROR(FIND(""-"",L56)), K56 - VALUE(REGEXEXTRACT(L56,""(\d+)"")), K56 * (1 - VALUE(REGEXEXTRACT(L56,""(\d+)""))/100) ) ), 2 ) ) ")," ") | O56: FALSE | R56: FALSE | S56: FALSE | T56: FALSE
M57: =IFERROR(__xludf.DUMMYFUNCTION("IF( K57="""", """", ROUND( IF( L57="""", K57, IF( ISERROR(FIND(""-"",L57)), K57 - VALUE(REGEXEXTRACT(L57,""(\d+)"")), K57 * (1 - VALUE(REGEXEXTRACT(L57,""(\d+)""))/100) ) ), 2 ) ) ")," ") | O57: FALSE | R57: FALSE | S57: FALSE | T57: FALSE
M58: =IFERROR(__xludf.DUMMYFUNCTION("IF( K58="""", """", ROUND( IF( L58="""", K58, IF( ISERROR(FIND(""-"",L58)), K58 - VALUE(REGEXEXTRACT(L58,""(\d+)"")), K58 * (1 - VALUE(REGEXEXTRACT(L58,""(\d+)""))/100) ) ), 2 ) ) ")," ") | O58: FALSE | R58: FALSE | S58: FALSE | T58: FALSE
M59: =IFERROR(__xludf.DUMMYFUNCTION("IF( K59="""", """", ROUND( IF( L59="""", K59, IF( ISERROR(FIND(""-"",L59)), K59 - VALUE(REGEXEXTRACT(L59,""(\d+)"")), K59 * (1 - VALUE(REGEXEXTRACT(L59,""(\d+)""))/100) ) ), 2 ) ) ")," ") | O59: FALSE | R59: FALSE | S59: FALSE | T59: FALSE
M60: =IFERROR(__xludf.DUMMYFUNCTION("IF( K60="""", """", ROUND( IF( L60="""", K60, IF( ISERROR(FIND(""-"",L60)), K60 - VALUE(REGEXEXTRACT(L60,""(\d+)"")), K60 * (1 - VALUE(REGEXEXTRACT(L60,""(\d+)""))/100) ) ), 2 ) ) ")," ") | O60: FALSE | R60: FALSE | S60: FALSE | T60: FALSE
M61: =IFERROR(__xludf.DUMMYFUNCTION("IF( K61="""", """", ROUND( IF( L61="""", K61, IF( ISERROR(FIND(""-"",L61)), K61 - VALUE(REGEXEXTRACT(L61,""(\d+)"")), K61 * (1 - VALUE(REGEXEXTRACT(L61,""(\d+)""))/100) ) ), 2 ) ) ")," ") | O61: FALSE | R61: FALSE | S61: FALSE | T61: FALSE
M62: =IFERROR(__xludf.DUMMYFUNCTION("IF( K62="""", """", ROUND( IF( L62="""", K62, IF( ISERROR(FIND(""-"",L62)), K62 - VALUE(REGEXEXTRACT(L62,""(\d+)"")), K62 * (1 - VALUE(REGEXEXTRACT(L62,""(\d+)""))/100) ) ), 2 ) ) ")," ") | O62: FALSE | R62: FALSE | S62: FALSE | T62: FALSE
M63: =IFERROR(__xludf.DUMMYFUNCTION("IF( K63="""", """", ROUND( IF( L63="""", K63, IF( ISERROR(FIND(""-"",L63)), K63 - VALUE(REGEXEXTRACT(L63,""(\d+)"")), K63 * (1 - VALUE(REGEXEXTRACT(L63,""(\d+)""))/100) ) ), 2 ) ) ")," ") | O63: FALSE | R63: FALSE | S63: FALSE | T63: FALSE
M64: =IFERROR(__xludf.DUMMYFUNCTION("IF( K64="""", """", ROUND( IF( L64="""", K64, IF( ISERROR(FIND(""-"",L64)), K64 - VALUE(REGEXEXTRACT(L64,""(\d+)"")), K64 * (1 - VALUE(REGEXEXTRACT(L64,""(\d+)""))/100) ) ), 2 ) ) ")," ") | O64: FALSE | R64: FALSE | S64: FALSE | T64: FALSE
M65: =IFERROR(__xludf.DUMMYFUNCTION("IF( K65="""", """", ROUND( IF( L65="""", K65, IF( ISERROR(FIND(""-"",L65)), K65 - VALUE(REGEXEXTRACT(L65,""(\d+)"")), K65 * (1 - VALUE(REGEXEXTRACT(L65,""(\d+)""))/100) ) ), 2 ) ) ")," ") | O65: FALSE | R65: FALSE | S65: FALSE | T65: FALSE
M66: =IFERROR(__xludf.DUMMYFUNCTION("IF( K66="""", """", ROUND( IF( L66="""", K66, IF( ISERROR(FIND(""-"",L66)), K66 - VALUE(REGEXEXTRACT(L66,""(\d+)"")), K66 * (1 - VALUE(REGEXEXTRACT(L66,""(\d+)""))/100) ) ), 2 ) ) ")," ") | O66: FALSE | R66: FALSE | S66: FALSE | T66: FALSE
M67: =IFERROR(__xludf.DUMMYFUNCTION("IF( K67="""", """", ROUND( IF( L67="""", K67, IF( ISERROR(FIND(""-"",L67)), K67 - VALUE(REGEXEXTRACT(L67,""(\d+)"")), K67 * (1 - VALUE(REGEXEXTRACT(L67,""(\d+)""))/100) ) ), 2 ) ) ")," ") | O67: FALSE | R67: FALSE | S67: FALSE | T67: FALSE
M68: =IFERROR(__xludf.DUMMYFUNCTION("IF( K68="""", """", ROUND( IF( L68="""", K68, IF( ISERROR(FIND(""-"",L68)), K68 - VALUE(REGEXEXTRACT(L68,""(\d+)"")), K68 * (1 - VALUE(REGEXEXTRACT(L68,""(\d+)""))/100) ) ), 2 ) ) ")," ") | O68: FALSE | R68: FALSE | S68: FALSE | T68: FALSE
M69: =IFERROR(__xludf.DUMMYFUNCTION("IF( K69="""", """", ROUND( IF( L69="""", K69, IF( ISERROR(FIND(""-"",L69)), K69 - VALUE(REGEXEXTRACT(L69,""(\d+)"")), K69 * (1 - VALUE(REGEXEXTRACT(L69,""(\d+)""))/100) ) ), 2 ) ) ")," ") | O69: FALSE | R69: FALSE | S69: FALSE | T69: FALSE
M70: =IFERROR(__xludf.DUMMYFUNCTION("IF( K70="""", """", ROUND( IF( L70="""", K70, IF( ISERROR(FIND(""-"",L70)), K70 - VALUE(REGEXEXTRACT(L70,""(\d+)"")), K70 * (1 - VALUE(REGEXEXTRACT(L70,""(\d+)""))/100) ) ), 2 ) ) ")," ") | O70: FALSE | R70: FALSE | S70: FALSE | T70: FALSE
M71: =IFERROR(__xludf.DUMMYFUNCTION("IF( K71="""", """", ROUND( IF( L71="""", K71, IF( ISERROR(FIND(""-"",L71)), K71 - VALUE(REGEXEXTRACT(L71,""(\d+)"")), K71 * (1 - VALUE(REGEXEXTRACT(L71,""(\d+)""))/100) ) ), 2 ) ) ")," ") | O71: FALSE | R71: FALSE | S71: FALSE | T71: FALSE
M72: =IFERROR(__xludf.DUMMYFUNCTION("IF( K72="""", """", ROUND( IF( L72="""", K72, IF( ISERROR(FIND(""-"",L72)), K72 - VALUE(REGEXEXTRACT(L72,""(\d+)"")), K72 * (1 - VALUE(REGEXEXTRACT(L72,""(\d+)""))/100) ) ), 2 ) ) ")," ") | O72: FALSE | R72: FALSE | S72: FALSE | T72: FALSE
M73: =IFERROR(__xludf.DUMMYFUNCTION("IF( K73="""", """", ROUND( IF( L73="""", K73, IF( ISERROR(FIND(""-"",L73)), K73 - VALUE(REGEXEXTRACT(L73,""(\d+)"")), K73 * (1 - VALUE(REGEXEXTRACT(L73,""(\d+)""))/100) ) ), 2 ) ) ")," ") | O73: FALSE | R73: FALSE | S73: FALSE | T73: FALSE
M74: =IFERROR(__xludf.DUMMYFUNCTION("IF( K74="""", """", ROUND( IF( L74="""", K74, IF( ISERROR(FIND(""-"",L74)), K74 - VALUE(REGEXEXTRACT(L74,""(\d+)"")), K74 * (1 - VALUE(REGEXEXTRACT(L74,""(\d+)""))/100) ) ), 2 ) ) ")," ") | O74: FALSE | R74: FALSE | S74: FALSE | T74: FALSE
M75: =IFERROR(__xludf.DUMMYFUNCTION("IF( K75="""", """", ROUND( IF( L75="""", K75, IF( ISERROR(FIND(""-"",L75)), K75 - VALUE(REGEXEXTRACT(L75,""(\d+)"")), K75 * (1 - VALUE(REGEXEXTRACT(L75,""(\d+)""))/100) ) ), 2 ) ) ")," ") | O75: FALSE | R75: FALSE | S75: FALSE | T75: FALSE
M76: =IFERROR(__xludf.DUMMYFUNCTION("IF( K76="""", """", ROUND( IF( L76="""", K76, IF( ISERROR(FIND(""-"",L76)), K76 - VALUE(REGEXEXTRACT(L76,""(\d+)"")), K76 * (1 - VALUE(REGEXEXTRACT(L76,""(\d+)""))/100) ) ), 2 ) ) ")," ") | O76: FALSE | R76: FALSE | S76: FALSE | T76: FALSE
M77: =IFERROR(__xludf.DUMMYFUNCTION("IF( K77="""", """", ROUND( IF( L77="""", K77, IF( ISERROR(FIND(""-"",L77)), K77 - VALUE(REGEXEXTRACT(L77,""(\d+)"")), K77 * (1 - VALUE(REGEXEXTRACT(L77,""(\d+)""))/100) ) ), 2 ) ) ")," ") | O77: FALSE | R77: FALSE | S77: FALSE | T77: FALSE
M78: =IFERROR(__xludf.DUMMYFUNCTION("IF( K78="""", """", ROUND( IF( L78="""", K78, IF( ISERROR(FIND(""-"",L78)), K78 - VALUE(REGEXEXTRACT(L78,""(\d+)"")), K78 * (1 - VALUE(REGEXEXTRACT(L78,""(\d+)""))/100) ) ), 2 ) ) ")," ") | O78: FALSE | R78: FALSE | S78: FALSE | T78: FALSE
M79: =IFERROR(__xludf.DUMMYFUNCTION("IF( K79="""", """", ROUND( IF( L79="""", K79, IF( ISERROR(FIND(""-"",L79)), K79 - VALUE(REGEXEXTRACT(L79,""(\d+)"")), K79 * (1 - VALUE(REGEXEXTRACT(L79,""(\d+)""))/100) ) ), 2 ) ) ")," ") | O79: FALSE | R79: FALSE | S79: FALSE | T79: FALSE
M80: =IFERROR(__xludf.DUMMYFUNCTION("IF( K80="""", """", ROUND( IF( L80="""", K80, IF( ISERROR(FIND(""-"",L80)), K80 - VALUE(REGEXEXTRACT(L80,""(\d+)"")), K80 * (1 - VALUE(REGEXEXTRACT(L80,""(\d+)""))/100) ) ), 2 ) ) ")," ") | O80: FALSE | R80: FALSE | S80: FALSE | T80: FALSE
M81: =IFERROR(__xludf.DUMMYFUNCTION("IF( K81="""", """", ROUND( IF( L81="""", K81, IF( ISERROR(FIND(""-"",L81)), K81 - VALUE(REGEXEXTRACT(L81,""(\d+)"")), K81 * (1 - VALUE(REGEXEXTRACT(L81,""(\d+)""))/100) ) ), 2 ) ) ")," ") | O81: FALSE | R81: FALSE | S81: FALSE | T81: FALSE
M82: =IFERROR(__xludf.DUMMYFUNCTION("IF( K82="""", """", ROUND( IF( L82="""", K82, IF( ISERROR(FIND(""-"",L82)), K82 - VALUE(REGEXEXTRACT(L82,""(\d+)"")), K82 * (1 - VALUE(REGEXEXTRACT(L82,""(\d+)""))/100) ) ), 2 ) ) ")," ") | O82: FALSE | R82: FALSE | S82: FALSE | T82: FALSE
M83: =IFERROR(__xludf.DUMMYFUNCTION("IF( K83="""", """", ROUND( IF( L83="""", K83, IF( ISERROR(FIND(""-"",L83)), K83 - VALUE(REGEXEXTRACT(L83,""(\d+)"")), K83 * (1 - VALUE(REGEXEXTRACT(L83,""(\d+)""))/100) ) ), 2 ) ) ")," ") | O83: FALSE | R83: FALSE | S83: FALSE | T83: FALSE
A84: TOTALE | B84: =COUNTIF(B4:B83,"ONLINE")+COUNTIF(B4:B83,"SEDE*") -> 17 | C84: TOTALE | D84: =COUNTIF(D4:D83, "*") -> 8 | E84: =COUNTIF(E4:E83, "*") -> 17 | F84: =COUNTIF(F4:F83, "*") -> 17 | G84: =COUNTA(G4:G83) -> 17 | H84: =COUNTIF(H4:H83, "*") -> 17 | I84: =COUNTIF(I4:I83, "*") -> 17 | J84: TOTALE | K84: =SUM(K4:K83) -> 544 | L84: =COUNTIF(L4:L83, "*") -> 9 | M84: =SUM(M4:M83) -> 526 | N84: =COUNTIF(N4:N83, "*") -> 17 | O84: =SUMPRODUCT(--O4:O83) -> 17 | P84: =COUNTIF(P4:P83, "*") -> 0 | Q84: =COUNTIF(Q4:Q83, "*") -> 17 | R84: =SUMPRODUCT(--R4:R83) -> 14 | S84: =SUMPRODUCT(--S4:S83) -> 3 | T84: =SUMPRODUCT(--T4:T83) -> 17
A85: SEDE | B85: =COUNTIF(B4:B83, "SEDE*") -> 6 | D85: TOTALI WS 1 | E85: LISTA PREZZI | F85: =IFERROR(__xludf.DUMMYFUNCTION("IFERROR(TRANSPOSE(SORT(UNIQUE(FILTER($M$4:$M$83,$M$4:$M$83<>"""")))),"""")"),30.0) -> 30 | G85: =IFERROR(__xludf.DUMMYFUNCTION("""COMPUTED_VALUE"""),32.0) -> 32 | P85: TOTALE | Q85: =IF(SUM(F87:O87)=0,"",SUM(F87:O87)) -> 182 | R85: Verifica | S85: =IF(SUM(M84) = SUM(Q85:Q89), "OK", "ERRORE") -> OK
A86: ONLINE | B86: =COUNTIF(B4:B83, "ONLINE") -> 11 | E86: PERSONE SEDE | F86: =IF( F$85="", "", COUNTIFS($B$4:$B$83,"*SEDE*",$M$4:$M$83,F$85) ) -> 5 | G86: =IF( G$85="", "", COUNTIFS($B$4:$B$83,"*SEDE*",$M$4:$M$83,G$85) ) -> 1 | H86: =IF( H$85="", "", COUNTIFS($B$4:$B$83,"*SEDE*",$M$4:$M$83,H$85) ) | I86: =IF( I$85="", "", COUNTIFS($B$4:$B$83,"*SEDE*",$M$4:$M$83,I$85) ) | J86: =IF( J$85="", "", COUNTIFS($B$4:$B$83,"*SEDE*",$M$4:$M$83,J$85) ) | K86: =IF( K$85="", "", COUNTIFS($B$4:$B$83,"*SEDE*",$M$4:$M$83,K$85) ) | L86: =IF( L$85="", "", COUNTIFS($B$4:$B$83,"*SEDE*",$M$4:$M$83,L$85) ) | M86: =IF( M$85="", "", COUNTIFS($B$4:$B$83,"*SEDE*",$M$4:$M$83,M$85) ) | ... O86: =IF( O$85="", "", COUNTIFS($B$4:$B$83,"*SEDE*",$M$4:$M$83,O$85) )
E87: subTOTALE SEDE | F87: =IF( F$85="", "", SUMIFS($M$4:$M$83,$B$4:$B$83,"*SEDE*",$M$4:$M$83,F$85) ) -> 150 | G87: =IF( G$85="", "", SUMIFS($M$4:$M$83,$B$4:$B$83,"*SEDE*",$M$4:$M$83,G$85) ) -> 32 | H87: =IF( H$85="", "", SUMIFS($M$4:$M$83,$B$4:$B$83,"*SEDE*",$M$4:$M$83,H$85) ) | I87: =IF( I$85="", "", SUMIFS($M$4:$M$83,$B$4:$B$83,"*SEDE*",$M$4:$M$83,I$85) ) | J87: =IF( J$85="", "", SUMIFS($M$4:$M$83,$B$4:$B$83,"*SEDE*",$M$4:$M$83,J$85) ) | K87: =IF( K$85="", "", SUMIFS($M$4:$M$83,$B$4:$B$83,"*SEDE*",$M$4:$M$83,K$85) ) | L87: =IF( L$85="", "", SUMIFS($M$4:$M$83,$B$4:$B$83,"*SEDE*",$M$4:$M$83,L$85) ) | M87: =IF( M$85="", "", SUMIFS($M$4:$M$83,$B$4:$B$83,"*SEDE*",$M$4:$M$83,M$85) ) | ... O87: =IF( O$85="", "", SUMIFS($M$4:$M$83,$B$4:$B$83,"*SEDE*",$M$4:$M$83,O$85) )
E88: PERSONE ONLINE | F88: =IF( F$85="", "", COUNTIFS($B$4:$B$83,"*ONLINE*",$M$4:$M$83,F$85) ) -> 4 | G88: =IF( G$85="", "", COUNTIFS($B$4:$B$83,"*ONLINE*",$M$4:$M$83,G$85) ) -> 7 | H88: =IF( H$85="", "", COUNTIFS($B$4:$B$83,"*ONLINE*",$M$4:$M$83,H$85) ) | I88: =IF( I$85="", "", COUNTIFS($B$4:$B$83,"*ONLINE*",$M$4:$M$83,I$85) ) | J88: =IF( J$85="", "", COUNTIFS($B$4:$B$83,"*ONLINE*",$M$4:$M$83,J$85) ) | K88: =IF( K$85="", "", COUNTIFS($B$4:$B$83,"*ONLINE*",$M$4:$M$83,K$85) ) | L88: =IF( L$85="", "", COUNTIFS($B$4:$B$83,"*ONLINE*",$M$4:$M$83,L$85) ) | M88: =IF( M$85="", "", COUNTIFS($B$4:$B$83,"*ONLINE*",$M$4:$M$83,M$85) ) | ... O88: =IF( O$85="", "", COUNTIFS($B$4:$B$83,"*ONLINE*",$M$4:$M$83,O$85) ) | P88: TOTALE | Q88: =IF(SUM(F89:O89)=0,"",SUM(F89:O89)) -> 344
E89: subTOTALE ONLINE | F89: =IF( F$85="", "", SUMIFS($M$4:$M$83,$B$4:$B$83,"*ONLINE*",$M$4:$M$83,F$85) ) -> 120 | G89: =IF( G$85="", "", SUMIFS($M$4:$M$83,$B$4:$B$83,"*ONLINE*",$M$4:$M$83,G$85) ) -> 224 | H89: =IF( H$85="", "", SUMIFS($M$4:$M$83,$B$4:$B$83,"*ONLINE*",$M$4:$M$83,H$85) ) | I89: =IF( I$85="", "", SUMIFS($M$4:$M$83,$B$4:$B$83,"*ONLINE*",$M$4:$M$83,I$85) ) | J89: =IF( J$85="", "", SUMIFS($M$4:$M$83,$B$4:$B$83,"*ONLINE*",$M$4:$M$83,J$85) ) | K89: =IF( K$85="", "", SUMIFS($M$4:$M$83,$B$4:$B$83,"*ONLINE*",$M$4:$M$83,K$85) ) | L89: =IF( L$85="", "", SUMIFS($M$4:$M$83,$B$4:$B$83,"*ONLINE*",$M$4:$M$83,L$85) ) | M89: =IF( M$85="", "", SUMIFS($M$4:$M$83,$B$4:$B$83,"*ONLINE*",$M$4:$M$83,M$85) ) | ... O89: =IF( O$85="", "", SUMIFS($M$4:$M$83,$B$4:$B$83,"*ONLINE*",$M$4:$M$83,O$85) )
C90: LISTA D'ATTESA oppure [ORARIO]_[GENERE] (€X entro il XX/XX compreso → €Y entro il YY/YY compreso → €Z il giorno stesso)
M91: =IFERROR(__xludf.DUMMYFUNCTION("IF( K91="""", """", ROUND( IF( L91="""", K91, IF( ISERROR(FIND(""-"",L91)), K91 - VALUE(REGEXEXTRACT(L91,""(\d+)"")), K91 * (1 - VALUE(REGEXEXTRACT(L91,""(\d+)""))/100) ) ), 2 ) ) ")," ") | O91: FALSE | R91: FALSE | S91: FALSE | T91: FALSE
M92: =IFERROR(__xludf.DUMMYFUNCTION("IF( K92="""", """", ROUND( IF( L92="""", K92, IF( ISERROR(FIND(""-"",L92)), K92 - VALUE(REGEXEXTRACT(L92,""(\d+)"")), K92 * (1 - VALUE(REGEXEXTRACT(L92,""(\d+)""))/100) ) ), 2 ) ) ")," ") | O92: FALSE | R92: FALSE | S92: FALSE | T92: FALSE
M93: =IFERROR(__xludf.DUMMYFUNCTION("IF( K93="""", """", ROUND( IF( L93="""", K93, IF( ISERROR(FIND(""-"",L93)), K93 - VALUE(REGEXEXTRACT(L93,""(\d+)"")), K93 * (1 - VALUE(REGEXEXTRACT(L93,""(\d+)""))/100) ) ), 2 ) ) ")," ") | O93: FALSE | R93: FALSE | S93: FALSE | T93: FALSE
M94: =IFERROR(__xludf.DUMMYFUNCTION("IF( K94="""", """", ROUND( IF( L94="""", K94, IF( ISERROR(FIND(""-"",L94)), K94 - VALUE(REGEXEXTRACT(L94,""(\d+)"")), K94 * (1 - VALUE(REGEXEXTRACT(L94,""(\d+)""))/100) ) ), 2 ) ) ")," ") | O94: FALSE | R94: FALSE | S94: FALSE | T94: FALSE
M95: =IFERROR(__xludf.DUMMYFUNCTION("IF( K95="""", """", ROUND( IF( L95="""", K95, IF( ISERROR(FIND(""-"",L95)), K95 - VALUE(REGEXEXTRACT(L95,""(\d+)"")), K95 * (1 - VALUE(REGEXEXTRACT(L95,""(\d+)""))/100) ) ), 2 ) ) ")," ") | O95: FALSE | R95: FALSE | S95: FALSE | T95: FALSE
M96: =IFERROR(__xludf.DUMMYFUNCTION("IF( K96="""", """", ROUND( IF( L96="""", K96, IF( ISERROR(FIND(""-"",L96)), K96 - VALUE(REGEXEXTRACT(L96,""(\d+)"")), K96 * (1 - VALUE(REGEXEXTRACT(L96,""(\d+)""))/100) ) ), 2 ) ) ")," ") | O96: FALSE | R96: FALSE | S96: FALSE | T96: FALSE
M97: =IFERROR(__xludf.DUMMYFUNCTION("IF( K97="""", """", ROUND( IF( L97="""", K97, IF( ISERROR(FIND(""-"",L97)), K97 - VALUE(REGEXEXTRACT(L97,""(\d+)"")), K97 * (1 - VALUE(REGEXEXTRACT(L97,""(\d+)""))/100) ) ), 2 ) ) ")," ") | O97: FALSE | R97: FALSE | S97: FALSE | T97: FALSE
M98: =IFERROR(__xludf.DUMMYFUNCTION("IF( K98="""", """", ROUND( IF( L98="""", K98, IF( ISERROR(FIND(""-"",L98)), K98 - VALUE(REGEXEXTRACT(L98,""(\d+)"")), K98 * (1 - VALUE(REGEXEXTRACT(L98,""(\d+)""))/100) ) ), 2 ) ) ")," ") | O98: FALSE | R98: FALSE | S98: FALSE | T98: FALSE
M99: =IFERROR(__xludf.DUMMYFUNCTION("IF( K99="""", """", ROUND( IF( L99="""", K99, IF( ISERROR(FIND(""-"",L99)), K99 - VALUE(REGEXEXTRACT(L99,""(\d+)"")), K99 * (1 - VALUE(REGEXEXTRACT(L99,""(\d+)""))/100) ) ), 2 ) ) ")," ") | O99: FALSE | R99: FALSE | S99: FALSE | T99: FALSE
M100: =IFERROR(__xludf.DUMMYFUNCTION("IF( K100="""", """", ROUND( IF( L100="""", K100, IF( ISERROR(FIND(""-"",L100)), K100 - VALUE(REGEXEXTRACT(L100,""(\d+)"")), K100 * (1 - VALUE(REGEXEXTRACT(L100,""(\d+)""))/100) ) ), 2 ) )"&" ")," ") | O100: FALSE | R100: FALSE | S100: FALSE | T100: FALSE
...

Sheet WS_DIA_EN_CUBA
C1: WS_DIA EN CUBA_15MAR2026
A2: CHI SCRIVE | B2: VENDITA | C2: DATA INSERIMENTO /RICHIESTA | D2: ID ANAGRAFICA | E2: COGNOME | F2: NOME | G2: TELEFONO | H2: CODICE FISCALE | I2: EMAIL | J2: DATA PAGAMENTO /RICEVUTA | K2: QUOTA | L2: CODICE SCONTO | M2: IMPORTO FINALE | N2: DIGIT/CASH - TESS/NON TESS | O2: PRESENZA | P2: NOTE | Q2: INSERITO SU ATHENA | R2: RICEVUTA FATTA | S2: FATTURA FATTA | T2: VERIFICA PAGAMENTO
C3: 1° WS - YANEDIS - orario 14:30/15:30_GESTUALITA FEMMINILE (€32 entro il 14/02 compreso → €37 entro il 15/03 compreso) | N3: PRESENZA DONNE | O3: =SUMPRODUCT(--$O$4:$O$43) -> 32
A4: Estefany | B4: ONLINE | C4: 46063 | D4: ID-001250 | E4: SCIPIONI | F4: CLAUDIA | G4: 3396859611 | H4: SCPCLD64D42D749C | I4: claudia.scipioni@comune.milano.it | J4: 46063 | K4: 32 | M4: =IFERROR(__xludf.DUMMYFUNCTION("IF( K4="""", """", ROUND( IF( L4="""", K4, IF( ISERROR(FIND(""-"",L4)), K4 - VALUE(REGEXEXTRACT(L4,""(\d+)"")), K4 * (1 - VALUE(REGEXEXTRACT(L4,""(\d+)""))/100) ) ), 2 ) ) "),32.0) -> 32 | N4: DIGIT - TESSERATO | O4: TRUE | Q4: INSERITO | R4: TRUE | S4: FALSE | T4: TRUE
A5: Estefany | B5: ONLINE | C5: 46063 | D5: ID-000087 | E5: ROUVIERE | F5: SANDRA | G5: 3346051490 | H5: RVRSDR79R62Z110V | I5: sandra.rouviere123@gmail.com | J5: 46063 | K5: 32 | M5: =IFERROR(__xludf.DUMMYFUNCTION("IF( K5="""", """", ROUND( IF( L5="""", K5, IF( ISERROR(FIND(""-"",L5)), K5 - VALUE(REGEXEXTRACT(L5,""(\d+)"")), K5 * (1 - VALUE(REGEXEXTRACT(L5,""(\d+)""))/100) ) ), 2 ) ) "),32.0) -> 32 | N5: DIGIT - TESSERATO | O5: TRUE | Q5: INSERITO | R5: TRUE | S5: FALSE | T5: TRUE
A6: Estefany | B6: ONLINE | C6: 46063 | D6: ID-002969 | E6: REDFERN | F6: JADE LISA | G6: 3355278963 | H6: RDFJLS04H45I577J | I6: jadelisaredfern@gmail.com | J6: 46063 | K6: 32 | L6: ESTEFANY02WS | M6: =IFERROR(__xludf.DUMMYFUNCTION("IF( K6="""", """", ROUND( IF( L6="""", K6, IF( ISERROR(FIND(""-"",L6)), K6 - VALUE(REGEXEXTRACT(L6,""(\d+)"")), K6 * (1 - VALUE(REGEXEXTRACT(L6,""(\d+)""))/100) ) ), 2 ) ) "),30.0) -> 30 | N6: DIGIT - TESSERATO | O6: TRUE | Q6: INSERITO | R6: TRUE | S6: FALSE | T6: TRUE
A7: Estefany | B7: ONLINE | C7: 46063 | D7: ID-001804 | E7: CRIPPA | F7: MELIDE | G7: 3381642215 | H7: CRPMLD99M70E507E | I7: crippamelide@gmail.com | J7: 46063 | K7: 32 | M7: =IFERROR(__xludf.DUMMYFUNCTION("IF( K7="""", """", ROUND( IF( L7="""", K7, IF( ISERROR(FIND(""-"",L7)), K7 - VALUE(REGEXEXTRACT(L7,""(\d+)"")), K7 * (1 - VALUE(REGEXEXTRACT(L7,""(\d+)""))/100) ) ), 2 ) ) "),32.0) -> 32 | N7: DIGIT - TESSERATO | O7: TRUE | Q7: INSERITO | R7: TRUE | S7: FALSE | T7: TRUE
A8: Estefany | B8: ONLINE | C8: 46064 | D8: ID-001550 | E8: LATINI GUICCIARDI | F8: LUDOVICA | G8: 3496579417 | H8: LTNLVC95T66H501R | I8: ludo.latini@gmail.com | J8: 46064 | K8: 32 | M8: =IFERROR(__xludf.DUMMYFUNCTION("IF( K8="""", """", ROUND( IF( L8="""", K8, IF( ISERROR(FIND(""-"",L8)), K8 - VALUE(REGEXEXTRACT(L8,""(\d+)"")), K8 * (1 - VALUE(REGEXEXTRACT(L8,""(\d+)""))/100) ) ), 2 ) ) "),32.0) -> 32 | N8: DIGIT - TESSERATO | O8: TRUE | Q8: INSERITO | R8: TRUE | S8: FALSE | T8: TRUE
A9: Estefany | B9: ONLINE | C9: 46065 | E9: CARRIERA | F9: MARTA | G9: 3770848139 | H9: CRRMRT00P67G388G | I9: mcarriera27@gmail.com | J9: 46065 | K9: 32 | L9: ALEXANDRA02WS | M9: =IFERROR(__xludf.DUMMYFUNCTION("IF( K9="""", """", ROUND( IF( L9="""", K9, IF( ISERROR(FIND(""-"",L9)), K9 - VALUE(REGEXEXTRACT(L9,""(\d+)"")), K9 * (1 - VALUE(REGEXEXTRACT(L9,""(\d+)""))/100) ) ), 2 ) ) "),30.0) -> 30 | N9: DIGIT - NON TESSERATO | O9: TRUE | Q9: INSERITO | R9: FALSE | S9: TRUE | T9: TRUE
A10: Giuditta | B10: SEDE Giuditta | C10: 46065 | E10: BIANCHI | F10: ANGELA | G10: 3938905093 | H10: BNCNGL82P59L483M | I10: angela.19.bianchi.82@gmail.com | J10: 46065 | K10: 32 | L10: GIUDITTA02WS | M10: =IFERROR(__xludf.DUMMYFUNCTION("IF( K10="""", """", ROUND( IF( L10="""", K10, IF( ISERROR(FIND(""-"",L10)), K10 - VALUE(REGEXEXTRACT(L10,""(\d+)"")), K10 * (1 - VALUE(REGEXEXTRACT(L10,""(\d+)""))/100) ) ), 2 ) ) "),30.0) -> 30 | N10: CASH - TESSERATO | O10: TRUE | Q10: INSERITO | R10: TRUE | S10: FALSE | T10: TRUE
A11: Estefany | B11: ONLINE | C11: 46065 | E11: GENTILI | F11: IRENE | G11: 3202477786 | H11: GNTRNI91T56E783X | I11: gentili.irene@gmail.com | J11: 46065 | K11: 32 | M11: =IFERROR(__xludf.DUMMYFUNCTION("IF( K11="""", """", ROUND( IF( L11="""", K11, IF( ISERROR(FIND(""-"",L11)), K11 - VALUE(REGEXEXTRACT(L11,""(\d+)"")), K11 * (1 - VALUE(REGEXEXTRACT(L11,""(\d+)""))/100) ) ), 2 ) ) "),32.0) -> 32 | N11: DIGIT - TESSERATO | O11: TRUE | Q11: INSERITO | R11: TRUE | S11: FALSE | T11: TRUE
A12: Giuditta | B12: SEDE Giuditta | C12: 46066 | E12: GRAMEGNA | F12: VALERIA | G12: 3398864050 | H12: GRMPML82S65F205N | I12: pamelagramegna@gmail.com | J12: 46066 | K12: 32 | L12: GIUDITTA02WS | M12: =IFERROR(__xludf.DUMMYFUNCTION("IF( K12="""", """", ROUND( IF( L12="""", K12, IF( ISERROR(FIND(""-"",L12)), K12 - VALUE(REGEXEXTRACT(L12,""(\d+)"")), K12 * (1 - VALUE(REGEXEXTRACT(L12,""(\d+)""))/100) ) ), 2 ) ) "),30.0) -> 30 | N12: CASH - TESSERATO | O12: TRUE | Q12: INSERITO | R12: TRUE | S12: FALSE | T12: TRUE
A13: Estefany | B13: ONLINE | C13: 46066 | D13: ID-000898 | E13: PRECERUTTI | F13: MANUELA | G13: 3420984354 | H13: PRCMNL64P64F205Y | I13: manuela.precerutti@cchellenic.com | J13: 46066 | K13: 32 | L13: ALEXANDRA02WS | M13: =IFERROR(__xludf.DUMMYFUNCTION("IF( K13="""", """", ROUND( IF( L13="""", K13, IF( ISERROR(FIND(""-"",L13)), K13 - VALUE(REGEXEXTRACT(L13,""(\d+)"")), K13 * (1 - VALUE(REGEXEXTRACT(L13,""(\d+)""))/100) ) ), 2 ) ) "),30.0) -> 30 | N13: DIGIT - TESSERATO | O13: TRUE | Q13: INSERITO | R13: TRUE | S13: FALSE | T13: TRUE
A14: Estefany | B14: ONLINE | C14: 46067 | D14: ID-001745 | E14: CARRIERO | F14: DANIELA ANTONELLA | G14: 3346013249 | H14: CRRDLN65D53F205I | I14: Danielacarriero@yahoo.it | J14: 46067 | K14: 32 | M14: =IFERROR(__xludf.DUMMYFUNCTION("IF( K14="""", """", ROUND( IF( L14="""", K14, IF( ISERROR(FIND(""-"",L14)), K14 - VALUE(REGEXEXTRACT(L14,""(\d+)"")), K14 * (1 - VALUE(REGEXEXTRACT(L14,""(\d+)""))/100) ) ), 2 ) ) "),32.0) -> 32 | N14: DIGIT - TESSERATO | O14: TRUE | Q14: INSERITO | R14: TRUE | S14: FALSE | T14: TRUE
A15: Estefany | B15: SEDE Estefany | C15: 46069 | D15: ID-000348 | E15: BUA | F15: LETIZIA | G15: 3896980899 | H15: BUALTZ01L58F205U | I15: perrie2013@libero.it | J15: 46069 | K15: 37 | L15: ESTEFANY02WS | M15: =IFERROR(__xludf.DUMMYFUNCTION("IF( K15="""", """", ROUND( IF( L15="""", K15, IF( ISERROR(FIND(""-"",L15)), K15 - VALUE(REGEXEXTRACT(L15,""(\d+)"")), K15 * (1 - VALUE(REGEXEXTRACT(L15,""(\d+)""))/100) ) ), 2 ) ) "),35.0) -> 35 | N15: CASH - TESSERATO | O15: FALSE | Q15: INSERITO | R15: TRUE | S15: FALSE | T15: TRUE
A16: Estefany | B16: ONLINE | C16: 46067 | D16: ID-001366 | E16: MARASCHI | F16: PADMINI | G16: 3807877826 | H16: MRSPMN99H61Z222B | I16: paddy.mx9@gmail.com | J16: 46067 | K16: 32 | L16: NURA02WS | M16: =IFERROR(__xludf.DUMMYFUNCTION("IF( K16="""", """", ROUND( IF( L16="""", K16, IF( ISERROR(FIND(""-"",L16)), K16 - VALUE(REGEXEXTRACT(L16,""(\d+)"")), K16 * (1 - VALUE(REGEXEXTRACT(L16,""(\d+)""))/100) ) ), 2 ) ) "),30.0) -> 30 | N16: DIGIT - TESSERATO | O16: TRUE | Q16: INSERITO | R16: TRUE | S16: FALSE | T16: TRUE
A17: Estefany | B17: ONLINE | C17: 46067 | D17: ID-002259 | E17: ELEUTERI | F17: GIULIA | G17: 3486480889 | H17: LTRGLI06H52A944N | I17: giulia.eleuteri06@gmail.com | J17: 46067 | K17: 32 | M17: =IFERROR(__xludf.DUMMYFUNCTION("IF( K17="""", """", ROUND( IF( L17="""", K17, IF( ISERROR(FIND(""-"",L17)), K17 - VALUE(REGEXEXTRACT(L17,""(\d+)"")), K17 * (1 - VALUE(REGEXEXTRACT(L17,""(\d+)""))/100) ) ), 2 ) ) "),32.0) -> 32 | N17: DIGIT - TESSERATO | O17: TRUE | Q17: INSERITO | R17: TRUE | S17: FALSE | T17: TRUE
A18: Estefany | B18: ONLINE | C18: 46069 | D18: ID-000113 | E18: LACAGNINA | F18: ROBERTA | G18: 3923922667 | H18: LCGRRT81A57G273D | I18: roberta.lacagnina@gmail.com | J18: 46069 | K18: 37 | L18: UNDIAENCUBA05 | M18: =IFERROR(__xludf.DUMMYFUNCTION("IF( K18="""", """", ROUND( IF( L18="""", K18, IF( ISERROR(FIND(""-"",L18)), K18 - VALUE(REGEXEXTRACT(L18,""(\d+)"")), K18 * (1 - VALUE(REGEXEXTRACT(L18,""(\d+)""))/100) ) ), 2 ) ) "),32.0) -> 32 | N18: DIGIT - TESSERATO | O18: TRUE | Q18: INSERITO | R18: TRUE | S18: FALSE | T18: TRUE
A19: Estefany | B19: ONLINE | C19: 46070 | D19: ID-001314 | E19: INGEGNERI | F19: VIRGINIA | G19: 3478840176 | H19: NGGVGN91E55A059K | I19: virginiaingegneri@gmail.com | J19: 46070 | K19: 37 | M19: =IFERROR(__xludf.DUMMYFUNCTION("IF( K19="""", """", ROUND( IF( L19="""", K19, IF( ISERROR(FIND(""-"",L19)), K19 - VALUE(REGEXEXTRACT(L19,""(\d+)"")), K19 * (1 - VALUE(REGEXEXTRACT(L19,""(\d+)""))/100) ) ), 2 ) ) "),37.0) -> 37 | N19: DIGIT - TESSERATO | O19: TRUE | Q19: INSERITO | R19: TRUE | S19: FALSE | T19: TRUE
A20: Estefany | B20: ONLINE | C20: 46070 | D20: ID-000814 | E20: MARIANI | F20: ROBERTA | G20: 3498923170 | H20: MRNRRT87R46F205T | I20: Roberta_Mariani@hotmail.it | J20: 46070 | K20: 37 | M20: =IFERROR(__xludf.DUMMYFUNCTION("IF( K20="""", """", ROUND( IF( L20="""", K20, IF( ISERROR(FIND(""-"",L20)), K20 - VALUE(REGEXEXTRACT(L20,""(\d+)"")), K20 * (1 - VALUE(REGEXEXTRACT(L20,""(\d+)""))/100) ) ), 2 ) ) "),37.0) -> 37 | N20: DIGIT - TESSERATO | O20: TRUE | Q20: INSERITO | R20: TRUE | S20: FALSE | T20: TRUE
A21: Estefany | B21: ONLINE | C21: 46074 | D21: ID-000788 | E21: TOSCANO | F21: CHIARA | G21: 3286790381 | H21: TSCCHR88C50A053U | I21: chiaratoscano@tiscali.it | J21: 46074 | K21: 37 | L21: ESTEFANY02WS | M21: =IFERROR(__xludf.DUMMYFUNCTION("IF( K21="""", """", ROUND( IF( L21="""", K21, IF( ISERROR(FIND(""-"",L21)), K21 - VALUE(REGEXEXTRACT(L21,""(\d+)"")), K21 * (1 - VALUE(REGEXEXTRACT(L21,""(\d+)""))/100) ) ), 2 ) ) "),35.0) -> 35 | N21: DIGIT - TESSERATO | O21: TRUE | Q21: INSERITO | R21: TRUE | S21: FALSE | T21: TRUE
A22: Estefany | B22: ONLINE | C22: 46074 | E22: GASPARRONI | F22: SERENA | G22: 3497103252 | H22: GSPSRN84R61E783S | I22: s.gasparroni@gmail.com | J22: 46074 | K22: 37 | M22: =IFERROR(__xludf.DUMMYFUNCTION("IF( K22="""", """", ROUND( IF( L22="""", K22, IF( ISERROR(FIND(""-"",L22)), K22 - VALUE(REGEXEXTRACT(L22,""(\d+)"")), K22 * (1 - VALUE(REGEXEXTRACT(L22,""(\d+)""))/100) ) ), 2 ) ) "),37.0) -> 37 | N22: DIGIT - NON TESSERATO | O22: TRUE | P22: HA PAGATO X2 | Q22: INSERITO | R22: FALSE | S22: TRUE | T22: TRUE
A23: Estefany | B23: ONLINE | C23: 46074 | E23: GASPARRONI | F23: SERENA | G23: 3497103252 | H23: GSPSRN84R61E783S | I23: s.gasparroni@gmail.com | J23: 46074 | K23: 37 | M23: =IFERROR(__xludf.DUMMYFUNCTION("IF( K23="""", """", ROUND( IF( L23="""", K23, IF( ISERROR(FIND(""-"",L23)), K23 - VALUE(REGEXEXTRACT(L23,""(\d+)"")), K23 * (1 - VALUE(REGEXEXTRACT(L23,""(\d+)""))/100) ) ), 2 ) ) "),37.0) -> 37 | N23: DIGIT - NON TESSERATO | O23: TRUE | P23: HA PAGATO X2 | Q23: INSERITO | R23: FALSE | S23: TRUE | T23: TRUE
A24: Estefany | B24: ONLINE | C24: 46075 | E24: NOVAES SANTOS | F24: LAILA | G24: 3272618075 | H24: NVSLLA88T68Z602X | I24: novaes.laila@gmail.com | J24: 46075 | K24: 37 | M24: =IFERROR(__xludf.DUMMYFUNCTION("IF( K24="""", """", ROUND( IF( L24="""", K24, IF( ISERROR(FIND(""-"",L24)), K24 - VALUE(REGEXEXTRACT(L24,""(\d+)"")), K24 * (1 - VALUE(REGEXEXTRACT(L24,""(\d+)""))/100) ) ), 2 ) ) "),37.0) -> 37 | N24: DIGIT - NON TESSERATO | O24: TRUE | Q24: INSERITO | R24: FALSE | S24: TRUE | T24: TRUE
A25: Estefany | B25: ONLINE | C25: 46080 | D25: ID-002822 | E25: MARSEGLIA | F25: SABINA | G25: 3482727792 | H25: MRSSBN70T50F205I | I25: sabrina.marseglia@gmail.com | J25: 46080 | K25: 37 | M25: =IFERROR(__xludf.DUMMYFUNCTION("IF( K25="""", """", ROUND( IF( L25="""", K25, IF( ISERROR(FIND(""-"",L25)), K25 - VALUE(REGEXEXTRACT(L25,""(\d+)"")), K25 * (1 - VALUE(REGEXEXTRACT(L25,""(\d+)""))/100) ) ), 2 ) ) "),37.0) -> 37 | N25: DIGIT - TESSERATO | O25: TRUE | Q25: INSERITO | R25: TRUE | S25: FALSE | T25: TRUE
A26: Estefany | B26: ONLINE | C26: 46082 | E26: D'ORIA | F26: LAURA | G26: 3468106903 | H26: DROLRA70H63H264Y | I26: laura.doria1970@gmail.com | J26: 46082 | K26: 37 | M26: =IFERROR(__xludf.DUMMYFUNCTION("IF( K26="""", """", ROUND( IF( L26="""", K26, IF( ISERROR(FIND(""-"",L26)), K26 - VALUE(REGEXEXTRACT(L26,""(\d+)"")), K26 * (1 - VALUE(REGEXEXTRACT(L26,""(\d+)""))/100) ) ), 2 ) ) "),37.0) -> 37 | N26: DIGIT - NON TESSERATO | O26: TRUE | Q26: INSERITO | R26: FALSE | S26: TRUE | T26: TRUE
A27: Estefany | B27: ONLINE | C27: 46083 | E27: LUKASOVA | F27: KATERINA | G27: 3334201020 | H27: LKSKRN75R42Z156L | I27: katerinalksv@gmail.com | J27: 46083 | K27: 37 | L27: ESTEFANY02WS | M27: =IFERROR(__xludf.DUMMYFUNCTION("IF( K27="""", """", ROUND( IF( L27="""", K27, IF( ISERROR(FIND(""-"",L27)), K27 - VALUE(REGEXEXTRACT(L27,""(\d+)"")), K27 * (1 - VALUE(REGEXEXTRACT(L27,""(\d+)""))/100) ) ), 2 ) ) "),35.0) -> 35 | N27: DIGIT - NON TESSERATO | O27: TRUE | Q27: INSERITO | R27: FALSE | S27: TRUE | T27: TRUE
A28: Nura | B28: SEDE Nura | C28: 46088 | E28: CANNIZZARO | F28: GIULIA | G28: 3291314909 | H28: CNNGLI00S55B300S | I28: giulia00cannizzaro@gmail.com | J28: 46088 | K28: 37 | M28: =IFERROR(__xludf.DUMMYFUNCTION("IF( K28="""", """", ROUND( IF( L28="""", K28, IF( ISERROR(FIND(""-"",L28)), K28 - VALUE(REGEXEXTRACT(L28,""(\d+)"")), K28 * (1 - VALUE(REGEXEXTRACT(L28,""(\d+)""))/100) ) ), 2 ) ) "),37.0) -> 37 | N28: DIGIT - TESSERATO | O28: TRUE | Q28: INSERITO | R28: TRUE | S28: FALSE | T28: TRUE
A29: Nura | B29: SEDE Nura | C29: 46091 | E29: MEUCCI | F29: EMANUELA EMILIA | G29: 3333544512 | H29: MCCMLM83M43F205X | I29: emanuela.meucci@gmail.com | J29: 46091 | K29: 37 | L29: NURA02WS | M29: =IFERROR(__xludf.DUMMYFUNCTION("IF( K29="""", """", ROUND( IF( L29="""", K29, IF( ISERROR(FIND(""-"",L29)), K29 - VALUE(REGEXEXTRACT(L29,""(\d+)"")), K29 * (1 - VALUE(REGEXEXTRACT(L29,""(\d+)""))/100) ) ), 2 ) ) "),35.0) -> 35 | N29: DIGIT - TESSERATO | O29: TRUE | Q29: INSERITO | R29: TRUE | S29: FALSE | T29: TRUE
A30: Nura | B30: SEDE Nura | C30: 46091 | E30: MARITATO | F30: MONICA ANNA | G30: 3208721656 | H30: MRTMCN77L58C002J | I30: MARITATO.MONICA@VIRGILIO.IT | J30: 46091 | K30: 37 | L30: NURA02WS | M30: =IFERROR(__xludf.DUMMYFUNCTION("IF( K30="""", """", ROUND( IF( L30="""", K30, IF( ISERROR(FIND(""-"",L30)), K30 - VALUE(REGEXEXTRACT(L30,""(\d+)"")), K30 * (1 - VALUE(REGEXEXTRACT(L30,""(\d+)""))/100) ) ), 2 ) ) "),35.0) -> 35 | N30: DIGIT - TESSERATO | O30: TRUE | Q30: INSERITO | R30: TRUE | S30: FALSE | T30: TRUE
A31: Estefany | B31: ONLINE | C31: 46092 | E31: SORESEN | F31: SARA | G31: 3342155647 | H31: SRNSMR91T65Z116Q | I31: sara.m.sorensen@gmail.com | J31: 46092 | K31: 37 | M31: =IFERROR(__xludf.DUMMYFUNCTION("IF( K31="""", """", ROUND( IF( L31="""", K31, IF( ISERROR(FIND(""-"",L31)), K31 - VALUE(REGEXEXTRACT(L31,""(\d+)"")), K31 * (1 - VALUE(REGEXEXTRACT(L31,""(\d+)""))/100) ) ), 2 ) ) "),37.0) -> 37 | N31: DIGIT - NON TESSERATO | O31: TRUE | Q31: INSERITO | R31: FALSE | S31: TRUE | T31: TRUE
A32: Estefany | B32: ONLINE | C32: 46092 | E32: CAMPOLUNGO | F32: SARA | G32: 3401295574 | H32: CMPSRA91S66A271J | I32: sara.campolungo@tiscali.it | J32: 46092 | K32: 37 | M32: =IFERROR(__xludf.DUMMYFUNCTION("IF( K32="""", """", ROUND( IF( L32="""", K32, IF( ISERROR(FIND(""-"",L32)), K32 - VALUE(REGEXEXTRACT(L32,""(\d+)"")), K32 * (1 - VALUE(REGEXEXTRACT(L32,""(\d+)""))/100) ) ), 2 ) ) "),37.0) -> 37 | N32: DIGIT - NON TESSERATO | O32: TRUE | Q32: INSERITO | R32: FALSE | S32: TRUE | T32: TRUE
A33: Estefany | B33: ONLINE | C33: 46093 | D33: ID-003270 | E33: SORIA | F33: ANNA | G33: 9178530786 | H33: SRONFL88R66Z404U | I33: annafeliciavs@gmail.com | J33: 46093 | K33: 37 | M33: =IFERROR(__xludf.DUMMYFUNCTION("IF( K33="""", """", ROUND( IF( L33="""", K33, IF( ISERROR(FIND(""-"",L33)), K33 - VALUE(REGEXEXTRACT(L33,""(\d+)"")), K33 * (1 - VALUE(REGEXEXTRACT(L33,""(\d+)""))/100) ) ), 2 ) ) "),37.0) -> 37 | N33: DIGIT - TESSERATO | O33: TRUE | Q33: INSERITO | R33: TRUE | S33: FALSE | T33: TRUE
A34: Estefany | B34: ONLINE | C34: 46095 | D34: ID-001944 | E34: KARA | F34: SERAP | G34: 393760494267 | H34: KRASRP97E63Z243W | I34: serap.karaa97@gmail.com | J34: 46095 | K34: 37 | M34: =IFERROR(__xludf.DUMMYFUNCTION("IF( K34="""", """", ROUND( IF( L34="""", K34, IF( ISERROR(FIND(""-"",L34)), K34 - VALUE(REGEXEXTRACT(L34,""(\d+)"")), K34 * (1 - VALUE(REGEXEXTRACT(L34,""(\d+)""))/100) ) ), 2 ) ) "),37.0) -> 37 | N34: DIGIT - TESSERATO | O34: TRUE | Q34: INSERITO | R34: TRUE | S34: FALSE | T34: TRUE
A35: Estefany | B35: ONLINE | C35: 46095 | E35: MORETTI | F35: PATRIZIA | G35: 3460892521 | H35: MRTPRZ74B45H827Y | I35: patriziamoretti@tiscali.it | J35: 46095 | K35: 37 | L35: ESTEFANY02WS | M35: =IFERROR(__xludf.DUMMYFUNCTION("IF( K35="""", """", ROUND( IF( L35="""", K35, IF( ISERROR(FIND(""-"",L35)), K35 - VALUE(REGEXEXTRACT(L35,""(\d+)"")), K35 * (1 - VALUE(REGEXEXTRACT(L35,""(\d+)""))/100) ) ), 2 ) ) "),35.0) -> 35 | N35: DIGIT - NON TESSERATO | O35: TRUE | Q35: INSERITO | R35: FALSE | S35: TRUE | T35: TRUE
A36: Estefany | B36: ONLINE | C36: 46095 | E36: CONTE | F36: ELENA | G36: 3476833177 | H36: CNTLNE75S61F205A | I36: ele.conte75@gmail.com | J36: 46095 | K36: 37 | L36: ESTEFANY02WS | M36: =IFERROR(__xludf.DUMMYFUNCTION("IF( K36="""", """", ROUND( IF( L36="""", K36, IF( ISERROR(FIND(""-"",L36)), K36 - VALUE(REGEXEXTRACT(L36,""(\d+)"")), K36 * (1 - VALUE(REGEXEXTRACT(L36,""(\d+)""))/100) ) ), 2 ) ) "),35.0) -> 35 | N36: DIGIT - NON TESSERATO | O36: TRUE | Q36: INSERITO | R36: FALSE | S36: TRUE | T36: TRUE
M37: =IFERROR(__xludf.DUMMYFUNCTION("IF( K37="""", """", ROUND( IF( L37="""", K37, IF( ISERROR(FIND(""-"",L37)), K37 - VALUE(REGEXEXTRACT(L37,""(\d+)"")), K37 * (1 - VALUE(REGEXEXTRACT(L37,""(\d+)""))/100) ) ), 2 ) ) ")," ") | O37: FALSE | R37: FALSE | S37: FALSE | T37: FALSE
M38: =IFERROR(__xludf.DUMMYFUNCTION("IF( K38="""", """", ROUND( IF( L38="""", K38, IF( ISERROR(FIND(""-"",L38)), K38 - VALUE(REGEXEXTRACT(L38,""(\d+)"")), K38 * (1 - VALUE(REGEXEXTRACT(L38,""(\d+)""))/100) ) ), 2 ) ) ")," ") | O38: FALSE | R38: FALSE | S38: FALSE | T38: FALSE
M39: =IFERROR(__xludf.DUMMYFUNCTION("IF( K39="""", """", ROUND( IF( L39="""", K39, IF( ISERROR(FIND(""-"",L39)), K39 - VALUE(REGEXEXTRACT(L39,""(\d+)"")), K39 * (1 - VALUE(REGEXEXTRACT(L39,""(\d+)""))/100) ) ), 2 ) ) ")," ") | O39: FALSE | R39: FALSE | S39: FALSE | T39: FALSE
M40: =IFERROR(__xludf.DUMMYFUNCTION("IF( K40="""", """", ROUND( IF( L40="""", K40, IF( ISERROR(FIND(""-"",L40)), K40 - VALUE(REGEXEXTRACT(L40,""(\d+)"")), K40 * (1 - VALUE(REGEXEXTRACT(L40,""(\d+)""))/100) ) ), 2 ) ) ")," ") | O40: FALSE | R40: FALSE | S40: FALSE | T40: FALSE
M41: =IFERROR(__xludf.DUMMYFUNCTION("IF( K41="""", """", ROUND( IF( L41="""", K41, IF( ISERROR(FIND(""-"",L41)), K41 - VALUE(REGEXEXTRACT(L41,""(\d+)"")), K41 * (1 - VALUE(REGEXEXTRACT(L41,""(\d+)""))/100) ) ), 2 ) ) ")," ") | O41: FALSE | R41: FALSE | S41: FALSE | T41: FALSE
M42: =IFERROR(__xludf.DUMMYFUNCTION("IF( K42="""", """", ROUND( IF( L42="""", K42, IF( ISERROR(FIND(""-"",L42)), K42 - VALUE(REGEXEXTRACT(L42,""(\d+)"")), K42 * (1 - VALUE(REGEXEXTRACT(L42,""(\d+)""))/100) ) ), 2 ) ) ")," ") | O42: FALSE | R42: FALSE | S42: FALSE | T42: FALSE
M43: =IFERROR(__xludf.DUMMYFUNCTION("IF( K43="""", """", ROUND( IF( L43="""", K43, IF( ISERROR(FIND(""-"",L43)), K43 - VALUE(REGEXEXTRACT(L43,""(\d+)"")), K43 * (1 - VALUE(REGEXEXTRACT(L43,""(\d+)""))/100) ) ), 2 ) ) ")," ") | O43: FALSE | R43: FALSE | S43: FALSE | T43: FALSE
C44: NO | N44: PRESENZA UOMINI | O44: =SUMPRODUCT(--$O$45:$O$84) -> 0
M45: =IFERROR(__xludf.DUMMYFUNCTION("IF( K45="""", """", ROUND( IF( L45="""", K45, IF( ISERROR(FIND(""-"",L45)), K45 - VALUE(REGEXEXTRACT(L45,""(\d+)"")), K45 * (1 - VALUE(REGEXEXTRACT(L45,""(\d+)""))/100) ) ), 2 ) ) ")," ") | O45: FALSE | R45: FALSE | S45: FALSE | T45: FALSE
M46: =IFERROR(__xludf.DUMMYFUNCTION("IF( K46="""", """", ROUND( IF( L46="""", K46, IF( ISERROR(FIND(""-"",L46)), K46 - VALUE(REGEXEXTRACT(L46,""(\d+)"")), K46 * (1 - VALUE(REGEXEXTRACT(L46,""(\d+)""))/100) ) ), 2 ) ) ")," ") | O46: FALSE | R46: FALSE | S46: FALSE | T46: FALSE
M47: =IFERROR(__xludf.DUMMYFUNCTION("IF( K47="""", """", ROUND( IF( L47="""", K47, IF( ISERROR(FIND(""-"",L47)), K47 - VALUE(REGEXEXTRACT(L47,""(\d+)"")), K47 * (1 - VALUE(REGEXEXTRACT(L47,""(\d+)""))/100) ) ), 2 ) ) ")," ") | O47: FALSE | R47: FALSE | S47: FALSE | T47: FALSE
M48: =IFERROR(__xludf.DUMMYFUNCTION("IF( K48="""", """", ROUND( IF( L48="""", K48, IF( ISERROR(FIND(""-"",L48)), K48 - VALUE(REGEXEXTRACT(L48,""(\d+)"")), K48 * (1 - VALUE(REGEXEXTRACT(L48,""(\d+)""))/100) ) ), 2 ) ) ")," ") | O48: FALSE | R48: FALSE | S48: FALSE | T48: FALSE
M49: =IFERROR(__xludf.DUMMYFUNCTION("IF( K49="""", """", ROUND( IF( L49="""", K49, IF( ISERROR(FIND(""-"",L49)), K49 - VALUE(REGEXEXTRACT(L49,""(\d+)"")), K49 * (1 - VALUE(REGEXEXTRACT(L49,""(\d+)""))/100) ) ), 2 ) ) ")," ") | O49: FALSE | R49: FALSE | S49: FALSE | T49: FALSE
M50: =IFERROR(__xludf.DUMMYFUNCTION("IF( K50="""", """", ROUND( IF( L50="""", K50, IF( ISERROR(FIND(""-"",L50)), K50 - VALUE(REGEXEXTRACT(L50,""(\d+)"")), K50 * (1 - VALUE(REGEXEXTRACT(L50,""(\d+)""))/100) ) ), 2 ) ) ")," ") | O50: FALSE | R50: FALSE | S50: FALSE | T50: FALSE
M51: =IFERROR(__xludf.DUMMYFUNCTION("IF( K51="""", """", ROUND( IF( L51="""", K51, IF( ISERROR(FIND(""-"",L51)), K51 - VALUE(REGEXEXTRACT(L51,""(\d+)"")), K51 * (1 - VALUE(REGEXEXTRACT(L51,""(\d+)""))/100) ) ), 2 ) ) ")," ") | O51: FALSE | R51: FALSE | S51: FALSE | T51: FALSE
M52: =IFERROR(__xludf.DUMMYFUNCTION("IF( K52="""", """", ROUND( IF( L52="""", K52, IF( ISERROR(FIND(""-"",L52)), K52 - VALUE(REGEXEXTRACT(L52,""(\d+)"")), K52 * (1 - VALUE(REGEXEXTRACT(L52,""(\d+)""))/100) ) ), 2 ) ) ")," ") | O52: FALSE | R52: FALSE | S52: FALSE | T52: FALSE
M53: =IFERROR(__xludf.DUMMYFUNCTION("IF( K53="""", """", ROUND( IF( L53="""", K53, IF( ISERROR(FIND(""-"",L53)), K53 - VALUE(REGEXEXTRACT(L53,""(\d+)"")), K53 * (1 - VALUE(REGEXEXTRACT(L53,""(\d+)""))/100) ) ), 2 ) ) ")," ") | O53: FALSE | R53: FALSE | S53: FALSE | T53: FALSE
M54: =IFERROR(__xludf.DUMMYFUNCTION("IF( K54="""", """", ROUND( IF( L54="""", K54, IF( ISERROR(FIND(""-"",L54)), K54 - VALUE(REGEXEXTRACT(L54,""(\d+)"")), K54 * (1 - VALUE(REGEXEXTRACT(L54,""(\d+)""))/100) ) ), 2 ) ) ")," ") | O54: FALSE | R54: FALSE | S54: FALSE | T54: FALSE
M55: =IFERROR(__xludf.DUMMYFUNCTION("IF( K55="""", """", ROUND( IF( L55="""", K55, IF( ISERROR(FIND(""-"",L55)), K55 - VALUE(REGEXEXTRACT(L55,""(\d+)"")), K55 * (1 - VALUE(REGEXEXTRACT(L55,""(\d+)""))/100) ) ), 2 ) ) ")," ") | O55: FALSE | R55: FALSE | S55: FALSE | T55: FALSE
M56: =IFERROR(__xludf.DUMMYFUNCTION("IF( K56="""", """", ROUND( IF( L56="""", K56, IF( ISERROR(FIND(""-"",L56)), K56 - VALUE(REGEXEXTRACT(L56,""(\d+)"")), K56 * (1 - VALUE(REGEXEXTRACT(L56,""(\d+)""))/100) ) ), 2 ) ) ")," ") | O56: FALSE | R56: FALSE | S56: FALSE | T56: FALSE
M57: =IFERROR(__xludf.DUMMYFUNCTION("IF( K57="""", """", ROUND( IF( L57="""", K57, IF( ISERROR(FIND(""-"",L57)), K57 - VALUE(REGEXEXTRACT(L57,""(\d+)"")), K57 * (1 - VALUE(REGEXEXTRACT(L57,""(\d+)""))/100) ) ), 2 ) ) ")," ") | O57: FALSE | R57: FALSE | S57: FALSE | T57: FALSE
M58: =IFERROR(__xludf.DUMMYFUNCTION("IF( K58="""", """", ROUND( IF( L58="""", K58, IF( ISERROR(FIND(""-"",L58)), K58 - VALUE(REGEXEXTRACT(L58,""(\d+)"")), K58 * (1 - VALUE(REGEXEXTRACT(L58,""(\d+)""))/100) ) ), 2 ) ) ")," ") | O58: FALSE | R58: FALSE | S58: FALSE | T58: FALSE
M59: =IFERROR(__xludf.DUMMYFUNCTION("IF( K59="""", """", ROUND( IF( L59="""", K59, IF( ISERROR(FIND(""-"",L59)), K59 - VALUE(REGEXEXTRACT(L59,""(\d+)"")), K59 * (1 - VALUE(REGEXEXTRACT(L59,""(\d+)""))/100) ) ), 2 ) ) ")," ") | O59: FALSE | R59: FALSE | S59: FALSE | T59: FALSE
M60: =IFERROR(__xludf.DUMMYFUNCTION("IF( K60="""", """", ROUND( IF( L60="""", K60, IF( ISERROR(FIND(""-"",L60)), K60 - VALUE(REGEXEXTRACT(L60,""(\d+)"")), K60 * (1 - VALUE(REGEXEXTRACT(L60,""(\d+)""))/100) ) ), 2 ) ) ")," ") | O60: FALSE | R60: FALSE | S60: FALSE | T60: FALSE
M61: =IFERROR(__xludf.DUMMYFUNCTION("IF( K61="""", """", ROUND( IF( L61="""", K61, IF( ISERROR(FIND(""-"",L61)), K61 - VALUE(REGEXEXTRACT(L61,""(\d+)"")), K61 * (1 - VALUE(REGEXEXTRACT(L61,""(\d+)""))/100) ) ), 2 ) ) ")," ") | O61: FALSE | R61: FALSE | S61: FALSE | T61: FALSE
M62: =IFERROR(__xludf.DUMMYFUNCTION("IF( K62="""", """", ROUND( IF( L62="""", K62, IF( ISERROR(FIND(""-"",L62)), K62 - VALUE(REGEXEXTRACT(L62,""(\d+)"")), K62 * (1 - VALUE(REGEXEXTRACT(L62,""(\d+)""))/100) ) ), 2 ) ) ")," ") | O62: FALSE | R62: FALSE | S62: FALSE | T62: FALSE
M63: =IFERROR(__xludf.DUMMYFUNCTION("IF( K63="""", """", ROUND( IF( L63="""", K63, IF( ISERROR(FIND(""-"",L63)), K63 - VALUE(REGEXEXTRACT(L63,""(\d+)"")), K63 * (1 - VALUE(REGEXEXTRACT(L63,""(\d+)""))/100) ) ), 2 ) ) ")," ") | O63: FALSE | R63: FALSE | S63: FALSE | T63: FALSE
M64: =IFERROR(__xludf.DUMMYFUNCTION("IF( K64="""", """", ROUND( IF( L64="""", K64, IF( ISERROR(FIND(""-"",L64)), K64 - VALUE(REGEXEXTRACT(L64,""(\d+)"")), K64 * (1 - VALUE(REGEXEXTRACT(L64,""(\d+)""))/100) ) ), 2 ) ) ")," ") | O64: FALSE | R64: FALSE | S64: FALSE | T64: FALSE
M65: =IFERROR(__xludf.DUMMYFUNCTION("IF( K65="""", """", ROUND( IF( L65="""", K65, IF( ISERROR(FIND(""-"",L65)), K65 - VALUE(REGEXEXTRACT(L65,""(\d+)"")), K65 * (1 - VALUE(REGEXEXTRACT(L65,""(\d+)""))/100) ) ), 2 ) ) ")," ") | O65: FALSE | R65: FALSE | S65: FALSE | T65: FALSE
M66: =IFERROR(__xludf.DUMMYFUNCTION("IF( K66="""", """", ROUND( IF( L66="""", K66, IF( ISERROR(FIND(""-"",L66)), K66 - VALUE(REGEXEXTRACT(L66,""(\d+)"")), K66 * (1 - VALUE(REGEXEXTRACT(L66,""(\d+)""))/100) ) ), 2 ) ) ")," ") | O66: FALSE | R66: FALSE | S66: FALSE | T66: FALSE
M67: =IFERROR(__xludf.DUMMYFUNCTION("IF( K67="""", """", ROUND( IF( L67="""", K67, IF( ISERROR(FIND(""-"",L67)), K67 - VALUE(REGEXEXTRACT(L67,""(\d+)"")), K67 * (1 - VALUE(REGEXEXTRACT(L67,""(\d+)""))/100) ) ), 2 ) ) ")," ") | O67: FALSE | R67: FALSE | S67: FALSE | T67: FALSE
M68: =IFERROR(__xludf.DUMMYFUNCTION("IF( K68="""", """", ROUND( IF( L68="""", K68, IF( ISERROR(FIND(""-"",L68)), K68 - VALUE(REGEXEXTRACT(L68,""(\d+)"")), K68 * (1 - VALUE(REGEXEXTRACT(L68,""(\d+)""))/100) ) ), 2 ) ) ")," ") | O68: FALSE | R68: FALSE | S68: FALSE | T68: FALSE
M69: =IFERROR(__xludf.DUMMYFUNCTION("IF( K69="""", """", ROUND( IF( L69="""", K69, IF( ISERROR(FIND(""-"",L69)), K69 - VALUE(REGEXEXTRACT(L69,""(\d+)"")), K69 * (1 - VALUE(REGEXEXTRACT(L69,""(\d+)""))/100) ) ), 2 ) ) ")," ") | O69: FALSE | R69: FALSE | S69: FALSE | T69: FALSE
M70: =IFERROR(__xludf.DUMMYFUNCTION("IF( K70="""", """", ROUND( IF( L70="""", K70, IF( ISERROR(FIND(""-"",L70)), K70 - VALUE(REGEXEXTRACT(L70,""(\d+)"")), K70 * (1 - VALUE(REGEXEXTRACT(L70,""(\d+)""))/100) ) ), 2 ) ) ")," ") | O70: FALSE | R70: FALSE | S70: FALSE | T70: FALSE
M71: =IFERROR(__xludf.DUMMYFUNCTION("IF( K71="""", """", ROUND( IF( L71="""", K71, IF( ISERROR(FIND(""-"",L71)), K71 - VALUE(REGEXEXTRACT(L71,""(\d+)"")), K71 * (1 - VALUE(REGEXEXTRACT(L71,""(\d+)""))/100) ) ), 2 ) ) ")," ") | O71: FALSE | R71: FALSE | S71: FALSE | T71: FALSE
M72: =IFERROR(__xludf.DUMMYFUNCTION("IF( K72="""", """", ROUND( IF( L72="""", K72, IF( ISERROR(FIND(""-"",L72)), K72 - VALUE(REGEXEXTRACT(L72,""(\d+)"")), K72 * (1 - VALUE(REGEXEXTRACT(L72,""(\d+)""))/100) ) ), 2 ) ) ")," ") | O72: FALSE | R72: FALSE | S72: FALSE | T72: FALSE
M73: =IFERROR(__xludf.DUMMYFUNCTION("IF( K73="""", """", ROUND( IF( L73="""", K73, IF( ISERROR(FIND(""-"",L73)), K73 - VALUE(REGEXEXTRACT(L73,""(\d+)"")), K73 * (1 - VALUE(REGEXEXTRACT(L73,""(\d+)""))/100) ) ), 2 ) ) ")," ") | O73: FALSE | R73: FALSE | S73: FALSE | T73: FALSE
M74: =IFERROR(__xludf.DUMMYFUNCTION("IF( K74="""", """", ROUND( IF( L74="""", K74, IF( ISERROR(FIND(""-"",L74)), K74 - VALUE(REGEXEXTRACT(L74,""(\d+)"")), K74 * (1 - VALUE(REGEXEXTRACT(L74,""(\d+)""))/100) ) ), 2 ) ) ")," ") | O74: FALSE | R74: FALSE | S74: FALSE | T74: FALSE
M75: =IFERROR(__xludf.DUMMYFUNCTION("IF( K75="""", """", ROUND( IF( L75="""", K75, IF( ISERROR(FIND(""-"",L75)), K75 - VALUE(REGEXEXTRACT(L75,""(\d+)"")), K75 * (1 - VALUE(REGEXEXTRACT(L75,""(\d+)""))/100) ) ), 2 ) ) ")," ") | O75: FALSE | R75: FALSE | S75: FALSE | T75: FALSE
M76: =IFERROR(__xludf.DUMMYFUNCTION("IF( K76="""", """", ROUND( IF( L76="""", K76, IF( ISERROR(FIND(""-"",L76)), K76 - VALUE(REGEXEXTRACT(L76,""(\d+)"")), K76 * (1 - VALUE(REGEXEXTRACT(L76,""(\d+)""))/100) ) ), 2 ) ) ")," ") | O76: FALSE | R76: FALSE | S76: FALSE | T76: FALSE
M77: =IFERROR(__xludf.DUMMYFUNCTION("IF( K77="""", """", ROUND( IF( L77="""", K77, IF( ISERROR(FIND(""-"",L77)), K77 - VALUE(REGEXEXTRACT(L77,""(\d+)"")), K77 * (1 - VALUE(REGEXEXTRACT(L77,""(\d+)""))/100) ) ), 2 ) ) ")," ") | O77: FALSE | R77: FALSE | S77: FALSE | T77: FALSE
M78: =IFERROR(__xludf.DUMMYFUNCTION("IF( K78="""", """", ROUND( IF( L78="""", K78, IF( ISERROR(FIND(""-"",L78)), K78 - VALUE(REGEXEXTRACT(L78,""(\d+)"")), K78 * (1 - VALUE(REGEXEXTRACT(L78,""(\d+)""))/100) ) ), 2 ) ) ")," ") | O78: FALSE | R78: FALSE | S78: FALSE | T78: FALSE
M79: =IFERROR(__xludf.DUMMYFUNCTION("IF( K79="""", """", ROUND( IF( L79="""", K79, IF( ISERROR(FIND(""-"",L79)), K79 - VALUE(REGEXEXTRACT(L79,""(\d+)"")), K79 * (1 - VALUE(REGEXEXTRACT(L79,""(\d+)""))/100) ) ), 2 ) ) ")," ") | O79: FALSE | R79: FALSE | S79: FALSE | T79: FALSE
M80: =IFERROR(__xludf.DUMMYFUNCTION("IF( K80="""", """", ROUND( IF( L80="""", K80, IF( ISERROR(FIND(""-"",L80)), K80 - VALUE(REGEXEXTRACT(L80,""(\d+)"")), K80 * (1 - VALUE(REGEXEXTRACT(L80,""(\d+)""))/100) ) ), 2 ) ) ")," ") | O80: FALSE | R80: FALSE | S80: FALSE | T80: FALSE
M81: =IFERROR(__xludf.DUMMYFUNCTION("IF( K81="""", """", ROUND( IF( L81="""", K81, IF( ISERROR(FIND(""-"",L81)), K81 - VALUE(REGEXEXTRACT(L81,""(\d+)"")), K81 * (1 - VALUE(REGEXEXTRACT(L81,""(\d+)""))/100) ) ), 2 ) ) ")," ") | O81: FALSE | R81: FALSE | S81: FALSE | T81: FALSE
M82: =IFERROR(__xludf.DUMMYFUNCTION("IF( K82="""", """", ROUND( IF( L82="""", K82, IF( ISERROR(FIND(""-"",L82)), K82 - VALUE(REGEXEXTRACT(L82,""(\d+)"")), K82 * (1 - VALUE(REGEXEXTRACT(L82,""(\d+)""))/100) ) ), 2 ) ) ")," ") | O82: FALSE | R82: FALSE | S82: FALSE | T82: FALSE
M83: =IFERROR(__xludf.DUMMYFUNCTION("IF( K83="""", """", ROUND( IF( L83="""", K83, IF( ISERROR(FIND(""-"",L83)), K83 - VALUE(REGEXEXTRACT(L83,""(\d+)"")), K83 * (1 - VALUE(REGEXEXTRACT(L83,""(\d+)""))/100) ) ), 2 ) ) ")," ") | O83: FALSE | R83: FALSE | S83: FALSE | T83: FALSE
M84: =IFERROR(__xludf.DUMMYFUNCTION("IF( K84="""", """", ROUND( IF( L84="""", K84, IF( ISERROR(FIND(""-"",L84)), K84 - VALUE(REGEXEXTRACT(L84,""(\d+)"")), K84 * (1 - VALUE(REGEXEXTRACT(L84,""(\d+)""))/100) ) ), 2 ) ) ")," ") | O84: FALSE | R84: FALSE | S84: FALSE | T84: FALSE
A85: TOTALE | B85: =COUNTIF(B4:B84,"ONLINE")+COUNTIF(B4:B84,"SEDE*") -> 33 | C85: TOTALE | D85: =COUNTIF(D4:D84, "*") -> 17 | E85: =COUNTIF(E4:E84, "*") -> 33 | F85: =COUNTIF(F4:F84, "*") -> 33 | G85: =COUNTA(G4:G84) -> 33 | H85: =COUNTIF(H4:H84, "*") -> 33 | I85: =COUNTIF(I4:I84, "*") -> 33 | J85: TOTALE | K85: =SUM(K4:K84) -> 1156 | L85: =COUNTIF(L4:L84, "*") -> 14 | M85: =SUM(M4:M84) -> 1125 | N85: =COUNTIF(N4:N43, "*")+COUNTIF(N45:N84, "*") -> 33 | O85: =SUMPRODUCT(--O4:O84) -> 32 | P85: =COUNTIF(P4:P84, "*") -> 2 | Q85: =COUNTIF(Q4:Q84, "*") -> 33 | R85: =SUMPRODUCT(--R4:R84) -> 23 | S85: =SUMPRODUCT(--S4:S84) -> 10 | T85: =SUMPRODUCT(--T4:T84) -> 33
A86: SEDE | B86: =COUNTIF(B4:B84, "SEDE*") -> 6 | D86: TOTALI WS 1 | E86: LISTA PREZZI | F86: =IFERROR(__xludf.DUMMYFUNCTION("IFERROR(TRANSPOSE(SORT(UNIQUE(FILTER($M$4:$M$84,$M$4:$M$84<>"""")))),"""")"),30.0) -> 30 | G86: =IFERROR(__xludf.DUMMYFUNCTION("""COMPUTED_VALUE"""),32.0) -> 32 | H86: =IFERROR(__xludf.DUMMYFUNCTION("""COMPUTED_VALUE"""),35.0) -> 35 | I86: =IFERROR(__xludf.DUMMYFUNCTION("""COMPUTED_VALUE"""),37.0) -> 37 | P86: TOTALE | Q86: =IF(SUM(F88:O88)=0,"",SUM(F88:O88)) -> 202 | R86: Verifica | S86: =IF(SUM(M85) = SUM(Q86:Q90), "OK", "ERRORE") -> OK
A87: ONLINE | B87: =COUNTIF(B4:B84, "ONLINE") -> 27 | E87: PERSONE SEDE | F87: =IF( F$86="", "", COUNTIFS($B$4:$B$84,"*SEDE*",$M$4:$M$84,F$86) ) -> 2 | G87: =IF( G$86="", "", COUNTIFS($B$4:$B$84,"*SEDE*",$M$4:$M$84,G$86) ) -> 0 | H87: =IF( H$86="", "", COUNTIFS($B$4:$B$84,"*SEDE*",$M$4:$M$84,H$86) ) -> 3 | I87: =IF( I$86="", "", COUNTIFS($B$4:$B$84,"*SEDE*",$M$4:$M$84,I$86) ) -> 1 | J87: =IF( J$86="", "", COUNTIFS($B$4:$B$84,"*SEDE*",$M$4:$M$84,J$86) ) | K87: =IF( K$86="", "", COUNTIFS($B$4:$B$84,"*SEDE*",$M$4:$M$84,K$86) ) | L87: =IF( L$86="", "", COUNTIFS($B$4:$B$84,"*SEDE*",$M$4:$M$84,L$86) ) | M87: =IF( M$86="", "", COUNTIFS($B$4:$B$84,"*SEDE*",$M$4:$M$84,M$86) ) | ... O87: =IF( O$86="", "", COUNTIFS($B$4:$B$84,"*SEDE*",$M$4:$M$84,O$86) )
A88: DONNE | B88: =COUNTIF($E4:$E43, "*") -> 33 | E88: subTOTALE SEDE | F88: =IF( F$86="", "", SUMIFS($M$4:$M$84,$B$4:$B$84,"*SEDE*",$M$4:$M$84,F$86) ) -> 60 | G88: =IF( G$86="", "", SUMIFS($M$4:$M$84,$B$4:$B$84,"*SEDE*",$M$4:$M$84,G$86) ) -> 0 | H88: =IF( H$86="", "", SUMIFS($M$4:$M$84,$B$4:$B$84,"*SEDE*",$M$4:$M$84,H$86) ) -> 105 | I88: =IF( I$86="", "", SUMIFS($M$4:$M$84,$B$4:$B$84,"*SEDE*",$M$4:$M$84,I$86) ) -> 37 | J88: =IF( J$86="", "", SUMIFS($M$4:$M$84,$B$4:$B$84,"*SEDE*",$M$4:$M$84,J$86) ) | K88: =IF( K$86="", "", SUMIFS($M$4:$M$84,$B$4:$B$84,"*SEDE*",$M$4:$M$84,K$86) ) | L88: =IF( L$86="", "", SUMIFS($M$4:$M$84,$B$4:$B$84,"*SEDE*",$M$4:$M$84,L$86) ) | M88: =IF( M$86="", "", SUMIFS($M$4:$M$84,$B$4:$B$84,"*SEDE*",$M$4:$M$84,M$86) ) | ... O88: =IF( O$86="", "", SUMIFS($M$4:$M$84,$B$4:$B$84,"*SEDE*",$M$4:$M$84,O$86) )
A89: UOMINI | B89: =COUNTIF(E45:E84, "*") -> 0 | E89: PERSONE ONLINE | F89: =IF( F$86="", "", COUNTIFS($B$4:$B$84,"*ONLINE*",$M$4:$M$84,F$86) ) -> 4 | G89: =IF( G$86="", "", COUNTIFS($B$4:$B$84,"*ONLINE*",$M$4:$M$84,G$86) ) -> 8 | H89: =IF( H$86="", "", COUNTIFS($B$4:$B$84,"*ONLINE*",$M$4:$M$84,H$86) ) -> 4 | I89: =IF( I$86="", "", COUNTIFS($B$4:$B$84,"*ONLINE*",$M$4:$M$84,I$86) ) -> 11 | J89: =IF( J$86="", "", COUNTIFS($B$4:$B$84,"*ONLINE*",$M$4:$M$84,J$86) ) | K89: =IF( K$86="", "", COUNTIFS($B$4:$B$84,"*ONLINE*",$M$4:$M$84,K$86) ) | L89: =IF( L$86="", "", COUNTIFS($B$4:$B$84,"*ONLINE*",$M$4:$M$84,L$86) ) | M89: =IF( M$86="", "", COUNTIFS($B$4:$B$84,"*ONLINE*",$M$4:$M$84,M$86) ) | ... O89: =IF( O$86="", "", COUNTIFS($B$4:$B$84,"*ONLINE*",$M$4:$M$84,O$86) ) | P89: TOTALE | Q89: =IF(SUM(F90:O90)=0,"",SUM(F90:O90)) -> 923
E90: subTOTALE ONLINE | F90: =IF( F$86="", "", SUMIFS($M$4:$M$84,$B$4:$B$84,"*ONLINE*",$M$4:$M$84,F$86) ) -> 120 | G90: =IF( G$86="", "", SUMIFS($M$4:$M$84,$B$4:$B$84,"*ONLINE*",$M$4:$M$84,G$86) ) -> 256 | H90: =IF( H$86="", "", SUMIFS($M$4:$M$84,$B$4:$B$84,"*ONLINE*",$M$4:$M$84,H$86) ) -> 140 | I90: =IF( I$86="", "", SUMIFS($M$4:$M$84,$B$4:$B$84,"*ONLINE*",$M$4:$M$84,I$86) ) -> 407 | J90: =IF( J$86="", "", SUMIFS($M$4:$M$84,$B$4:$B$84,"*ONLINE*",$M$4:$M$84,J$86) ) | K90: =IF( K$86="", "", SUMIFS($M$4:$M$84,$B$4:$B$84,"*ONLINE*",$M$4:$M$84,K$86) ) | L90: =IF( L$86="", "", SUMIFS($M$4:$M$84,$B$4:$B$84,"*ONLINE*",$M$4:$M$84,L$86) ) | M90: =IF( M$86="", "", SUMIFS($M$4:$M$84,$B$4:$B$84,"*ONLINE*",$M$4:$M$84,M$86) ) | ... O90: =IF( O$86="", "", SUMIFS($M$4:$M$84,$B$4:$B$84,"*ONLINE*",$M$4:$M$84,O$86) )
C91: NO | N91: PRESENZA DONNE | O91: =SUMPRODUCT(--$O$92:$O$130) -> 0
M92: =IFERROR(__xludf.DUMMYFUNCTION("IF( K92="""", """", ROUND( IF( L92="""", K92, IF( ISERROR(FIND(""-"",L92)), K92 - VALUE(REGEXEXTRACT(L92,""(\d+)"")), K92 * (1 - VALUE(REGEXEXTRACT(L92,""(\d+)""))/100) ) ), 2 ) ) ")," ") | O92: FALSE | R92: FALSE | S92: FALSE | T92: FALSE
M93: =IFERROR(__xludf.DUMMYFUNCTION("IF( K93="""", """", ROUND( IF( L93="""", K93, IF( ISERROR(FIND(""-"",L93)), K93 - VALUE(REGEXEXTRACT(L93,""(\d+)"")), K93 * (1 - VALUE(REGEXEXTRACT(L93,""(\d+)""))/100) ) ), 2 ) ) ")," ") | O93: FALSE | R93: FALSE | S93: FALSE | T93: FALSE
M94: =IFERROR(__xludf.DUMMYFUNCTION("IF( K94="""", """", ROUND( IF( L94="""", K94, IF( ISERROR(FIND(""-"",L94)), K94 - VALUE(REGEXEXTRACT(L94,""(\d+)"")), K94 * (1 - VALUE(REGEXEXTRACT(L94,""(\d+)""))/100) ) ), 2 ) ) ")," ") | O94: FALSE | R94: FALSE | S94: FALSE | T94: FALSE
M95: =IFERROR(__xludf.DUMMYFUNCTION("IF( K95="""", """", ROUND( IF( L95="""", K95, IF( ISERROR(FIND(""-"",L95)), K95 - VALUE(REGEXEXTRACT(L95,""(\d+)"")), K95 * (1 - VALUE(REGEXEXTRACT(L95,""(\d+)""))/100) ) ), 2 ) ) ")," ") | O95: FALSE | R95: FALSE | S95: FALSE | T95: FALSE
M96: =IFERROR(__xludf.DUMMYFUNCTION("IF( K96="""", """", ROUND( IF( L96="""", K96, IF( ISERROR(FIND(""-"",L96)), K96 - VALUE(REGEXEXTRACT(L96,""(\d+)"")), K96 * (1 - VALUE(REGEXEXTRACT(L96,""(\d+)""))/100) ) ), 2 ) ) ")," ") | O96: FALSE | R96: FALSE | S96: FALSE | T96: FALSE
M97: =IFERROR(__xludf.DUMMYFUNCTION("IF( K97="""", """", ROUND( IF( L97="""", K97, IF( ISERROR(FIND(""-"",L97)), K97 - VALUE(REGEXEXTRACT(L97,""(\d+)"")), K97 * (1 - VALUE(REGEXEXTRACT(L97,""(\d+)""))/100) ) ), 2 ) ) ")," ") | O97: FALSE | R97: FALSE | S97: FALSE | T97: FALSE
M98: =IFERROR(__xludf.DUMMYFUNCTION("IF( K98="""", """", ROUND( IF( L98="""", K98, IF( ISERROR(FIND(""-"",L98)), K98 - VALUE(REGEXEXTRACT(L98,""(\d+)"")), K98 * (1 - VALUE(REGEXEXTRACT(L98,""(\d+)""))/100) ) ), 2 ) ) ")," ") | O98: FALSE | R98: FALSE | S98: FALSE | T98: FALSE
M99: =IFERROR(__xludf.DUMMYFUNCTION("IF( K99="""", """", ROUND( IF( L99="""", K99, IF( ISERROR(FIND(""-"",L99)), K99 - VALUE(REGEXEXTRACT(L99,""(\d+)"")), K99 * (1 - VALUE(REGEXEXTRACT(L99,""(\d+)""))/100) ) ), 2 ) ) ")," ") | O99: FALSE | R99: FALSE | S99: FALSE | T99: FALSE
M100: =IFERROR(__xludf.DUMMYFUNCTION("IF( K100="""", """", ROUND( IF( L100="""", K100, IF( ISERROR(FIND(""-"",L100)), K100 - VALUE(REGEXEXTRACT(L100,""(\d+)"")), K100 * (1 - VALUE(REGEXEXTRACT(L100,""(\d+)""))/100) ) ), 2 ) )"&" ")," ") | O100: FALSE | R100: FALSE | S100: FALSE | T100: FALSE
...

Sheet OC_ANAHITA
C1: OC_ANAHITA_01MAR2026
A2: CHI SCRIVE | B2: VENDITA | C2: DATA INSERIMENTO /RICHIESTA | D2: ID ANAGRAFICA | E2: COGNOME | F2: NOME | G2: TELEFONO | H2: CODICE FISCALE | I2: EMAIL | J2: DATA PAGAMENTO /RICEVUTA | K2: QUOTA | L2: CODICE SCONTO | M2: IMPORTO FINALE | N2: DIGIT/CASH - TESS/NON TESS | O2: PRESENZA | P2: NOTE | Q2: INSERITO SU ATHENA | R2: RICEVUTA FATTA | S2: FATTURA FATTA | T2: VERIFICA PAGAMENTO
C3: 14:30-16:00_HEELS (€22 entro il 15/02 compreso → €27 dal 16/02 all'01/03 compreso)
A4: Estefany | B4: ONLINE | C4: 46057 | D4: ID-002165 | E4: VENTURINI | F4: LISA | G4: 3299590445 | H4: VNTLSI98M43I608M | I4: lisa03venturini@gmail.com | J4: 46057 | K4: 22 | M4: =IFERROR(__xludf.DUMMYFUNCTION("IF( K4="""", """", ROUND( IF( L4="""", K4, IF( ISERROR(FIND(""-"",L4)), K4 - VALUE(REGEXEXTRACT(L4,""(\d+)"")), K4 * (1 - VALUE(REGEXEXTRACT(L4,""(\d+)""))/100) ) ), 2 ) ) "),22.0) -> 22 | N4: DIGIT - TESSERATO | O4: TRUE | Q4: INSERITO | R4: TRUE | S4: FALSE | T4: TRUE
A5: Estefany | B5: ONLINE | C5: 46057 | E5: ESPOSTI | F5: ALESSIA | G5: 3920234147 | H5: SPSLSS04S69B639I | I5: alessiaesposti04@gmail.com | J5: 46057 | K5: 22 | L5: ESTEFANY02WS | M5: =IFERROR(__xludf.DUMMYFUNCTION("IF( K5="""", """", ROUND( IF( L5="""", K5, IF( ISERROR(FIND(""-"",L5)), K5 - VALUE(REGEXEXTRACT(L5,""(\d+)"")), K5 * (1 - VALUE(REGEXEXTRACT(L5,""(\d+)""))/100) ) ), 2 ) ) "),20.0) -> 20 | N5: DIGIT - NON TESSERATO | O5: FALSE | Q5: INSERITO | R5: FALSE | S5: TRUE | T5: TRUE
A6: Estefany | B6: ONLINE | C6: 46059 | E6: FERRANDINO | F6: MATTEO | G6: 3468298086 | H6: FRRMTT99E26B729Y | I6: matteoferrandino@hotmail.it | J6: 46059 | K6: 22 | L6: ALEXANDRA02WS | M6: =IFERROR(__xludf.DUMMYFUNCTION("IF( K6="""", """", ROUND( IF( L6="""", K6, IF( ISERROR(FIND(""-"",L6)), K6 - VALUE(REGEXEXTRACT(L6,""(\d+)"")), K6 * (1 - VALUE(REGEXEXTRACT(L6,""(\d+)""))/100) ) ), 2 ) ) "),20.0) -> 20 | N6: DIGIT - NON TESSERATO | O6: TRUE | Q6: INSERITO | R6: FALSE | S6: TRUE | T6: TRUE
A7: Estefany | B7: ONLINE | C7: 46059 | E7: NAVA | F7: ALESSANDRA | G7: 3338369306 | H7: NVALSN98D66M052C | I7: alessandranava100@gmail.com | J7: 46059 | K7: 22 | L7: ALEXANDRA02WS | M7: =IFERROR(__xludf.DUMMYFUNCTION("IF( K7="""", """", ROUND( IF( L7="""", K7, IF( ISERROR(FIND(""-"",L7)), K7 - VALUE(REGEXEXTRACT(L7,""(\d+)"")), K7 * (1 - VALUE(REGEXEXTRACT(L7,""(\d+)""))/100) ) ), 2 ) ) "),20.0) -> 20 | N7: DIGIT - NON TESSERATO | O7: TRUE | Q7: INSERITO | R7: FALSE | S7: TRUE | T7: TRUE
A8: Estefany | B8: ONLINE | C8: 46059 | D8: ID-000222 | E8: FONTE | F8: SOFIA | G8: 3423550544 | H8: FNTSFO05D53H224D | I8: sofiafonte2005@gmail.com | J8: 46059 | K8: 22 | M8: =IFERROR(__xludf.DUMMYFUNCTION("IF( K8="""", """", ROUND( IF( L8="""", K8, IF( ISERROR(FIND(""-"",L8)), K8 - VALUE(REGEXEXTRACT(L8,""(\d+)"")), K8 * (1 - VALUE(REGEXEXTRACT(L8,""(\d+)""))/100) ) ), 2 ) ) "),22.0) -> 22 | N8: DIGIT - TESSERATO | O8: TRUE | Q8: INSERITO | R8: TRUE | S8: FALSE | T8: TRUE
A9: Estefany | B9: ONLINE | C9: 46059 | D9: ID-002131 | E9: FERHATTI | F9: MERSSI | G9: 3345811794 | H9: FRHMSS99R61L840M | I9: ferhatimerssi@hotmail.com | J9: 46059 | K9: 22 | L9: ALEXANDRA02WS | M9: =IFERROR(__xludf.DUMMYFUNCTION("IF( K9="""", """", ROUND( IF( L9="""", K9, IF( ISERROR(FIND(""-"",L9)), K9 - VALUE(REGEXEXTRACT(L9,""(\d+)"")), K9 * (1 - VALUE(REGEXEXTRACT(L9,""(\d+)""))/100) ) ), 2 ) ) "),20.0) -> 20 | N9: DIGIT - TESSERATO | O9: TRUE | Q9: INSERITO | R9: TRUE | S9: FALSE | T9: TRUE
A10: Estefany | B10: ONLINE | C10: 46059 | D10: ID-000744 | E10: DIPINTO | F10: SARA | G10: 3485835439 | H10: DPNSRA06L53F205K | I10: dipi.sara13@gmail.com | J10: 46059 | K10: 22 | L10: ESTEFANY02WS | M10: =IFERROR(__xludf.DUMMYFUNCTION("IF( K10="""", """", ROUND( IF( L10="""", K10, IF( ISERROR(FIND(""-"",L10)), K10 - VALUE(REGEXEXTRACT(L10,""(\d+)"")), K10 * (1 - VALUE(REGEXEXTRACT(L10,""(\d+)""))/100) ) ), 2 ) ) "),20.0) -> 20 | N10: DIGIT - TESSERATO | O10: TRUE | Q10: INSERITO | R10: TRUE | S10: FALSE | T10: TRUE
A11: Estefany | B11: ONLINE | C11: 46059 | E11: TARANTINI | F11: GIULIA | G11: 3313332724 | H11: TRNGLI00A57D542O | I11: giulia.tarantini01@gmail.com | J11: 46059 | K11: 22 | M11: =IFERROR(__xludf.DUMMYFUNCTION("IF( K11="""", """", ROUND( IF( L11="""", K11, IF( ISERROR(FIND(""-"",L11)), K11 - VALUE(REGEXEXTRACT(L11,""(\d+)"")), K11 * (1 - VALUE(REGEXEXTRACT(L11,""(\d+)""))/100) ) ), 2 ) ) "),22.0) -> 22 | N11: DIGIT - NON TESSERATO | O11: TRUE | Q11: INSERITO | R11: FALSE | S11: TRUE | T11: TRUE
A12: Estefany | B12: ONLINE | C12: 46060 | E12: GANDOLFO | F12: MARTINA | G12: 3463595862 | H12: GNDMTN00E60D969M | I12: marty.gandalf@gmail.com | J12: 46060 | K12: 22 | M12: =IFERROR(__xludf.DUMMYFUNCTION("IF( K12="""", """", ROUND( IF( L12="""", K12, IF( ISERROR(FIND(""-"",L12)), K12 - VALUE(REGEXEXTRACT(L12,""(\d+)"")), K12 * (1 - VALUE(REGEXEXTRACT(L12,""(\d+)""))/100) ) ), 2 ) ) "),22.0) -> 22 | N12: DIGIT - NON TESSERATO | O12: TRUE | Q12: INSERITO | R12: FALSE | S12: TRUE | T12: TRUE
A13: Estefany | B13: ONLINE | C13: 46060 | E13: RAIMONDI | F13: FRANCESCA | G13: 3423729995 | H13: RMNFNC92H54L400M | I13: francy140692@gmail.com | J13: 46060 | K13: 22 | L13: ESTEFANY02WS | M13: =IFERROR(__xludf.DUMMYFUNCTION("IF( K13="""", """", ROUND( IF( L13="""", K13, IF( ISERROR(FIND(""-"",L13)), K13 - VALUE(REGEXEXTRACT(L13,""(\d+)"")), K13 * (1 - VALUE(REGEXEXTRACT(L13,""(\d+)""))/100) ) ), 2 ) ) "),20.0) -> 20 | N13: DIGIT - NON TESSERATO | O13: TRUE | Q13: INSERITO | R13: FALSE | S13: TRUE | T13: TRUE
A14: Estefany | B14: ONLINE | C14: 46061 | D14: ID-000108 | E14: DESERTI | F14: CHIARA | G14: 3519350411 | H14: DSRCHR07C64I577M | I14: desertichiara@gmail.com | J14: 46061 | K14: 22 | M14: =IFERROR(__xludf.DUMMYFUNCTION("IF( K14="""", """", ROUND( IF( L14="""", K14, IF( ISERROR(FIND(""-"",L14)), K14 - VALUE(REGEXEXTRACT(L14,""(\d+)"")), K14 * (1 - VALUE(REGEXEXTRACT(L14,""(\d+)""))/100) ) ), 2 ) ) "),22.0) -> 22 | N14: DIGIT - TESSERATO | O14: TRUE | Q14: INSERITO | R14: TRUE | S14: FALSE | T14: TRUE
A15: Estefany | B15: ONLINE | C15: 46061 | D15: ID-001366 | E15: MARASCHI | F15: PADMINI | G15: 3807877826 | H15: MRSPMN99H61Z222B | I15: paddy.mx9@gmail.com | J15: 46061 | K15: 22 | L15: NURA02WS | M15: =IFERROR(__xludf.DUMMYFUNCTION("IF( K15="""", """", ROUND( IF( L15="""", K15, IF( ISERROR(FIND(""-"",L15)), K15 - VALUE(REGEXEXTRACT(L15,""(\d+)"")), K15 * (1 - VALUE(REGEXEXTRACT(L15,""(\d+)""))/100) ) ), 2 ) ) "),20.0) -> 20 | N15: DIGIT - TESSERATO | O15: TRUE | Q15: INSERITO | R15: TRUE | S15: FALSE | T15: TRUE
A16: Estefany | B16: ONLINE | C16: 46061 | E16: MARTINUCCI | F16: FRANCESCA | G16: 3924515558 | H16: MRTFNC01C58L049O | I16: francesca.martinucci18@gmail.com | J16: 46061 | K16: 22 | M16: =IFERROR(__xludf.DUMMYFUNCTION("IF( K16="""", """", ROUND( IF( L16="""", K16, IF( ISERROR(FIND(""-"",L16)), K16 - VALUE(REGEXEXTRACT(L16,""(\d+)"")), K16 * (1 - VALUE(REGEXEXTRACT(L16,""(\d+)""))/100) ) ), 2 ) ) "),22.0) -> 22 | N16: DIGIT - NON TESSERATO | O16: TRUE | Q16: INSERITO | R16: FALSE | S16: TRUE | T16: TRUE
A17: Estefany | B17: ONLINE | C17: 46061 | E17: MARTINUCCIA | F17: SARA | G17: 3803794681 | H17: MRTSRA03C50L049X | I17: sara.martinucci03@gmail.com | J17: 46061 | K17: 22 | M17: =IFERROR(__xludf.DUMMYFUNCTION("IF( K17="""", """", ROUND( IF( L17="""", K17, IF( ISERROR(FIND(""-"",L17)), K17 - VALUE(REGEXEXTRACT(L17,""(\d+)"")), K17 * (1 - VALUE(REGEXEXTRACT(L17,""(\d+)""))/100) ) ), 2 ) ) "),22.0) -> 22 | N17: DIGIT - NON TESSERATO | O17: TRUE | Q17: INSERITO | R17: FALSE | S17: TRUE | T17: TRUE
A18: Estefany | B18: ONLINE | C18: 46062 | E18: SORTINO | F18: VITTORIA | G18: 3347340944 | H18: SRTVTR91P53B428H | I18: vittoriasortino@hotmal.it | J18: 46062 | K18: 22 | M18: =IFERROR(__xludf.DUMMYFUNCTION("IF( K18="""", """", ROUND( IF( L18="""", K18, IF( ISERROR(FIND(""-"",L18)), K18 - VALUE(REGEXEXTRACT(L18,""(\d+)"")), K18 * (1 - VALUE(REGEXEXTRACT(L18,""(\d+)""))/100) ) ), 2 ) ) "),22.0) -> 22 | N18: DIGIT - TESSERATO | O18: TRUE | Q18: INSERITO | R18: TRUE | S18: FALSE | T18: TRUE
A19: Nura | B19: SEDE Nura | C19: 46065 | E19: RASELLI | F19: MARTINA | G19: 3668777487 | H19: RSLMTN04T43M109C | I19: rasellimartina@gmail.com | J19: 46058 | K19: 22 | L19: NURA02WS | M19: =IFERROR(__xludf.DUMMYFUNCTION("IF( K19="""", """", ROUND( IF( L19="""", K19, IF( ISERROR(FIND(""-"",L19)), K19 - VALUE(REGEXEXTRACT(L19,""(\d+)"")), K19 * (1 - VALUE(REGEXEXTRACT(L19,""(\d+)""))/100) ) ), 2 ) ) "),20.0) -> 20 | N19: DIGIT - NON TESSERATO | O19: FALSE | Q19: INSERITO | R19: FALSE | S19: TRUE | T19: TRUE
A20: Estefany | B20: ONLINE | C20: 46063 | D20: ID-001028 | E20: DI NALLO | F20: GIULIA | G20: 3343323763 | H20: DNLGLI91D58G482T | I20: giuliadinallo@gmail.com | J20: 46063 | K20: 22 | M20: =IFERROR(__xludf.DUMMYFUNCTION("IF( K20="""", """", ROUND( IF( L20="""", K20, IF( ISERROR(FIND(""-"",L20)), K20 - VALUE(REGEXEXTRACT(L20,""(\d+)"")), K20 * (1 - VALUE(REGEXEXTRACT(L20,""(\d+)""))/100) ) ), 2 ) ) "),22.0) -> 22 | N20: DIGIT - TESSERATO | O20: TRUE | Q20: INSERITO | R20: TRUE | S20: FALSE | T20: TRUE
A21: Estefany | B21: ONLINE | C21: 46063 | E21: SPIRIDENKO | F21: EKATERINA | G21: 3665482253 | H21: SPRKRN86D66Z135E | I21: spiridenko.caterina@gmail.com | J21: 46063 | K21: 22 | L21: ESTEFANY02WS | M21: =IFERROR(__xludf.DUMMYFUNCTION("IF( K21="""", """", ROUND( IF( L21="""", K21, IF( ISERROR(FIND(""-"",L21)), K21 - VALUE(REGEXEXTRACT(L21,""(\d+)"")), K21 * (1 - VALUE(REGEXEXTRACT(L21,""(\d+)""))/100) ) ), 2 ) ) "),20.0) -> 20 | N21: DIGIT - NON TESSERATO | O21: FALSE | Q21: INSERITO | R21: FALSE | S21: TRUE | T21: TRUE
A22: Estefany | B22: ONLINE | C22: 46064 | E22: KOVA | F22: OLEKSANDRA | G22: 3913836441 | H22: KVLLSN05S56Z138S | I22: alekovak55@gmail.com | J22: 46064 | K22: 22 | L22: ALEXANDRA02WS | M22: =IFERROR(__xludf.DUMMYFUNCTION("IF( K22="""", """", ROUND( IF( L22="""", K22, IF( ISERROR(FIND(""-"",L22)), K22 - VALUE(REGEXEXTRACT(L22,""(\d+)"")), K22 * (1 - VALUE(REGEXEXTRACT(L22,""(\d+)""))/100) ) ), 2 ) ) "),20.0) -> 20 | N22: DIGIT - NON TESSERATO | O22: TRUE | Q22: INSERITO | R22: FALSE | S22: TRUE | T22: TRUE
A23: Estefany | B23: ONLINE | C23: 46064 | E23: NACUCCHI | F23: PAOLA | G23: 3883027426 | H23: NCCPLA01M49A048L | I23: aolanacu01@gmail.com | J23: 46064 | K23: 22 | L23: NURA02WS | M23: =IFERROR(__xludf.DUMMYFUNCTION("IF( K23="""", """", ROUND( IF( L23="""", K23, IF( ISERROR(FIND(""-"",L23)), K23 - VALUE(REGEXEXTRACT(L23,""(\d+)"")), K23 * (1 - VALUE(REGEXEXTRACT(L23,""(\d+)""))/100) ) ), 2 ) ) "),20.0) -> 20 | N23: DIGIT - TESSERATO | O23: TRUE | Q23: INSERITO | R23: TRUE | S23: FALSE | T23: TRUE
A24: Estefany | B24: ONLINE | C24: 46065 | D24: ID-001585 | E24: GEORGIEVA | F24: PLAMENA | G24: 3420354305 | H24: GRGPMN94H43Z104Y | I24: plamena.georgieva3@yahoo.com | J24: 46065 | K24: 22 | L24: NURA02WS | M24: =IFERROR(__xludf.DUMMYFUNCTION("IF( K24="""", """", ROUND( IF( L24="""", K24, IF( ISERROR(FIND(""-"",L24)), K24 - VALUE(REGEXEXTRACT(L24,""(\d+)"")), K24 * (1 - VALUE(REGEXEXTRACT(L24,""(\d+)""))/100) ) ), 2 ) ) "),20.0) -> 20 | N24: DIGIT - TESSERATO | O24: TRUE | Q24: INSERITO | R24: TRUE | S24: FALSE | T24: TRUE
A25: Estefany | B25: ONLINE | C25: 46065 | E25: FORNACIARI MEDANICH | F25: AURORA MARIA | G25: 3384362858 | H25: FRNRMR95R69G337O | I25: Aurimfm@gmail.com | J25: 46063 | K25: 22 | L25: NURA02WS | M25: =IFERROR(__xludf.DUMMYFUNCTION("IF( K25="""", """", ROUND( IF( L25="""", K25, IF( ISERROR(FIND(""-"",L25)), K25 - VALUE(REGEXEXTRACT(L25,""(\d+)"")), K25 * (1 - VALUE(REGEXEXTRACT(L25,""(\d+)""))/100) ) ), 2 ) ) "),20.0) -> 20 | N25: DIGIT - NON TESSERATO | O25: TRUE | Q25: INSERITO | R25: FALSE | S25: TRUE | T25: TRUE
A26: Giuditta | B26: SEDE Giuditta | C26: 46066 | E26: KAKIZAKI | F26: ITZUKI | G26: 3271246216 | H26: KKZTSK77S50Z219O | I26: itsukikakizaki@gmail.com | J26: 46066 | K26: 22 | L26: GIUDITTA02WS | M26: =IFERROR(__xludf.DUMMYFUNCTION("IF( K26="""", """", ROUND( IF( L26="""", K26, IF( ISERROR(FIND(""-"",L26)), K26 - VALUE(REGEXEXTRACT(L26,""(\d+)"")), K26 * (1 - VALUE(REGEXEXTRACT(L26,""(\d+)""))/100) ) ), 2 ) ) "),20.0) -> 20 | N26: CASH - TESSERATO | O26: TRUE | Q26: INSERITO | R26: TRUE | S26: FALSE | T26: TRUE
A27: Estefany | B27: ONLINE | C27: 46066 | D27: ID-000935 | E27: ZILIO | F27: MICAELA | G27: 3342947286 | H27: ZLIMCL98S66F205K | I27: ziliomicaela@gmail.com | J27: 46066 | K27: 22 | L27: NURA02WS | M27: =IFERROR(__xludf.DUMMYFUNCTION("IF( K27="""", """", ROUND( IF( L27="""", K27, IF( ISERROR(FIND(""-"",L27)), K27 - VALUE(REGEXEXTRACT(L27,""(\d+)"")), K27 * (1 - VALUE(REGEXEXTRACT(L27,""(\d+)""))/100) ) ), 2 ) ) "),20.0) -> 20 | N27: DIGIT - TESSERATO | O27: TRUE | Q27: INSERITO | R27: TRUE | S27: FALSE | T27: TRUE
A28: Estefany | B28: ONLINE | C28: 46066 | E28: CAMPANA | F28: CARMEN | G28: 3466219763 | H28: CMPCMN92R69A783N | I28: psicologa.carmencampana@gmail.com | J28: 46067 | K28: 22 | L28: NURA02WS | M28: =IFERROR(__xludf.DUMMYFUNCTION("IF( K28="""", """", ROUND( IF( L28="""", K28, IF( ISERROR(FIND(""-"",L28)), K28 - VALUE(REGEXEXTRACT(L28,""(\d+)"")), K28 * (1 - VALUE(REGEXEXTRACT(L28,""(\d+)""))/100) ) ), 2 ) ) "),20.0) -> 20 | N28: DIGIT - NON TESSERATO | O28: TRUE | Q28: INSERITO | R28: FALSE | S28: TRUE | T28: TRUE
A29: Estefany | B29: ONLINE | C29: 46067 | D29: ID-000963 | E29: MICHELI | F29: LINDA | G29: 3317286206 | H29: MCHLND03L41C816Q | I29: lindamicheli@icloud.com | J29: 46067 | K29: 22 | M29: =IFERROR(__xludf.DUMMYFUNCTION("IF( K29="""", """", ROUND( IF( L29="""", K29, IF( ISERROR(FIND(""-"",L29)), K29 - VALUE(REGEXEXTRACT(L29,""(\d+)"")), K29 * (1 - VALUE(REGEXEXTRACT(L29,""(\d+)""))/100) ) ), 2 ) ) "),22.0) -> 22 | N29: DIGIT - TESSERATO | O29: TRUE | Q29: INSERITO | R29: TRUE | S29: FALSE | T29: TRUE
A30: Estefany | B30: ONLINE | C30: 46067 | E30: SEMPRINI | F30: MATHILDA | G30: 3926253328 | H30: SMPMHL03H58F205F | I30: matthyhs@gmail.com | J30: 46067 | K30: 22 | L30: ALEXANDRA02WS | M30: =IFERROR(__xludf.DUMMYFUNCTION("IF( K30="""", """", ROUND( IF( L30="""", K30, IF( ISERROR(FIND(""-"",L30)), K30 - VALUE(REGEXEXTRACT(L30,""(\d+)"")), K30 * (1 - VALUE(REGEXEXTRACT(L30,""(\d+)""))/100) ) ), 2 ) ) "),20.0) -> 20 | N30: DIGIT - TESSERATO | O30: TRUE | Q30: INSERITO | R30: TRUE | S30: FALSE | T30: TRUE
A31: Estefany | B31: ONLINE | C31: 46067 | E31: PIANEZZE | F31: SARA | G31: 3291631986 | H31: PNZSRA06A56F205M | I31: sara.pianezze06@gmail.com | J31: 46067 | K31: 22 | L31: ESTEFANY02WS | M31: =IFERROR(__xludf.DUMMYFUNCTION("IF( K31="""", """", ROUND( IF( L31="""", K31, IF( ISERROR(FIND(""-"",L31)), K31 - VALUE(REGEXEXTRACT(L31,""(\d+)"")), K31 * (1 - VALUE(REGEXEXTRACT(L31,""(\d+)""))/100) ) ), 2 ) ) "),20.0) -> 20 | N31: DIGIT - NON TESSERATO | O31: TRUE | Q31: INSERITO | R31: FALSE | S31: TRUE | T31: TRUE
A32: Estefany | B32: ONLINE | C32: 46067 | D32: ID-000159 | E32: SEMPRINI | F32: MIKAELA | G32: 3317412540 | H32: SMPMKL99D59F205I | I32: mikaelamiky99@gmail.com | J32: 46067 | K32: 22 | L32: ALEXANDRA02WS | M32: =IFERROR(__xludf.DUMMYFUNCTION("IF( K32="""", """", ROUND( IF( L32="""", K32, IF( ISERROR(FIND(""-"",L32)), K32 - VALUE(REGEXEXTRACT(L32,""(\d+)"")), K32 * (1 - VALUE(REGEXEXTRACT(L32,""(\d+)""))/100) ) ), 2 ) ) "),20.0) -> 20 | N32: DIGIT - TESSERATO | O32: TRUE | Q32: INSERITO | R32: TRUE | S32: FALSE | T32: TRUE
A33: Estefany | B33: ONLINE | C33: 46067 | D33: ID-002211 | E33: BERTOCCHI | F33: DIANA | G33: 3496735854 | H33: BRTDNI01M63D969Q | I33: la.reverberi@gmail.com | J33: 46067 | K33: 22 | M33: =IFERROR(__xludf.DUMMYFUNCTION("IF( K33="""", """", ROUND( IF( L33="""", K33, IF( ISERROR(FIND(""-"",L33)), K33 - VALUE(REGEXEXTRACT(L33,""(\d+)"")), K33 * (1 - VALUE(REGEXEXTRACT(L33,""(\d+)""))/100) ) ), 2 ) ) "),22.0) -> 22 | N33: DIGIT - TESSERATO | O33: TRUE | Q33: INSERITO | R33: TRUE | S33: FALSE | T33: TRUE
A34: Estefany | B34: ONLINE | C34: 46067 | D34: ID-000129 | E34: PIVA | F34: GIULIA | G34: 3337184341 | H34: PVIGLI04R64F205I | I34: giulia.piva2024@gmail.com | J34: 46067 | K34: 22 | L34: NURA02WS | M34: =IFERROR(__xludf.DUMMYFUNCTION("IF( K34="""", """", ROUND( IF( L34="""", K34, IF( ISERROR(FIND(""-"",L34)), K34 - VALUE(REGEXEXTRACT(L34,""(\d+)"")), K34 * (1 - VALUE(REGEXEXTRACT(L34,""(\d+)""))/100) ) ), 2 ) ) "),20.0) -> 20 | N34: DIGIT - TESSERATO | O34: TRUE | Q34: INSERITO | R34: TRUE | S34: FALSE | T34: TRUE
A35: Estefany | B35: ONLINE | C35: 46068 | E35: GAMANNOSSI | F35: ARIANNA | G35: 3485751038 | H35: GMNRNN96S44A564V | I35: agamannossi@gmail.com | J35: 46068 | K35: 22 | M35: =IFERROR(__xludf.DUMMYFUNCTION("IF( K35="""", """", ROUND( IF( L35="""", K35, IF( ISERROR(FIND(""-"",L35)), K35 - VALUE(REGEXEXTRACT(L35,""(\d+)"")), K35 * (1 - VALUE(REGEXEXTRACT(L35,""(\d+)""))/100) ) ), 2 ) ) "),22.0) -> 22 | N35: DIGIT - NON TESSERATO | O35: TRUE | Q35: INSERITO | R35: FALSE | S35: TRUE | T35: TRUE
A36: Estefany | B36: ONLINE | C36: 46068 | D36: ID-000263 | E36: AMAGUAY | F36: CAMILA | G36: 3887207103 | H36: MGYCLV06R66Z605I | I36: munozvalentina445@gmail.com | J36: 46068 | K36: 22 | L36: NURA02WS | M36: =IFERROR(__xludf.DUMMYFUNCTION("IF( K36="""", """", ROUND( IF( L36="""", K36, IF( ISERROR(FIND(""-"",L36)), K36 - VALUE(REGEXEXTRACT(L36,""(\d+)"")), K36 * (1 - VALUE(REGEXEXTRACT(L36,""(\d+)""))/100) ) ), 2 ) ) "),20.0) -> 20 | N36: DIGIT - TESSERATO | O36: TRUE | Q36: INSERITO | R36: TRUE | S36: FALSE | T36: TRUE
A37: Estefany | B37: ONLINE | C37: 46076 | E37: ROGNINI | F37: CAROLINA | G37: 3204460419 | H37: RGNCLN01B51E897F | I37: carolina.2001@icloud.com | J37: 46076 | K37: 27 | L37: ESTEFANY02WS | M37: =IFERROR(__xludf.DUMMYFUNCTION("IF( K37="""", """", ROUND( IF( L37="""", K37, IF( ISERROR(FIND(""-"",L37)), K37 - VALUE(REGEXEXTRACT(L37,""(\d+)"")), K37 * (1 - VALUE(REGEXEXTRACT(L37,""(\d+)""))/100) ) ), 2 ) ) "),25.0) -> 25 | N37: DIGIT - NON TESSERATO | O37: TRUE | Q37: INSERITO | R37: FALSE | S37: TRUE | T37: TRUE
A38: Estefany | B38: ONLINE | C38: 46076 | E38: BOLOGNINI | F38: MICHELLE | G38: 3474184467 | H38: BLGMHL00P59E897P | I38: michelle00bolognini@gmail.com | J38: 46076 | K38: 27 | M38: =IFERROR(__xludf.DUMMYFUNCTION("IF( K38="""", """", ROUND( IF( L38="""", K38, IF( ISERROR(FIND(""-"",L38)), K38 - VALUE(REGEXEXTRACT(L38,""(\d+)"")), K38 * (1 - VALUE(REGEXEXTRACT(L38,""(\d+)""))/100) ) ), 2 ) ) "),27.0) -> 27 | N38: DIGIT - NON TESSERATO | O38: TRUE | Q38: INSERITO | R38: FALSE | S38: TRUE | T38: TRUE
A39: Estefany | B39: ONLINE | C39: 46076 | E39: ENRIQUEZ | F39: ERIKA JOY | G39: 3899691211 | H39: NRQRJY00T41H224R | I39: Eerikajoy@yahoo.it | J39: 46076 | K39: 27 | M39: =IFERROR(__xludf.DUMMYFUNCTION("IF( K39="""", """", ROUND( IF( L39="""", K39, IF( ISERROR(FIND(""-"",L39)), K39 - VALUE(REGEXEXTRACT(L39,""(\d+)"")), K39 * (1 - VALUE(REGEXEXTRACT(L39,""(\d+)""))/100) ) ), 2 ) ) "),27.0) -> 27 | N39: DIGIT - NON TESSERATO | O39: TRUE | Q39: INSERITO | R39: FALSE | S39: TRUE | T39: TRUE
A40: Estefany | B40: ONLINE | C40: 46077 | E40: BOUDRAR | F40: AYA | G40: 3299173345 | H40: BDRYAA03H50Z330V | I40: ayaboudrar0@gmail.com | J40: 46077 | K40: 27 | M40: =IFERROR(__xludf.DUMMYFUNCTION("IF( K40="""", """", ROUND( IF( L40="""", K40, IF( ISERROR(FIND(""-"",L40)), K40 - VALUE(REGEXEXTRACT(L40,""(\d+)"")), K40 * (1 - VALUE(REGEXEXTRACT(L40,""(\d+)""))/100) ) ), 2 ) ) "),27.0) -> 27 | N40: DIGIT - NON TESSERATO | O40: TRUE | Q40: INSERITO | R40: FALSE | S40: TRUE | T40: TRUE
A41: Estefany | B41: ONLINE | C41: 46079 | E41: BOLOGNINI | F41: GRETA | G41: 3496466509 | H41: BLGGRT06T44E897M | I41: gretabolognini06@libero.it | J41: 46079 | K41: 27 | M41: =IFERROR(__xludf.DUMMYFUNCTION("IF( K41="""", """", ROUND( IF( L41="""", K41, IF( ISERROR(FIND(""-"",L41)), K41 - VALUE(REGEXEXTRACT(L41,""(\d+)"")), K41 * (1 - VALUE(REGEXEXTRACT(L41,""(\d+)""))/100) ) ), 2 ) ) "),27.0) -> 27 | N41: DIGIT - NON TESSERATO | O41: TRUE | Q41: INSERITO | R41: FALSE | S41: TRUE | T41: TRUE
A42: Estefany | B42: ONLINE | C42: 46081 | E42: GAVIRAGHI | F42: CATERINA | G42: 3389976851 | H42: GVRCRN00H69M052F | I42: categaviraghi@gmail.com | J42: 46081 | K42: 27 | L42: ESTEFANY02WS | M42: =IFERROR(__xludf.DUMMYFUNCTION("IF( K42="""", """", ROUND( IF( L42="""", K42, IF( ISERROR(FIND(""-"",L42)), K42 - VALUE(REGEXEXTRACT(L42,""(\d+)"")), K42 * (1 - VALUE(REGEXEXTRACT(L42,""(\d+)""))/100) ) ), 2 ) ) "),25.0) -> 25 | N42: DIGIT - NON TESSERATO | O42: TRUE | Q42: INSERITO | R42: FALSE | S42: TRUE | T42: TRUE
A43: Joel | B43: SEDE Joel | C43: 46082 | D43: ID-002128 | E43: DELLA CA' | F43: MARTINA | G43: 3478337785 | H43: DLLMTN94R67B300W | I43: martina.dellaca@gmail.com | J43: 46082 | K43: 27 | M43: =IFERROR(__xludf.DUMMYFUNCTION("IF( K43="""", """", ROUND( IF( L43="""", K43, IF( ISERROR(FIND(""-"",L43)), K43 - VALUE(REGEXEXTRACT(L43,""(\d+)"")), K43 * (1 - VALUE(REGEXEXTRACT(L43,""(\d+)""))/100) ) ), 2 ) ) "),27.0) -> 27 | N43: CASH - TESSERATO | O43: TRUE | Q43: INSERITO | R43: TRUE | S43: FALSE | T43: TRUE
A44: Joel | B44: ONLINE | C44: 46081 | D44: ID-004328 | E44: FORNARI | F44: EMMA | G44: 3274578882 | H44: FRNMME00D59C573R | I44: emmafornari@gmail.com | J44: 46081 | K44: 27 | M44: =IFERROR(__xludf.DUMMYFUNCTION("IF( K44="""", """", ROUND( IF( L44="""", K44, IF( ISERROR(FIND(""-"",L44)), K44 - VALUE(REGEXEXTRACT(L44,""(\d+)"")), K44 * (1 - VALUE(REGEXEXTRACT(L44,""(\d+)""))/100) ) ), 2 ) ) "),27.0) -> 27 | N44: DIGIT - TESSERATO | O44: TRUE | Q44: INSERITO | R44: TRUE | S44: FALSE | T44: TRUE
M45: =IFERROR(__xludf.DUMMYFUNCTION("IF( K45="""", """", ROUND( IF( L45="""", K45, IF( ISERROR(FIND(""-"",L45)), K45 - VALUE(REGEXEXTRACT(L45,""(\d+)"")), K45 * (1 - VALUE(REGEXEXTRACT(L45,""(\d+)""))/100) ) ), 2 ) ) ")," ") | O45: FALSE | R45: FALSE | S45: FALSE | T45: FALSE
M46: =IFERROR(__xludf.DUMMYFUNCTION("IF( K46="""", """", ROUND( IF( L46="""", K46, IF( ISERROR(FIND(""-"",L46)), K46 - VALUE(REGEXEXTRACT(L46,""(\d+)"")), K46 * (1 - VALUE(REGEXEXTRACT(L46,""(\d+)""))/100) ) ), 2 ) ) ")," ") | O46: FALSE | R46: FALSE | S46: FALSE | T46: FALSE
M47: =IFERROR(__xludf.DUMMYFUNCTION("IF( K47="""", """", ROUND( IF( L47="""", K47, IF( ISERROR(FIND(""-"",L47)), K47 - VALUE(REGEXEXTRACT(L47,""(\d+)"")), K47 * (1 - VALUE(REGEXEXTRACT(L47,""(\d+)""))/100) ) ), 2 ) ) ")," ") | O47: FALSE | R47: FALSE | S47: FALSE | T47: FALSE
M48: =IFERROR(__xludf.DUMMYFUNCTION("IF( K48="""", """", ROUND( IF( L48="""", K48, IF( ISERROR(FIND(""-"",L48)), K48 - VALUE(REGEXEXTRACT(L48,""(\d+)"")), K48 * (1 - VALUE(REGEXEXTRACT(L48,""(\d+)""))/100) ) ), 2 ) ) ")," ") | O48: FALSE | R48: FALSE | S48: FALSE | T48: FALSE
M49: =IFERROR(__xludf.DUMMYFUNCTION("IF( K49="""", """", ROUND( IF( L49="""", K49, IF( ISERROR(FIND(""-"",L49)), K49 - VALUE(REGEXEXTRACT(L49,""(\d+)"")), K49 * (1 - VALUE(REGEXEXTRACT(L49,""(\d+)""))/100) ) ), 2 ) ) ")," ") | O49: FALSE | R49: FALSE | S49: FALSE | T49: FALSE
M50: =IFERROR(__xludf.DUMMYFUNCTION("IF( K50="""", """", ROUND( IF( L50="""", K50, IF( ISERROR(FIND(""-"",L50)), K50 - VALUE(REGEXEXTRACT(L50,""(\d+)"")), K50 * (1 - VALUE(REGEXEXTRACT(L50,""(\d+)""))/100) ) ), 2 ) ) ")," ") | O50: FALSE | R50: FALSE | S50: FALSE | T50: FALSE
M51: =IFERROR(__xludf.DUMMYFUNCTION("IF( K51="""", """", ROUND( IF( L51="""", K51, IF( ISERROR(FIND(""-"",L51)), K51 - VALUE(REGEXEXTRACT(L51,""(\d+)"")), K51 * (1 - VALUE(REGEXEXTRACT(L51,""(\d+)""))/100) ) ), 2 ) ) ")," ") | O51: FALSE | R51: FALSE | S51: FALSE | T51: FALSE
M52: =IFERROR(__xludf.DUMMYFUNCTION("IF( K52="""", """", ROUND( IF( L52="""", K52, IF( ISERROR(FIND(""-"",L52)), K52 - VALUE(REGEXEXTRACT(L52,""(\d+)"")), K52 * (1 - VALUE(REGEXEXTRACT(L52,""(\d+)""))/100) ) ), 2 ) ) ")," ") | O52: FALSE | R52: FALSE | S52: FALSE | T52: FALSE
M53: =IFERROR(__xludf.DUMMYFUNCTION("IF( K53="""", """", ROUND( IF( L53="""", K53, IF( ISERROR(FIND(""-"",L53)), K53 - VALUE(REGEXEXTRACT(L53,""(\d+)"")), K53 * (1 - VALUE(REGEXEXTRACT(L53,""(\d+)""))/100) ) ), 2 ) ) ")," ") | O53: FALSE | R53: FALSE | S53: FALSE | T53: FALSE
M54: =IFERROR(__xludf.DUMMYFUNCTION("IF( K54="""", """", ROUND( IF( L54="""", K54, IF( ISERROR(FIND(""-"",L54)), K54 - VALUE(REGEXEXTRACT(L54,""(\d+)"")), K54 * (1 - VALUE(REGEXEXTRACT(L54,""(\d+)""))/100) ) ), 2 ) ) ")," ") | O54: FALSE | R54: FALSE | S54: FALSE | T54: FALSE
M55: =IFERROR(__xludf.DUMMYFUNCTION("IF( K55="""", """", ROUND( IF( L55="""", K55, IF( ISERROR(FIND(""-"",L55)), K55 - VALUE(REGEXEXTRACT(L55,""(\d+)"")), K55 * (1 - VALUE(REGEXEXTRACT(L55,""(\d+)""))/100) ) ), 2 ) ) ")," ") | O55: FALSE | R55: FALSE | S55: FALSE | T55: FALSE
M56: =IFERROR(__xludf.DUMMYFUNCTION("IF( K56="""", """", ROUND( IF( L56="""", K56, IF( ISERROR(FIND(""-"",L56)), K56 - VALUE(REGEXEXTRACT(L56,""(\d+)"")), K56 * (1 - VALUE(REGEXEXTRACT(L56,""(\d+)""))/100) ) ), 2 ) ) ")," ") | O56: FALSE | R56: FALSE | S56: FALSE | T56: FALSE
M57: =IFERROR(__xludf.DUMMYFUNCTION("IF( K57="""", """", ROUND( IF( L57="""", K57, IF( ISERROR(FIND(""-"",L57)), K57 - VALUE(REGEXEXTRACT(L57,""(\d+)"")), K57 * (1 - VALUE(REGEXEXTRACT(L57,""(\d+)""))/100) ) ), 2 ) ) ")," ") | O57: FALSE | R57: FALSE | S57: FALSE | T57: FALSE
M58: =IFERROR(__xludf.DUMMYFUNCTION("IF( K58="""", """", ROUND( IF( L58="""", K58, IF( ISERROR(FIND(""-"",L58)), K58 - VALUE(REGEXEXTRACT(L58,""(\d+)"")), K58 * (1 - VALUE(REGEXEXTRACT(L58,""(\d+)""))/100) ) ), 2 ) ) ")," ") | O58: FALSE | R58: FALSE | S58: FALSE | T58: FALSE
M59: =IFERROR(__xludf.DUMMYFUNCTION("IF( K59="""", """", ROUND( IF( L59="""", K59, IF( ISERROR(FIND(""-"",L59)), K59 - VALUE(REGEXEXTRACT(L59,""(\d+)"")), K59 * (1 - VALUE(REGEXEXTRACT(L59,""(\d+)""))/100) ) ), 2 ) ) ")," ") | O59: FALSE | R59: FALSE | S59: FALSE | T59: FALSE
M60: =IFERROR(__xludf.DUMMYFUNCTION("IF( K60="""", """", ROUND( IF( L60="""", K60, IF( ISERROR(FIND(""-"",L60)), K60 - VALUE(REGEXEXTRACT(L60,""(\d+)"")), K60 * (1 - VALUE(REGEXEXTRACT(L60,""(\d+)""))/100) ) ), 2 ) ) ")," ") | O60: FALSE | R60: FALSE | S60: FALSE | T60: FALSE
M61: =IFERROR(__xludf.DUMMYFUNCTION("IF( K61="""", """", ROUND( IF( L61="""", K61, IF( ISERROR(FIND(""-"",L61)), K61 - VALUE(REGEXEXTRACT(L61,""(\d+)"")), K61 * (1 - VALUE(REGEXEXTRACT(L61,""(\d+)""))/100) ) ), 2 ) ) ")," ") | O61: FALSE | R61: FALSE | S61: FALSE | T61: FALSE
M62: =IFERROR(__xludf.DUMMYFUNCTION("IF( K62="""", """", ROUND( IF( L62="""", K62, IF( ISERROR(FIND(""-"",L62)), K62 - VALUE(REGEXEXTRACT(L62,""(\d+)"")), K62 * (1 - VALUE(REGEXEXTRACT(L62,""(\d+)""))/100) ) ), 2 ) ) ")," ") | O62: FALSE | R62: FALSE | S62: FALSE | T62: FALSE
M63: =IFERROR(__xludf.DUMMYFUNCTION("IF( K63="""", """", ROUND( IF( L63="""", K63, IF( ISERROR(FIND(""-"",L63)), K63 - VALUE(REGEXEXTRACT(L63,""(\d+)"")), K63 * (1 - VALUE(REGEXEXTRACT(L63,""(\d+)""))/100) ) ), 2 ) ) ")," ") | O63: FALSE | R63: FALSE | S63: FALSE | T63: FALSE
M64: =IFERROR(__xludf.DUMMYFUNCTION("IF( K64="""", """", ROUND( IF( L64="""", K64, IF( ISERROR(FIND(""-"",L64)), K64 - VALUE(REGEXEXTRACT(L64,""(\d+)"")), K64 * (1 - VALUE(REGEXEXTRACT(L64,""(\d+)""))/100) ) ), 2 ) ) ")," ") | O64: FALSE | R64: FALSE | S64: FALSE | T64: FALSE
M65: =IFERROR(__xludf.DUMMYFUNCTION("IF( K65="""", """", ROUND( IF( L65="""", K65, IF( ISERROR(FIND(""-"",L65)), K65 - VALUE(REGEXEXTRACT(L65,""(\d+)"")), K65 * (1 - VALUE(REGEXEXTRACT(L65,""(\d+)""))/100) ) ), 2 ) ) ")," ") | O65: FALSE | R65: FALSE | S65: FALSE | T65: FALSE
M66: =IFERROR(__xludf.DUMMYFUNCTION("IF( K66="""", """", ROUND( IF( L66="""", K66, IF( ISERROR(FIND(""-"",L66)), K66 - VALUE(REGEXEXTRACT(L66,""(\d+)"")), K66 * (1 - VALUE(REGEXEXTRACT(L66,""(\d+)""))/100) ) ), 2 ) ) ")," ") | O66: FALSE | R66: FALSE | S66: FALSE | T66: FALSE
M67: =IFERROR(__xludf.DUMMYFUNCTION("IF( K67="""", """", ROUND( IF( L67="""", K67, IF( ISERROR(FIND(""-"",L67)), K67 - VALUE(REGEXEXTRACT(L67,""(\d+)"")), K67 * (1 - VALUE(REGEXEXTRACT(L67,""(\d+)""))/100) ) ), 2 ) ) ")," ") | O67: FALSE | R67: FALSE | S67: FALSE | T67: FALSE
M68: =IFERROR(__xludf.DUMMYFUNCTION("IF( K68="""", """", ROUND( IF( L68="""", K68, IF( ISERROR(FIND(""-"",L68)), K68 - VALUE(REGEXEXTRACT(L68,""(\d+)"")), K68 * (1 - VALUE(REGEXEXTRACT(L68,""(\d+)""))/100) ) ), 2 ) ) ")," ") | O68: FALSE | R68: FALSE | S68: FALSE | T68: FALSE
M69: =IFERROR(__xludf.DUMMYFUNCTION("IF( K69="""", """", ROUND( IF( L69="""", K69, IF( ISERROR(FIND(""-"",L69)), K69 - VALUE(REGEXEXTRACT(L69,""(\d+)"")), K69 * (1 - VALUE(REGEXEXTRACT(L69,""(\d+)""))/100) ) ), 2 ) ) ")," ") | O69: FALSE | R69: FALSE | S69: FALSE | T69: FALSE
M70: =IFERROR(__xludf.DUMMYFUNCTION("IF( K70="""", """", ROUND( IF( L70="""", K70, IF( ISERROR(FIND(""-"",L70)), K70 - VALUE(REGEXEXTRACT(L70,""(\d+)"")), K70 * (1 - VALUE(REGEXEXTRACT(L70,""(\d+)""))/100) ) ), 2 ) ) ")," ") | O70: FALSE | R70: FALSE | S70: FALSE | T70: FALSE
M71: =IFERROR(__xludf.DUMMYFUNCTION("IF( K71="""", """", ROUND( IF( L71="""", K71, IF( ISERROR(FIND(""-"",L71)), K71 - VALUE(REGEXEXTRACT(L71,""(\d+)"")), K71 * (1 - VALUE(REGEXEXTRACT(L71,""(\d+)""))/100) ) ), 2 ) ) ")," ") | O71: FALSE | R71: FALSE | S71: FALSE | T71: FALSE
M72: =IFERROR(__xludf.DUMMYFUNCTION("IF( K72="""", """", ROUND( IF( L72="""", K72, IF( ISERROR(FIND(""-"",L72)), K72 - VALUE(REGEXEXTRACT(L72,""(\d+)"")), K72 * (1 - VALUE(REGEXEXTRACT(L72,""(\d+)""))/100) ) ), 2 ) ) ")," ") | O72: FALSE | R72: FALSE | S72: FALSE | T72: FALSE
M73: =IFERROR(__xludf.DUMMYFUNCTION("IF( K73="""", """", ROUND( IF( L73="""", K73, IF( ISERROR(FIND(""-"",L73)), K73 - VALUE(REGEXEXTRACT(L73,""(\d+)"")), K73 * (1 - VALUE(REGEXEXTRACT(L73,""(\d+)""))/100) ) ), 2 ) ) ")," ") | O73: FALSE | R73: FALSE | S73: FALSE | T73: FALSE
M74: =IFERROR(__xludf.DUMMYFUNCTION("IF( K74="""", """", ROUND( IF( L74="""", K74, IF( ISERROR(FIND(""-"",L74)), K74 - VALUE(REGEXEXTRACT(L74,""(\d+)"")), K74 * (1 - VALUE(REGEXEXTRACT(L74,""(\d+)""))/100) ) ), 2 ) ) ")," ") | O74: FALSE | R74: FALSE | S74: FALSE | T74: FALSE
M75: =IFERROR(__xludf.DUMMYFUNCTION("IF( K75="""", """", ROUND( IF( L75="""", K75, IF( ISERROR(FIND(""-"",L75)), K75 - VALUE(REGEXEXTRACT(L75,""(\d+)"")), K75 * (1 - VALUE(REGEXEXTRACT(L75,""(\d+)""))/100) ) ), 2 ) ) ")," ") | O75: FALSE | R75: FALSE | S75: FALSE | T75: FALSE
M76: =IFERROR(__xludf.DUMMYFUNCTION("IF( K76="""", """", ROUND( IF( L76="""", K76, IF( ISERROR(FIND(""-"",L76)), K76 - VALUE(REGEXEXTRACT(L76,""(\d+)"")), K76 * (1 - VALUE(REGEXEXTRACT(L76,""(\d+)""))/100) ) ), 2 ) ) ")," ") | O76: FALSE | R76: FALSE | S76: FALSE | T76: FALSE
M77: =IFERROR(__xludf.DUMMYFUNCTION("IF( K77="""", """", ROUND( IF( L77="""", K77, IF( ISERROR(FIND(""-"",L77)), K77 - VALUE(REGEXEXTRACT(L77,""(\d+)"")), K77 * (1 - VALUE(REGEXEXTRACT(L77,""(\d+)""))/100) ) ), 2 ) ) ")," ") | O77: FALSE | R77: FALSE | S77: FALSE | T77: FALSE
M78: =IFERROR(__xludf.DUMMYFUNCTION("IF( K78="""", """", ROUND( IF( L78="""", K78, IF( ISERROR(FIND(""-"",L78)), K78 - VALUE(REGEXEXTRACT(L78,""(\d+)"")), K78 * (1 - VALUE(REGEXEXTRACT(L78,""(\d+)""))/100) ) ), 2 ) ) ")," ") | O78: FALSE | R78: FALSE | S78: FALSE | T78: FALSE
M79: =IFERROR(__xludf.DUMMYFUNCTION("IF( K79="""", """", ROUND( IF( L79="""", K79, IF( ISERROR(FIND(""-"",L79)), K79 - VALUE(REGEXEXTRACT(L79,""(\d+)"")), K79 * (1 - VALUE(REGEXEXTRACT(L79,""(\d+)""))/100) ) ), 2 ) ) ")," ") | O79: FALSE | R79: FALSE | S79: FALSE | T79: FALSE
M80: =IFERROR(__xludf.DUMMYFUNCTION("IF( K80="""", """", ROUND( IF( L80="""", K80, IF( ISERROR(FIND(""-"",L80)), K80 - VALUE(REGEXEXTRACT(L80,""(\d+)"")), K80 * (1 - VALUE(REGEXEXTRACT(L80,""(\d+)""))/100) ) ), 2 ) ) ")," ") | O80: FALSE | R80: FALSE | S80: FALSE | T80: FALSE
M81: =IFERROR(__xludf.DUMMYFUNCTION("IF( K81="""", """", ROUND( IF( L81="""", K81, IF( ISERROR(FIND(""-"",L81)), K81 - VALUE(REGEXEXTRACT(L81,""(\d+)"")), K81 * (1 - VALUE(REGEXEXTRACT(L81,""(\d+)""))/100) ) ), 2 ) ) ")," ") | O81: FALSE | R81: FALSE | S81: FALSE | T81: FALSE
M82: =IFERROR(__xludf.DUMMYFUNCTION("IF( K82="""", """", ROUND( IF( L82="""", K82, IF( ISERROR(FIND(""-"",L82)), K82 - VALUE(REGEXEXTRACT(L82,""(\d+)"")), K82 * (1 - VALUE(REGEXEXTRACT(L82,""(\d+)""))/100) ) ), 2 ) ) ")," ") | O82: FALSE | R82: FALSE | S82: FALSE | T82: FALSE
M83: =IFERROR(__xludf.DUMMYFUNCTION("IF( K83="""", """", ROUND( IF( L83="""", K83, IF( ISERROR(FIND(""-"",L83)), K83 - VALUE(REGEXEXTRACT(L83,""(\d+)"")), K83 * (1 - VALUE(REGEXEXTRACT(L83,""(\d+)""))/100) ) ), 2 ) ) ")," ") | O83: FALSE | R83: FALSE | S83: FALSE | T83: FALSE
A84: TOTALE | B84: =COUNTIF(B4:B83,"ONLINE")+COUNTIF(B4:B83,"SEDE*") -> 41 | C84: TOTALE | D84: =COUNTIF(D4:D83, "*") -> 16 | E84: =COUNTIF(E4:E83, "*") -> 41 | F84: =COUNTIF(F4:F83, "*") -> 41 | G84: =COUNTA(G4:G83) -> 41 | H84: =COUNTIF(H4:H83, "*") -> 41 | I84: =COUNTIF(I4:I83, "*") -> 41 | J84: TOTALE | K84: =SUM(K4:K83) -> 942 | L84: =COUNTIF(L4:L83, "*") -> 23 | M84: =SUM(M4:M83) -> 896 | N84: =COUNTIF(N4:N83, "*") -> 41 | O84: =SUMPRODUCT(--O4:O83) -> 38 | P84: =COUNTIF(P4:P83, "*") -> 0 | Q84: =COUNTIF(Q4:Q83, "*") -> 41 | R84: =SUMPRODUCT(--R4:R83) -> 20 | S84: =SUMPRODUCT(--S4:S83) -> 21 | T84: =SUMPRODUCT(--T4:T83) -> 41
A85: SEDE | B85: =COUNTIF(B4:B83, "SEDE*") -> 3 | D85: TOTALI WS 1 | E85: LISTA PREZZI | F85: =IFERROR(__xludf.DUMMYFUNCTION("IFERROR(TRANSPOSE(SORT(UNIQUE(FILTER($M$4:$M$83,$M$4:$M$83<>"""")))),"""")"),20.0) -> 20 | G85: =IFERROR(__xludf.DUMMYFUNCTION("""COMPUTED_VALUE"""),22.0) -> 22 | H85: =IFERROR(__xludf.DUMMYFUNCTION("""COMPUTED_VALUE"""),25.0) -> 25 | I85: =IFERROR(__xludf.DUMMYFUNCTION("""COMPUTED_VALUE"""),27.0) -> 27 | P85: TOTALE | Q85: =IF(SUM(F87:O87)=0,"",SUM(F87:O87)) -> 67 | R85: Verifica | S85: =IF(SUM(M84) = SUM(Q85:Q89), "OK", "ERRORE") -> OK
A86: ONLINE | B86: =COUNTIF(B4:B83, "ONLINE") -> 38 | E86: PERSONE SEDE | F86: =IF( F$85="", "", COUNTIFS($B$4:$B$83,"*SEDE*",$M$4:$M$83,F$85) ) -> 2 | G86: =IF( G$85="", "", COUNTIFS($B$4:$B$83,"*SEDE*",$M$4:$M$83,G$85) ) -> 0 | H86: =IF( H$85="", "", COUNTIFS($B$4:$B$83,"*SEDE*",$M$4:$M$83,H$85) ) -> 0 | I86: =IF( I$85="", "", COUNTIFS($B$4:$B$83,"*SEDE*",$M$4:$M$83,I$85) ) -> 1 | J86: =IF( J$85="", "", COUNTIFS($B$4:$B$83,"*SEDE*",$M$4:$M$83,J$85) ) | K86: =IF( K$85="", "", COUNTIFS($B$4:$B$83,"*SEDE*",$M$4:$M$83,K$85) ) | L86: =IF( L$85="", "", COUNTIFS($B$4:$B$83,"*SEDE*",$M$4:$M$83,L$85) ) | M86: =IF( M$85="", "", COUNTIFS($B$4:$B$83,"*SEDE*",$M$4:$M$83,M$85) ) | ... O86: =IF( O$85="", "", COUNTIFS($B$4:$B$83,"*SEDE*",$M$4:$M$83,O$85) )
E87: subTOTALE SEDE | F87: =IF( F$85="", "", SUMIFS($M$4:$M$83,$B$4:$B$83,"*SEDE*",$M$4:$M$83,F$85) ) -> 40 | G87: =IF( G$85="", "", SUMIFS($M$4:$M$83,$B$4:$B$83,"*SEDE*",$M$4:$M$83,G$85) ) -> 0 | H87: =IF( H$85="", "", SUMIFS($M$4:$M$83,$B$4:$B$83,"*SEDE*",$M$4:$M$83,H$85) ) -> 0 | I87: =IF( I$85="", "", SUMIFS($M$4:$M$83,$B$4:$B$83,"*SEDE*",$M$4:$M$83,I$85) ) -> 27 | J87: =IF( J$85="", "", SUMIFS($M$4:$M$83,$B$4:$B$83,"*SEDE*",$M$4:$M$83,J$85) ) | K87: =IF( K$85="", "", SUMIFS($M$4:$M$83,$B$4:$B$83,"*SEDE*",$M$4:$M$83,K$85) ) | L87: =IF( L$85="", "", SUMIFS($M$4:$M$83,$B$4:$B$83,"*SEDE*",$M$4:$M$83,L$85) ) | M87: =IF( M$85="", "", SUMIFS($M$4:$M$83,$B$4:$B$83,"*SEDE*",$M$4:$M$83,M$85) ) | ... O87: =IF( O$85="", "", SUMIFS($M$4:$M$83,$B$4:$B$83,"*SEDE*",$M$4:$M$83,O$85) )
E88: PERSONE ONLINE | F88: =IF( F$85="", "", COUNTIFS($B$4:$B$83,"*ONLINE*",$M$4:$M$83,F$85) ) -> 19 | G88: =IF( G$85="", "", COUNTIFS($B$4:$B$83,"*ONLINE*",$M$4:$M$83,G$85) ) -> 12 | H88: =IF( H$85="", "", COUNTIFS($B$4:$B$83,"*ONLINE*",$M$4:$M$83,H$85) ) -> 2 | I88: =IF( I$85="", "", COUNTIFS($B$4:$B$83,"*ONLINE*",$M$4:$M$83,I$85) ) -> 5 | J88: =IF( J$85="", "", COUNTIFS($B$4:$B$83,"*ONLINE*",$M$4:$M$83,J$85) ) | K88: =IF( K$85="", "", COUNTIFS($B$4:$B$83,"*ONLINE*",$M$4:$M$83,K$85) ) | L88: =IF( L$85="", "", COUNTIFS($B$4:$B$83,"*ONLINE*",$M$4:$M$83,L$85) ) | M88: =IF( M$85="", "", COUNTIFS($B$4:$B$83,"*ONLINE*",$M$4:$M$83,M$85) ) | ... O88: =IF( O$85="", "", COUNTIFS($B$4:$B$83,"*ONLINE*",$M$4:$M$83,O$85) ) | P88: TOTALE | Q88: =IF(SUM(F89:O89)=0,"",SUM(F89:O89)) -> 829
E89: subTOTALE ONLINE | F89: =IF( F$85="", "", SUMIFS($M$4:$M$83,$B$4:$B$83,"*ONLINE*",$M$4:$M$83,F$85) ) -> 380 | G89: =IF( G$85="", "", SUMIFS($M$4:$M$83,$B$4:$B$83,"*ONLINE*",$M$4:$M$83,G$85) ) -> 264 | H89: =IF( H$85="", "", SUMIFS($M$4:$M$83,$B$4:$B$83,"*ONLINE*",$M$4:$M$83,H$85) ) -> 50 | I89: =IF( I$85="", "", SUMIFS($M$4:$M$83,$B$4:$B$83,"*ONLINE*",$M$4:$M$83,I$85) ) -> 135 | J89: =IF( J$85="", "", SUMIFS($M$4:$M$83,$B$4:$B$83,"*ONLINE*",$M$4:$M$83,J$85) ) | K89: =IF( K$85="", "", SUMIFS($M$4:$M$83,$B$4:$B$83,"*ONLINE*",$M$4:$M$83,K$85) ) | L89: =IF( L$85="", "", SUMIFS($M$4:$M$83,$B$4:$B$83,"*ONLINE*",$M$4:$M$83,L$85) ) | M89: =IF( M$85="", "", SUMIFS($M$4:$M$83,$B$4:$B$83,"*ONLINE*",$M$4:$M$83,M$85) ) | ... O89: =IF( O$85="", "", SUMIFS($M$4:$M$83,$B$4:$B$83,"*ONLINE*",$M$4:$M$83,O$85) )
C90: LISTA D'ATTESA oppure [ORARIO]_[GENERE] (€X entro il XX/XX compreso → €Y entro il YY/YY compreso → €Z il giorno stesso)
M91: =IFERROR(__xludf.DUMMYFUNCTION("IF( K91="""", """", ROUND( IF( L91="""", K91, IF( ISERROR(FIND(""-"",L91)), K91 - VALUE(REGEXEXTRACT(L91,""(\d+)"")), K91 * (1 - VALUE(REGEXEXTRACT(L91,""(\d+)""))/100) ) ), 2 ) ) ")," ") | O91: FALSE | R91: FALSE | S91: FALSE | T91: FALSE
M92: =IFERROR(__xludf.DUMMYFUNCTION("IF( K92="""", """", ROUND( IF( L92="""", K92, IF( ISERROR(FIND(""-"",L92)), K92 - VALUE(REGEXEXTRACT(L92,""(\d+)"")), K92 * (1 - VALUE(REGEXEXTRACT(L92,""(\d+)""))/100) ) ), 2 ) ) ")," ") | O92: FALSE | R92: FALSE | S92: FALSE | T92: FALSE
M93: =IFERROR(__xludf.DUMMYFUNCTION("IF( K93="""", """", ROUND( IF( L93="""", K93, IF( ISERROR(FIND(""-"",L93)), K93 - VALUE(REGEXEXTRACT(L93,""(\d+)"")), K93 * (1 - VALUE(REGEXEXTRACT(L93,""(\d+)""))/100) ) ), 2 ) ) ")," ") | O93: FALSE | R93: FALSE | S93: FALSE | T93: FALSE
M94: =IFERROR(__xludf.DUMMYFUNCTION("IF( K94="""", """", ROUND( IF( L94="""", K94, IF( ISERROR(FIND(""-"",L94)), K94 - VALUE(REGEXEXTRACT(L94,""(\d+)"")), K94 * (1 - VALUE(REGEXEXTRACT(L94,""(\d+)""))/100) ) ), 2 ) ) ")," ") | O94: FALSE | R94: FALSE | S94: FALSE | T94: FALSE
M95: =IFERROR(__xludf.DUMMYFUNCTION("IF( K95="""", """", ROUND( IF( L95="""", K95, IF( ISERROR(FIND(""-"",L95)), K95 - VALUE(REGEXEXTRACT(L95,""(\d+)"")), K95 * (1 - VALUE(REGEXEXTRACT(L95,""(\d+)""))/100) ) ), 2 ) ) ")," ") | O95: FALSE | R95: FALSE | S95: FALSE | T95: FALSE
M96: =IFERROR(__xludf.DUMMYFUNCTION("IF( K96="""", """", ROUND( IF( L96="""", K96, IF( ISERROR(FIND(""-"",L96)), K96 - VALUE(REGEXEXTRACT(L96,""(\d+)"")), K96 * (1 - VALUE(REGEXEXTRACT(L96,""(\d+)""))/100) ) ), 2 ) ) ")," ") | O96: FALSE | R96: FALSE | S96: FALSE | T96: FALSE
M97: =IFERROR(__xludf.DUMMYFUNCTION("IF( K97="""", """", ROUND( IF( L97="""", K97, IF( ISERROR(FIND(""-"",L97)), K97 - VALUE(REGEXEXTRACT(L97,""(\d+)"")), K97 * (1 - VALUE(REGEXEXTRACT(L97,""(\d+)""))/100) ) ), 2 ) ) ")," ") | O97: FALSE | R97: FALSE | S97: FALSE | T97: FALSE
M98: =IFERROR(__xludf.DUMMYFUNCTION("IF( K98="""", """", ROUND( IF( L98="""", K98, IF( ISERROR(FIND(""-"",L98)), K98 - VALUE(REGEXEXTRACT(L98,""(\d+)"")), K98 * (1 - VALUE(REGEXEXTRACT(L98,""(\d+)""))/100) ) ), 2 ) ) ")," ") | O98: FALSE | R98: FALSE | S98: FALSE | T98: FALSE
M99: =IFERROR(__xludf.DUMMYFUNCTION("IF( K99="""", """", ROUND( IF( L99="""", K99, IF( ISERROR(FIND(""-"",L99)), K99 - VALUE(REGEXEXTRACT(L99,""(\d+)"")), K99 * (1 - VALUE(REGEXEXTRACT(L99,""(\d+)""))/100) ) ), 2 ) ) ")," ") | O99: FALSE | R99: FALSE | S99: FALSE | T99: FALSE
M100: =IFERROR(__xludf.DUMMYFUNCTION("IF( K100="""", """", ROUND( IF( L100="""", K100, IF( ISERROR(FIND(""-"",L100)), K100 - VALUE(REGEXEXTRACT(L100,""(\d+)"")), K100 * (1 - VALUE(REGEXEXTRACT(L100,""(\d+)""))/100) ) ), 2 ) )"&" ")," ") | O100: FALSE | R100: FALSE | S100: FALSE | T100: FALSE
...

Sheet WS_EMANUELLO
C1: WS_EMANUEL LO_22FEBB2026
A2: CHI SCRIVE | B2: VENDITA | C2: DATA INSERIMENTO /RICHIESTA | D2: ID ANAGRAFICA | E2: COGNOME | F2: NOME | G2: TELEFONO | H2: CODICE FISCALE | I2: EMAIL | J2: DATA PAGAMENTO /RICEVUTA | K2: QUOTA | L2: CODICE SCONTO | M2: IMPORTO FINALE | N2: DIGIT/CASH - TESS/NON TESS | O2: PRESENZA | P2: NOTE | Q2: INSERITO SU ATHENA | R2: RICEVUTA FATTA | S2: FATTURA FATTA | T2: VERIFICA PAGAMENTO
C3: 14:00-15:45_HIPHOP (€45)
A4: Joel | B4: ONLINE | C4: 46006 | D4: ID-000963 | E4: MICHELI | F4: LINDA | G4: 3317286206 | H4: MCHLND03L41C816Q | I4: lindamicheli@icloud.com | J4: 46006 | K4: 45 | M4: =IFERROR(__xludf.DUMMYFUNCTION("IF( K4="""", """", ROUND( IF( L4="""", K4, IF( ISERROR(FIND(""-"",L4)), K4 - VALUE(REGEXEXTRACT(L4,""(\d+)"")), K4 * (1 - VALUE(REGEXEXTRACT(L4,""(\d+)""))/100) ) ), 2 ) ) "),45.0) -> 45 | N4: DIGIT - TESSERATO | O4: TRUE | Q4: INSERITO | R4: TRUE | S4: FALSE | T4: TRUE
A5: Joel | B5: ONLINE | C5: 46007 | E5: VIGONE | F5: MARTA | G5: 3497294140 | H5: VGNMRT10B41F952L | I5: pasquale.saggiomo90@gmail.com | J5: 46007 | K5: 45 | M5: =IFERROR(__xludf.DUMMYFUNCTION("IF( K5="""", """", ROUND( IF( L5="""", K5, IF( ISERROR(FIND(""-"",L5)), K5 - VALUE(REGEXEXTRACT(L5,""(\d+)"")), K5 * (1 - VALUE(REGEXEXTRACT(L5,""(\d+)""))/100) ) ), 2 ) ) "),45.0) -> 45 | N5: DIGIT - NON TESSERATO | O5: TRUE | Q5: INSERITO | R5: FALSE | S5: TRUE | T5: TRUE
A6: Joel | B6: ONLINE | C6: 46007 | D6: ID-003764 | E6: TORRES GOMEZ | F6: JHISSEL NOHELI | G6: 3801039339 | H6: TRRJSS03H68Z506V | I6: chaveznini26@gmail.com | J6: 46007 | K6: 45 | L6: NURA02WS | M6: =IFERROR(__xludf.DUMMYFUNCTION("IF( K6="""", """", ROUND( IF( L6="""", K6, IF( ISERROR(FIND(""-"",L6)), K6 - VALUE(REGEXEXTRACT(L6,""(\d+)"")), K6 * (1 - VALUE(REGEXEXTRACT(L6,""(\d+)""))/100) ) ), 2 ) ) "),43.0) -> 43 | N6: DIGIT - TESSERATO | O6: TRUE | Q6: INSERITO | R6: TRUE | S6: FALSE | T6: TRUE
A7: Joel | B7: ONLINE | C7: 46008 | D7: ID-000004 | E7: CAMPAGNA | F7: ALESSIO | G7: 3517240804 | H7: CMPLSS98A21H501J | I7: alessiotcgtrade@gmail.com | J7: 46008 | K7: 45 | L7: JOEL02WS | M7: =IFERROR(__xludf.DUMMYFUNCTION("IF( K7="""", """", ROUND( IF( L7="""", K7, IF( ISERROR(FIND(""-"",L7)), K7 - VALUE(REGEXEXTRACT(L7,""(\d+)"")), K7 * (1 - VALUE(REGEXEXTRACT(L7,""(\d+)""))/100) ) ), 2 ) ) "),43.0) -> 43 | N7: DIGIT - TESSERATO | O7: TRUE | Q7: INSERITO | R7: TRUE | S7: FALSE | T7: TRUE
A8: Joel | B8: ONLINE | C8: 46008 | E8: CORBETTA | F8: LUDOVICA | G8: 3498232734 | H8: CRBLVC08R71G388F | I8: roberta.villa@grandi11law.com | J8: 46008 | K8: 45 | L8: NURA02WS | M8: =IFERROR(__xludf.DUMMYFUNCTION("IF( K8="""", """", ROUND( IF( L8="""", K8, IF( ISERROR(FIND(""-"",L8)), K8 - VALUE(REGEXEXTRACT(L8,""(\d+)"")), K8 * (1 - VALUE(REGEXEXTRACT(L8,""(\d+)""))/100) ) ), 2 ) ) "),43.0) -> 43 | N8: DIGIT - NON TESSERATO | O8: TRUE | Q8: INSERITO | R8: FALSE | S8: TRUE | T8: TRUE
A9: Nura | B9: SEDE Nura | C9: 46006 | D9: ID-000301 | E9: CLIMA | F9: ALICE | G9: 3738832549 | H9: CLMLCA04D42F205Q | I9: aliceclima1@gmail.com | J9: 46006 | K9: 45 | L9: NURA02WS | M9: =IFERROR(__xludf.DUMMYFUNCTION("IF( K9="""", """", ROUND( IF( L9="""", K9, IF( ISERROR(FIND(""-"",L9)), K9 - VALUE(REGEXEXTRACT(L9,""(\d+)"")), K9 * (1 - VALUE(REGEXEXTRACT(L9,""(\d+)""))/100) ) ), 2 ) ) "),43.0) -> 43 | N9: DIGIT - TESSERATO | O9: TRUE | Q9: INSERITO | R9: TRUE | S9: FALSE | T9: TRUE
A10: Nura | B10: ONLINE | C10: 46008 | E10: LODATO | F10: REBECCA | G10: 3492394869 | H10: LDTRCC12E64B729I | I10: carolquici@gmail.com | J10: 46013 | K10: 45 | L10: NURA02WS | M10: =IFERROR(__xludf.DUMMYFUNCTION("IF( K10="""", """", ROUND( IF( L10="""", K10, IF( ISERROR(FIND(""-"",L10)), K10 - VALUE(REGEXEXTRACT(L10,""(\d+)"")), K10 * (1 - VALUE(REGEXEXTRACT(L10,""(\d+)""))/100) ) ), 2 ) ) "),43.0) -> 43 | O10: TRUE | P10: su ok gae (b/b) Q.D.A. Quici Dance Art asd Via Milano, 34 - 20835 Muggiò (MB) P.Iva: 07131830965 CF. 94619150157 | R10: FALSE | S10: TRUE | T10: TRUE
A11: Nura | B11: ONLINE | C11: 46008 | E11: MANFREDINI | F11: ILARIA | G11: 3492394869 | H11: MNFLRI12L48F704B | I11: carolquici@gmail.com | J11: 46013 | K11: 45 | L11: NURA02WS | M11: =IFERROR(__xludf.DUMMYFUNCTION("IF( K11="""", """", ROUND( IF( L11="""", K11, IF( ISERROR(FIND(""-"",L11)), K11 - VALUE(REGEXEXTRACT(L11,""(\d+)"")), K11 * (1 - VALUE(REGEXEXTRACT(L11,""(\d+)""))/100) ) ), 2 ) ) "),43.0) -> 43 | O11: TRUE | P11: su ok gae (b/b) | R11: FALSE | S11: TRUE | T11: TRUE
A12: Nura | B12: ONLINE | C12: 46008 | E12: SARTOR | F12: NOEMI | G12: 3492394869 | H12: SRTNMO12B60F704Y | I12: carolquici@gmail.com | J12: 46013 | K12: 45 | L12: NURA02WS | M12: =IFERROR(__xludf.DUMMYFUNCTION("IF( K12="""", """", ROUND( IF( L12="""", K12, IF( ISERROR(FIND(""-"",L12)), K12 - VALUE(REGEXEXTRACT(L12,""(\d+)"")), K12 * (1 - VALUE(REGEXEXTRACT(L12,""(\d+)""))/100) ) ), 2 ) ) "),43.0) -> 43 | O12: TRUE | P12: su ok gae (b/b) | R12: FALSE | S12: TRUE | T12: TRUE
A13: Nura | B13: ONLINE | C13: 46008 | E13: ZAPPAROLI | F13: LARA | G13: 3492394869 | H13: ZPPLRA12H47F205T | I13: carolquici@gmail.com | J13: 46013 | K13: 45 | L13: NURA02WS | M13: =IFERROR(__xludf.DUMMYFUNCTION("IF( K13="""", """", ROUND( IF( L13="""", K13, IF( ISERROR(FIND(""-"",L13)), K13 - VALUE(REGEXEXTRACT(L13,""(\d+)"")), K13 * (1 - VALUE(REGEXEXTRACT(L13,""(\d+)""))/100) ) ), 2 ) ) "),43.0) -> 43 | O13: TRUE | P13: su ok gae (b/b) | R13: FALSE | S13: TRUE | T13: TRUE
A14: Nura | B14: ONLINE | C14: 46008 | E14: FACCOLI | F14: ROSSELLA | G14: 3492394869 | H14: FCCRSL12M54F205N | I14: carolquici@gmail.com | J14: 46013 | K14: 45 | L14: NURA02WS | M14: =IFERROR(__xludf.DUMMYFUNCTION("IF( K14="""", """", ROUND( IF( L14="""", K14, IF( ISERROR(FIND(""-"",L14)), K14 - VALUE(REGEXEXTRACT(L14,""(\d+)"")), K14 * (1 - VALUE(REGEXEXTRACT(L14,""(\d+)""))/100) ) ), 2 ) ) "),43.0) -> 43 | O14: TRUE | P14: su ok gae (b/b) | R14: FALSE | S14: TRUE | T14: TRUE
A15: Nura | B15: ONLINE | C15: 46008 | E15: GENITONI | F15: SOFIA | G15: 3492394869 | H15: GNTSF013S62D286O | I15: carolquici@gmail.com | J15: 46013 | K15: 45 | L15: NURA02WS | M15: =IFERROR(__xludf.DUMMYFUNCTION("IF( K15="""", """", ROUND( IF( L15="""", K15, IF( ISERROR(FIND(""-"",L15)), K15 - VALUE(REGEXEXTRACT(L15,""(\d+)"")), K15 * (1 - VALUE(REGEXEXTRACT(L15,""(\d+)""))/100) ) ), 2 ) ) "),43.0) -> 43 | O15: TRUE | P15: su ok gae (b/b) | R15: FALSE | S15: TRUE | T15: TRUE
A16: Nura | B16: ONLINE | C16: 46008 | E16: QUICI | F16: CAROLINA | G16: 3492394869 | H16: QCUCLN79R46I690Z | I16: carolquici@gmail.com | J16: 46013 | K16: 45 | L16: NURA02WS | M16: =IFERROR(__xludf.DUMMYFUNCTION("IF( K16="""", """", ROUND( IF( L16="""", K16, IF( ISERROR(FIND(""-"",L16)), K16 - VALUE(REGEXEXTRACT(L16,""(\d+)"")), K16 * (1 - VALUE(REGEXEXTRACT(L16,""(\d+)""))/100) ) ), 2 ) ) "),43.0) -> 43 | O16: TRUE | P16: su ok gae (b/b) | R16: FALSE | S16: TRUE | T16: TRUE
A17: Joel | B17: ONLINE | C17: 46008 | D17: ID-000594 | E17: MAIORINO | F17: MARTINA | G17: 3883659924 | H17: MRNMTN98E57F205V | I17: martilove17@live.it | J17: 46008 | K17: 45 | L17: NURA02WS | M17: =IFERROR(__xludf.DUMMYFUNCTION("IF( K17="""", """", ROUND( IF( L17="""", K17, IF( ISERROR(FIND(""-"",L17)), K17 - VALUE(REGEXEXTRACT(L17,""(\d+)"")), K17 * (1 - VALUE(REGEXEXTRACT(L17,""(\d+)""))/100) ) ), 2 ) ) "),43.0) -> 43 | N17: DIGIT - TESSERATO | O17: TRUE | Q17: INSERITO | R17: TRUE | S17: FALSE | T17: TRUE
A18: Joel | B18: ONLINE | C18: 46009 | D18: ID-000738 | E18: COLLARILE | F18: ILEANA | G18: 3471193300 | H18: CLLLNI81D42F205O | I18: ilecolla@hotmail.com | J18: 46009 | K18: 45 | L18: NURA02WS | M18: =IFERROR(__xludf.DUMMYFUNCTION("IF( K18="""", """", ROUND( IF( L18="""", K18, IF( ISERROR(FIND(""-"",L18)), K18 - VALUE(REGEXEXTRACT(L18,""(\d+)"")), K18 * (1 - VALUE(REGEXEXTRACT(L18,""(\d+)""))/100) ) ), 2 ) ) "),43.0) -> 43 | N18: DIGIT - TESSERATO | O18: TRUE | P18: pagato per Caiola Marisol | Q18: INSERITO | R18: TRUE | S18: FALSE | T18: TRUE
A19: Joel | B19: ONLINE | C19: 46012 | E19: SISTI | F19: SARA ARIEL | G19: 3890786108 | H19: SSTSRL10D56E801B | I19: valsecchiarianna74@gmail.com | J19: 46012 | K19: 45 | M19: =IFERROR(__xludf.DUMMYFUNCTION("IF( K19="""", """", ROUND( IF( L19="""", K19, IF( ISERROR(FIND(""-"",L19)), K19 - VALUE(REGEXEXTRACT(L19,""(\d+)"")), K19 * (1 - VALUE(REGEXEXTRACT(L19,""(\d+)""))/100) ) ), 2 ) ) "),45.0) -> 45 | N19: DIGIT - NON TESSERATO | O19: TRUE | P19: ha pagato la mamma Arianna Valsecchi | Q19: INSERITO | R19: FALSE | S19: TRUE | T19: TRUE
A20: Joel | B20: ONLINE | C20: 46012 | E20: DORIA | F20: MELISSA | G20: 3460474709 | H20: DROMSS98A48F205X | I20: melissa.doria98@gmail.com | J20: 46012 | K20: 45 | M20: =IFERROR(__xludf.DUMMYFUNCTION("IF( K20="""", """", ROUND( IF( L20="""", K20, IF( ISERROR(FIND(""-"",L20)), K20 - VALUE(REGEXEXTRACT(L20,""(\d+)"")), K20 * (1 - VALUE(REGEXEXTRACT(L20,""(\d+)""))/100) ) ), 2 ) ) "),45.0) -> 45 | N20: DIGIT - NON TESSERATO | O20: TRUE | Q20: INSERITO | R20: FALSE | S20: TRUE | T20: TRUE
A21: Joel | B21: ONLINE | C21: 46013 | E21: KOSTANECKA | F21: ALEKSANDRA | G21: 3478569980 | H21: KSTLSN05A68Z127Q | I21: ola.kostanecka2005@gmail.com | J21: 46013 | K21: 45 | M21: =IFERROR(__xludf.DUMMYFUNCTION("IF( K21="""", """", ROUND( IF( L21="""", K21, IF( ISERROR(FIND(""-"",L21)), K21 - VALUE(REGEXEXTRACT(L21,""(\d+)"")), K21 * (1 - VALUE(REGEXEXTRACT(L21,""(\d+)""))/100) ) ), 2 ) ) "),45.0) -> 45 | N21: DIGIT - NON TESSERATO | O21: TRUE | Q21: INSERITO | R21: FALSE | S21: TRUE | T21: TRUE
A22: Joel | B22: ONLINE | C22: 46013 | E22: FONTANA | F22: ANNA | G22: 3468321647 | H22: FNTNNA12A49C638K | I22: voltolina.valentina@gmail.com | J22: 46013 | K22: 45 | M22: =IFERROR(__xludf.DUMMYFUNCTION("IF( K22="""", """", ROUND( IF( L22="""", K22, IF( ISERROR(FIND(""-"",L22)), K22 - VALUE(REGEXEXTRACT(L22,""(\d+)"")), K22 * (1 - VALUE(REGEXEXTRACT(L22,""(\d+)""))/100) ) ), 2 ) ) "),45.0) -> 45 | N22: DIGIT - NON TESSERATO | O22: TRUE | P22: ha pagato la mamma Voltolina Valentina | Q22: INSERITO | R22: FALSE | S22: TRUE | T22: TRUE
M23: =IFERROR(__xludf.DUMMYFUNCTION("IF( K23="""", """", ROUND( IF( L23="""", K23, IF( ISERROR(FIND(""-"",L23)), K23 - VALUE(REGEXEXTRACT(L23,""(\d+)"")), K23 * (1 - VALUE(REGEXEXTRACT(L23,""(\d+)""))/100) ) ), 2 ) ) ")," ") | O23: FALSE | S23: FALSE | T23: FALSE
A24: Joel | B24: ONLINE | C24: 46014 | E24: CREDENDINO | F24: MARIA ROSARIA | G24: 3294923016 | H24: CRDMRS91T41A024P | I24: credendinomaria.rosaria@gmail.com | J24: 46014 | K24: 45 | L24: NURA02WS | M24: =IFERROR(__xludf.DUMMYFUNCTION("IF( K24="""", """", ROUND( IF( L24="""", K24, IF( ISERROR(FIND(""-"",L24)), K24 - VALUE(REGEXEXTRACT(L24,""(\d+)"")), K24 * (1 - VALUE(REGEXEXTRACT(L24,""(\d+)""))/100) ) ), 2 ) ) "),43.0) -> 43 | N24: DIGIT - NON TESSERATO | O24: TRUE | Q24: INSERITO | R24: FALSE | S24: TRUE | T24: TRUE
A25: Joel | B25: ONLINE | C25: 46015 | E25: FUSCO | F25: ARIANNA DERIS | G25: 3469611413 | H25: FSCRND03A52F205K | I25: francesco.fusco18@icloud.com | J25: 46015 | K25: 45 | M25: =IFERROR(__xludf.DUMMYFUNCTION("IF( K25="""", """", ROUND( IF( L25="""", K25, IF( ISERROR(FIND(""-"",L25)), K25 - VALUE(REGEXEXTRACT(L25,""(\d+)"")), K25 * (1 - VALUE(REGEXEXTRACT(L25,""(\d+)""))/100) ) ), 2 ) ) "),45.0) -> 45 | N25: DIGIT - NON TESSERATO | O25: TRUE | Q25: INSERITO | R25: FALSE | S25: TRUE | T25: TRUE
A26: Joel | B26: ONLINE | C26: 46015 | E26: PONZI | F26: RACHELE | G26: 3407521135 | H26: PNZRHL08A48G337U | I26: adele.giovannetti.77@gmail.com | J26: 46015 | K26: 45 | L26: NURA02WS | M26: =IFERROR(__xludf.DUMMYFUNCTION("IF( K26="""", """", ROUND( IF( L26="""", K26, IF( ISERROR(FIND(""-"",L26)), K26 - VALUE(REGEXEXTRACT(L26,""(\d+)"")), K26 * (1 - VALUE(REGEXEXTRACT(L26,""(\d+)""))/100) ) ), 2 ) ) "),43.0) -> 43 | N26: DIGIT - NON TESSERATO | O26: FALSE | P26: NON puo' partecipare mail inviata dicendo di comunicare per un altra perona | Q26: INSERITO | R26: FALSE | S26: TRUE | T26: TRUE
A27: Joel | B27: ONLINE | C27: 46015 | E27: CAMERA | F27: REBECCA | G27: 3389178026 | H27: CMRRCC11S46G337K | I27: cameraraffaele.cr75@gmail.com | J27: 46015 | K27: 45 | M27: =IFERROR(__xludf.DUMMYFUNCTION("IF( K27="""", """", ROUND( IF( L27="""", K27, IF( ISERROR(FIND(""-"",L27)), K27 - VALUE(REGEXEXTRACT(L27,""(\d+)"")), K27 * (1 - VALUE(REGEXEXTRACT(L27,""(\d+)""))/100) ) ), 2 ) ) "),45.0) -> 45 | N27: DIGIT - NON TESSERATO | O27: TRUE | Q27: INSERITO | R27: FALSE | S27: TRUE | T27: TRUE
A28: Joel | B28: ONLINE | C28: 46017 | E28: FARANO | F28: MARGHERITA | G28: 3738730275 | H28: mail inviata | I28: margherita.farano@gmail.com | J28: 46017 | K28: 45 | M28: =IFERROR(__xludf.DUMMYFUNCTION("IF( K28="""", """", ROUND( IF( L28="""", K28, IF( ISERROR(FIND(""-"",L28)), K28 - VALUE(REGEXEXTRACT(L28,""(\d+)"")), K28 * (1 - VALUE(REGEXEXTRACT(L28,""(\d+)""))/100) ) ), 2 ) ) "),45.0) -> 45 | N28: DIGIT - NON TESSERATO | O28: TRUE | Q28: INSERITO | R28: FALSE | S28: TRUE | T28: TRUE
A29: Joel | B29: ONLINE | C29: 46017 | E29: LUPO | F29: VALENTINA | G29: 3470685410 | H29: LPUVNT01M52C933C | I29: lupo_valentina@outlook.it | J29: 46017 | K29: 45 | M29: =IFERROR(__xludf.DUMMYFUNCTION("IF( K29="""", """", ROUND( IF( L29="""", K29, IF( ISERROR(FIND(""-"",L29)), K29 - VALUE(REGEXEXTRACT(L29,""(\d+)"")), K29 * (1 - VALUE(REGEXEXTRACT(L29,""(\d+)""))/100) ) ), 2 ) ) "),45.0) -> 45 | N29: DIGIT - NON TESSERATO | O29: TRUE | Q29: INSERITO | R29: FALSE | S29: TRUE | T29: TRUE
A30: Joel | B30: ONLINE | C30: 46018 | E30: RANIERI | F30: REBECCA | G30: 3668728379 | H30: RNRRCC07B53G337C | I30: RANIERI.REBECCA.2007@GMAIL.COM | J30: 46018 | K30: 45 | L30: NURA02WS | M30: =IFERROR(__xludf.DUMMYFUNCTION("IF( K30="""", """", ROUND( IF( L30="""", K30, IF( ISERROR(FIND(""-"",L30)), K30 - VALUE(REGEXEXTRACT(L30,""(\d+)"")), K30 * (1 - VALUE(REGEXEXTRACT(L30,""(\d+)""))/100) ) ), 2 ) ) "),43.0) -> 43 | N30: DIGIT - NON TESSERATO | O30: TRUE | Q30: INSERITO | R30: FALSE | S30: TRUE | T30: TRUE
A31: Joel | B31: ONLINE | C31: 46019 | E31: COLOSIMO | F31: ALESSIA | G31: 3314597068 | H31: CLSLSS05S43D912Y | I31: alessiacolosimo8@gmail.com | J31: 46019 | K31: 45 | M31: =IFERROR(__xludf.DUMMYFUNCTION("IF( K31="""", """", ROUND( IF( L31="""", K31, IF( ISERROR(FIND(""-"",L31)), K31 - VALUE(REGEXEXTRACT(L31,""(\d+)"")), K31 * (1 - VALUE(REGEXEXTRACT(L31,""(\d+)""))/100) ) ), 2 ) ) "),45.0) -> 45 | N31: DIGIT - NON TESSERATO | O31: TRUE | Q31: INSERITO | R31: FALSE | S31: TRUE | T31: TRUE
A32: Joel | B32: ONLINE | C32: 46019 | E32: VATALARO | F32: AURORA | G32: 41782030722 | H32: VTLRRA10D62Z133H | I32: vatalaroaurora22@gmail.com | J32: 46019 | K32: 45 | M32: =IFERROR(__xludf.DUMMYFUNCTION("IF( K32="""", """", ROUND( IF( L32="""", K32, IF( ISERROR(FIND(""-"",L32)), K32 - VALUE(REGEXEXTRACT(L32,""(\d+)"")), K32 * (1 - VALUE(REGEXEXTRACT(L32,""(\d+)""))/100) ) ), 2 ) ) "),45.0) -> 45 | N32: DIGIT - NON TESSERATO | O32: TRUE | R32: FALSE | S32: TRUE | T32: TRUE
A33: Joel | B33: ONLINE | C33: 46020 | E33: COVI | F33: ELETTRA | G33: 3404751247 | H33: CVOLTR12H64E648Z | I33: karinborromeo@gmail.com | J33: 46020 | K33: 45 | M33: =IFERROR(__xludf.DUMMYFUNCTION("IF( K33="""", """", ROUND( IF( L33="""", K33, IF( ISERROR(FIND(""-"",L33)), K33 - VALUE(REGEXEXTRACT(L33,""(\d+)"")), K33 * (1 - VALUE(REGEXEXTRACT(L33,""(\d+)""))/100) ) ), 2 ) ) "),45.0) -> 45 | N33: DIGIT - NON TESSERATO | O33: TRUE | Q33: INSERITO | R33: FALSE | S33: TRUE | T33: TRUE
A34: Joel | B34: ONLINE | C34: 46020 | E34: CHIAPPONI | F34: JENNIFER | G34: 3779585466 | H34: CHPJNF12A55G337Z | I34: alineparma84@gmail.com | J34: 46020 | K34: 45 | M34: =IFERROR(__xludf.DUMMYFUNCTION("IF( K34="""", """", ROUND( IF( L34="""", K34, IF( ISERROR(FIND(""-"",L34)), K34 - VALUE(REGEXEXTRACT(L34,""(\d+)"")), K34 * (1 - VALUE(REGEXEXTRACT(L34,""(\d+)""))/100) ) ), 2 ) ) "),45.0) -> 45 | N34: DIGIT - NON TESSERATO | O34: TRUE | P34: HA PAGATO ALINE RODRIGUES | Q34: INSERITO | R34: FALSE | S34: TRUE | T34: TRUE
A35: Estefany | B35: ONLINE | C35: 46028 | E35: RICCIALDI | F35: TANIA | G35: 3920434044 | H35: DGRLXA06L11L219D | I35: triccialdi@gmail.com | J35: 46028 | K35: 45 | M35: =IFERROR(__xludf.DUMMYFUNCTION("IF( K35="""", """", ROUND( IF( L35="""", K35, IF( ISERROR(FIND(""-"",L35)), K35 - VALUE(REGEXEXTRACT(L35,""(\d+)"")), K35 * (1 - VALUE(REGEXEXTRACT(L35,""(\d+)""))/100) ) ), 2 ) ) "),45.0) -> 45 | N35: DIGIT - NON TESSERATO | O35: FALSE | Q35: INSERITO | R35: FALSE | S35: TRUE | T35: TRUE
A36: Joel | B36: ONLINE | C36: 46022 | E36: COLOMBO | F36: ANGELICA | G36: 3489301939 | H36: CLMNLC12R41D869M | I36: robysax77@yahoo.it | J36: 46022 | K36: 45 | L36: ALEXANDRA02WS | M36: =IFERROR(__xludf.DUMMYFUNCTION("IF( K36="""", """", ROUND( IF( L36="""", K36, IF( ISERROR(FIND(""-"",L36)), K36 - VALUE(REGEXEXTRACT(L36,""(\d+)"")), K36 * (1 - VALUE(REGEXEXTRACT(L36,""(\d+)""))/100) ) ), 2 ) ) "),43.0) -> 43 | N36: DIGIT - NON TESSERATO | O36: FALSE | Q36: INSERITO | R36: FALSE | S36: TRUE | T36: TRUE
A37: Joel | B37: ONLINE | C37: 46024 | E37: LO FURNO | F37: ELENA | G37: 3342159289 | H37: LFRLNE91H56E063Z | I37: lofurnoelena@gmail.com | J37: 46024 | K37: 45 | L37: NURA02WS | M37: =IFERROR(__xludf.DUMMYFUNCTION("IF( K37="""", """", ROUND( IF( L37="""", K37, IF( ISERROR(FIND(""-"",L37)), K37 - VALUE(REGEXEXTRACT(L37,""(\d+)"")), K37 * (1 - VALUE(REGEXEXTRACT(L37,""(\d+)""))/100) ) ), 2 ) ) "),43.0) -> 43 | N37: DIGIT - NON TESSERATO | O37: TRUE | Q37: INSERITO | R37: FALSE | S37: TRUE | T37: TRUE
